Workbook

Sheet Instructions
A9: How to fill in your Business Cashbook
A11: Columns:
A13: Column A | B13: In Column A enter the date of each transaction from the bank statement
A15: Column B | B15: Code - the codes at the top of the Income & Expense columns are Account Analysis codes.
B17: Enter the code number of the column the transaction is for (e.g. Bank Fees is code 710)
A19: Column C | B19: Detail - write the particulars of the transaction, e.g. the client name for income
A21: Column D | B21: Cashbook Balance - this column calculates itself, do not type in it
A23: Column E | B23: Ref. - the cheque number or the transaction's reference
A25: Column G | B25: Bank - the amount of the transaction: income is positive, an expense is negative ( - )
A27: Column H/I | B27: GST Income/Expense - calculated from the bank amount; leave blank where there is no GST,
B29: e.g. interest, bank fees, shareholder contributions and offshore subscriptions
A31: Row 108 | B31: Bank Balance - the closing balance shown on your bank statement.
A33: Row 110 | B33: Unpresented deposits - deposits not yet on the bank statement.
A35: Row 113 | B35: Unpresented cheques - payments not yet on the bank statement.
A74: SYNTHETIC TEST DATA - NOT A REAL STATEMENT

Sheet Cashbook
A1: Company Name: TUATARA LANE CONSULTING LIMITED
A3: Cashbook for period ending 31/03/2027 | K3: * | S3: *
J4: 707 | K4: 706 | L4: 703 | M4: 704 | N4: 709 | O4: 738 | P4: 739 | Q4: 714 | R4: 710 | S4: 711 | T4: 712 | U4: 713 | V4: 715 | W4: 724 | X4: 725 | Y4: 726 | Z4: 727 | AA4: 728 | AB4: 729 | AC4: 730 | AD4: 732 | AE4: 733 | AF4: 734 | AG4: 735
A5: Date | B5: Code | C5: Detail | D5: C/Book Balance | E5: Ref | G5: Bank | H5: GST Income | I5: GST Expense | J5: Income | K5: S/Holder Contribution | N5: Purchases | O5: ACC Levy | P5: No GST Purchases (online tech. subscriptions) | Q5: Interest | R5: Bank Fees | S5: Accountancy | T5: Legal Fees | U5: Vehicle Expenses | V5: Postage & Stationery | W5: Apartment Rent | X5: Power | Y5: Entertaintment | Z5: Internet | AA5: Mobile Plan - Tui Mobile | AB5: Car Parking | AC5: Contents Insurance | AD5: Indemnity Insurance | AE5: Fakeville Council Rates/Body Corp Fees | AF5: Home Office Expenses
K6: =IF($B6=706,SUM($G6-(SUM($H6:$I6))),"") | L6: =IF($B6=703,SUM($G6-(SUM($H6:$I6))),"") | M6: =IF($B6=704,SUM($G6-(SUM($H6:$I6))),"") | N6: =IF($B6=709,SUM($G6-(SUM($H6:$I6))),"") | O6: =IF($B6=738,SUM($G6-(SUM($H6:$I6))),"") | P6: =IF($B6=739,SUM($G6-(SUM($H6:$I6))),"") | Q6: =IF($B6=714,SUM($G6-(SUM($H6:$I6))),"") | R6: =IF($B6=710,SUM($G6-(SUM($H6:$I6))),"") | S6: =IF($B6=711,SUM($G6-(SUM($H6:$I6))),"") | T6: =IF($B6=712,SUM($G6-(SUM($H6:$I6))),"") | U6: =IF($B6=713,SUM($G6-(SUM($H6:$I6))),"") | V6: =IF($B6=715,SUM($G6-(SUM($H6:$I6))),"") | W6: =IF($B6=724,SUM($G6-(SUM($H6:$I6))),"") | X6: =IF($B6=725,SUM($G6-(SUM($H6:$I6))),"") | Y6: =IF($B6=726,SUM($G6-(SUM($H6:$I6))),"") | Z6: =IF($B6=727,SUM($G6-(SUM($H6:$I6))),"") | AA6: =IF($B6=728,SUM($G6-(SUM($H6:$I6))),"") | AB6: =IF($B6=729,SUM($G6-(SUM($H6:$I6))),"") | AC6: =IF($B6=730,SUM($G6-(SUM($H6:$I6))),"") | AD6: =IF($B6=732,SUM($G6-(SUM($H6:$I6))),"") | AE6: =IF($B6=733,SUM($G6-(SUM($H6:$I6))),"") | AF6: =IF($B6=734,SUM($G6-(SUM($H6:$I6))),"") | AG6: =IF($B6=705,SUM($G6-(SUM($H6:$I6))),"") | AH6: =IF($B6=735,SUM($G6-(SUM($H6:$I6))),"") | AI6: =IF($B6=736,SUM($G6-(SUM($H6:$I6))),"") | AJ6: =IF($B6=737,SUM($G6-(SUM($H6:$I6))),"") | AK6: =IF($B6=725,SUM($G6-(SUM($H6:$I6))),"") | AL6: =IF($B6=735,SUM($G6-(SUM($H6:$I6))),"") | AM6: =IF($B6=727,SUM($G6-(SUM($H6:$I6))),"") | AN6: =IF($B6=718,SUM($G6-(SUM($H6:$I6))),"") | AO6: =IF($B6=719,SUM($G6-(SUM($H6:$I6))),"") | AP6: =IF($B6=717,SUM($G6-(SUM($H6:$I6))),"") | AQ6: =IF($B6=722,SUM($G6-(SUM($H6:$I6))),"") | AR6: =IF($B6=708,SUM($G6-(SUM($H6:$I6))),"") | AS6: =IF($B6=701,SUM($G6-(SUM($H6:$I6))),"") | AT6: =IF($B6=702,SUM($G6-(SUM($H6:$I6))),"") | AU6: =IF($B6=731,SUM($G6-(SUM($H6:$I6))),"") | AV6: =IF($B6=730,SUM($G6-(SUM($H6:$I6))),"")
B7: 707 | C7: Income - October - Client (50% progress payment received) | D7: =D6+G7 -> 0 | F7: =SUM(H7:AV7)-G7 -> 0 | G7: 0 | H7: =IF(G7/23*3>0,SUM(G7/23*3),"") | I7: =IF(G7/23*3<0,SUM(G7/23*3),"") | J7: =IF($B7=707,SUM($G7-(SUM($H7:$I7))),"") -> 0 | K7: =IF($B7=706,SUM($G7-(SUM($H7:$I7))),"") | L7: =IF($B7=703,SUM($G7-(SUM($H7:$I7))),"") | M7: =IF($B7=704,SUM($G7-(SUM($H7:$I7))),"") | N7: =IF($B7=709,SUM($G7-(SUM($H7:$I7))),"") | O7: =IF($B7=738,SUM($G7-(SUM($H7:$I7))),"") | P7: =IF($B7=739,SUM($G7-(SUM($H7:$I7))),"") | Q7: =IF($B7=714,SUM($G7-(SUM($H7:$I7))),"") | R7: =IF($B7=710,SUM($G7-(SUM($H7:$I7))),"") | S7: =IF($B7=711,SUM($G7-(SUM($H7:$I7))),"") | T7: =IF($B7=712,SUM($G7-(SUM($H7:$I7))),"") | U7: =IF($B7=713,SUM($G7-(SUM($H7:$I7))),"") | V7: =IF($B7=715,SUM($G7-(SUM($H7:$I7))),"") | W7: =IF($B7=724,SUM($G7-(SUM($H7:$I7))),"") | X7: =IF($B7=725,SUM($G7-(SUM($H7:$I7))),"") | Y7: =IF($B7=726,SUM($G7-(SUM($H7:$I7))),"") | Z7: =IF($B7=727,SUM($G7-(SUM($H7:$I7))),"") | AA7: =IF($B7=728,SUM($G7-(SUM($H7:$I7))),"") | AB7: =IF($B7=729,SUM($G7-(SUM($H7:$I7))),"") | AC7: =IF($B7=730,SUM($G7-(SUM($H7:$I7))),"") | AD7: =IF($B7=732,SUM($G7-(SUM($H7:$I7))),"") | AE7: =IF($B7=733,SUM($G7-(SUM($H7:$I7))),"") | AF7: =IF($B7=734,SUM($G7-(SUM($H7:$I7))),"") | AG7: =IF($B7=705,SUM($G7-(SUM($H7:$I7))),"") | AH7: =IF($B7=735,SUM($G7-(SUM($H7:$I7))),"") | AI7: =IF($B7=736,SUM($G7-(SUM($H7:$I7))),"") | AJ7: =IF($B7=737,SUM($G7-(SUM($H7:$I7))),"") | AK7: =IF($B7=725,SUM($G7-(SUM($H7:$I7))),"") | AL7: =IF($B7=735,SUM($G7-(SUM($H7:$I7))),"") | AM7: =IF($B7=727,SUM($G7-(SUM($H7:$I7))),"") | AN7: =IF($B7=718,SUM($G7-(SUM($H7:$I7))),"") | AO7: =IF($B7=719,SUM($G7-(SUM($H7:$I7))),"") | AP7: =IF($B7=717,SUM($G7-(SUM($H7:$I7))),"") | AQ7: =IF($B7=722,SUM($G7-(SUM($H7:$I7))),"") | AR7: =IF($B7=708,SUM($G7-(SUM($H7:$I7))),"") | AS7: =IF($B7=701,SUM($G7-(SUM($H7:$I7))),"") | AT7: =IF($B7=702,SUM($G7-(SUM($H7:$I7))),"") | AU7: =IF($B7=731,SUM($G7-(SUM($H7:$I7))),"") | AV7: =IF($B7=730,SUM($G7-(SUM($H7:$I7))),"")
B8: 725 | C8: Power - Fibrewave | D8: =D7+G8 -> 0 | F8: =SUM(H8:AV8)-G8 -> 0 | G8: 0 | H8: =IF(G8/23*3>0,SUM(G8/23*3),"") | I8: =IF(G8/23*3<0,SUM(G8/23*3),"") | J8: =IF($B8=707,SUM($G8-(SUM($H8:$I8))),"") | K8: =IF($B8=706,SUM($G8-(SUM($H8:$I8))),"") | L8: =IF($B8=703,SUM($G8-(SUM($H8:$I8))),"") | M8: =IF($B8=704,SUM($G8-(SUM($H8:$I8))),"") | N8: =IF($B8=709,SUM($G8-(SUM($H8:$I8))),"") | O8: =IF($B8=738,SUM($G8-(SUM($H8:$I8))),"") | P8: =IF($B8=739,SUM($G8-(SUM($H8:$I8))),"") | Q8: =IF($B8=714,SUM($G8-(SUM($H8:$I8))),"") | R8: =IF($B8=710,SUM($G8-(SUM($H8:$I8))),"") | S8: =IF($B8=711,SUM($G8-(SUM($H8:$I8))),"") | T8: =IF($B8=712,SUM($G8-(SUM($H8:$I8))),"") | U8: =IF($B8=713,SUM($G8-(SUM($H8:$I8))),"") | V8: =IF($B8=715,SUM($G8-(SUM($H8:$I8))),"") | W8: =IF($B8=724,SUM($G8-(SUM($H8:$I8))),"") | X8: =IF($B8=725,SUM($G8-(SUM($H8:$I8))),"") -> 0 | Y8: =IF($B8=726,SUM($G8-(SUM($H8:$I8))),"") | Z8: =IF($B8=727,SUM($G8-(SUM($H8:$I8))),"") | AA8: =IF($B8=728,SUM($G8-(SUM($H8:$I8))),"") | AB8: =IF($B8=729,SUM($G8-(SUM($H8:$I8))),"") | AC8: =IF($B8=730,SUM($G8-(SUM($H8:$I8))),"") | AD8: =IF($B8=732,SUM($G8-(SUM($H8:$I8))),"") | AE8: =IF($B8=733,SUM($G8-(SUM($H8:$I8))),"") | AF8: =IF($B8=734,SUM($G8-(SUM($H8:$I8))),"") | AG8: =IF($B8=705,SUM($G8-(SUM($H8:$I8))),"") | AH8: =IF($B8=735,SUM($G8-(SUM($H8:$I8))),"") | AI8: =IF($B8=736,SUM($G8-(SUM($H8:$I8))),"") | AJ8: =IF($B8=737,SUM($G8-(SUM($H8:$I8))),"") | AK8: =IF($B8=725,SUM($G8-(SUM($H8:$I8))),"") -> 0 | AL8: =IF($B8=735,SUM($G8-(SUM($H8:$I8))),"") | AM8: =IF($B8=727,SUM($G8-(SUM($H8:$I8))),"") | AN8: =IF($B8=718,SUM($G8-(SUM($H8:$I8))),"") | AO8: =IF($B8=719,SUM($G8-(SUM($H8:$I8))),"") | AP8: =IF($B8=717,SUM($G8-(SUM($H8:$I8))),"") | AQ8: =IF($B8=722,SUM($G8-(SUM($H8:$I8))),"") | AR8: =IF($B8=708,SUM($G8-(SUM($H8:$I8))),"") | AS8: =IF($B8=701,SUM($G8-(SUM($H8:$I8))),"") | AT8: =IF($B8=702,SUM($G8-(SUM($H8:$I8))),"") | AU8: =IF($B8=731,SUM($G8-(SUM($H8:$I8))),"") | AV8: =IF($B8=730,SUM($G8-(SUM($H8:$I8))),"")
B9: 726 | C9: Entertainment (Business Lunch/Coffee/Meals/Drinks) | D9: =D8+G9 -> 0 | F9: =SUM(H9:AV9)-G9 -> 0 | G9: =-(OtherCalculation!C5) -> 0 | H9: =IF(G9/23*3>0,SUM(G9/23*3),"") | I9: =IF(G9/23*3<0,SUM(G9/23*3),"") | J9: =IF($B9=707,SUM($G9-(SUM($H9:$I9))),"") | K9: =IF($B9=706,SUM($G9-(SUM($H9:$I9))),"") | L9: =IF($B9=703,SUM($G9-(SUM($H9:$I9))),"") | M9: =IF($B9=704,SUM($G9-(SUM($H9:$I9))),"") | N9: =IF($B9=709,SUM($G9-(SUM($H9:$I9))),"") | O9: =IF($B9=738,SUM($G9-(SUM($H9:$I9))),"") | P9: =IF($B9=739,SUM($G9-(SUM($H9:$I9))),"") | Q9: =IF($B9=714,SUM($G9-(SUM($H9:$I9))),"") | R9: =IF($B9=710,SUM($G9-(SUM($H9:$I9))),"") | S9: =IF($B9=711,SUM($G9-(SUM($H9:$I9))),"") | T9: =IF($B9=712,SUM($G9-(SUM($H9:$I9))),"") | U9: =IF($B9=713,SUM($G9-(SUM($H9:$I9))),"") | V9: =IF($B9=715,SUM($G9-(SUM($H9:$I9))),"") | W9: =IF($B9=724,SUM($G9-(SUM($H9:$I9))),"") | X9: =IF($B9=725,SUM($G9-(SUM($H9:$I9))),"") | Y9: =IF($B9=726,SUM($G9-(SUM($H9:$I9))),"") -> 0 | Z9: =IF($B9=727,SUM($G9-(SUM($H9:$I9))),"") | AA9: =IF($B9=728,SUM($G9-(SUM($H9:$I9))),"") | AB9: =IF($B9=729,SUM($G9-(SUM($H9:$I9))),"") | AC9: =IF($B9=730,SUM($G9-(SUM($H9:$I9))),"") | AD9: =IF($B9=732,SUM($G9-(SUM($H9:$I9))),"") | AE9: =IF($B9=733,SUM($G9-(SUM($H9:$I9))),"") | AF9: =IF($B9=734,SUM($G9-(SUM($H9:$I9))),"") | AG9: =IF($B9=705,SUM($G9-(SUM($H9:$I9))),"") | AH9: =IF($B9=735,SUM($G9-(SUM($H9:$I9))),"") | AI9: =IF($B9=736,SUM($G9-(SUM($H9:$I9))),"") | AJ9: =IF($B9=737,SUM($G9-(SUM($H9:$I9))),"") | AK9: =IF($B9=725,SUM($G9-(SUM($H9:$I9))),"") | AL9: =IF($B9=735,SUM($G9-(SUM($H9:$I9))),"") | AM9: =IF($B9=727,SUM($G9-(SUM($H9:$I9))),"") | AN9: =IF($B9=718,SUM($G9-(SUM($H9:$I9))),"") | AO9: =IF($B9=719,SUM($G9-(SUM($H9:$I9))),"") | AP9: =IF($B9=717,SUM($G9-(SUM($H9:$I9))),"") | AQ9: =IF($B9=722,SUM($G9-(SUM($H9:$I9))),"") | AR9: =IF($B9=708,SUM($G9-(SUM($H9:$I9))),"") | AS9: =IF($B9=701,SUM($G9-(SUM($H9:$I9))),"") | AT9: =IF($B9=702,SUM($G9-(SUM($H9:$I9))),"") | AU9: =IF($B9=731,SUM($G9-(SUM($H9:$I9))),"") | AV9: =IF($B9=730,SUM($G9-(SUM($H9:$I9))),"")
B10: 727 | C10: Internet - Fibrewave | D10: =D9+G10 -> 0 | F10: =SUM(H10:AV10)-G10 -> 0 | G10: 0 | H10: =IF(G10/23*3>0,SUM(G10/23*3),"") | I10: =IF(G10/23*3<0,SUM(G10/23*3),"") | J10: =IF($B10=707,SUM($G10-(SUM($H10:$I10))),"") | K10: =IF($B10=706,SUM($G10-(SUM($H10:$I10))),"") | L10: =IF($B10=703,SUM($G10-(SUM($H10:$I10))),"") | M10: =IF($B10=704,SUM($G10-(SUM($H10:$I10))),"") | N10: =IF($B10=709,SUM($G10-(SUM($H10:$I10))),"") | O10: =IF($B10=738,SUM($G10-(SUM($H10:$I10))),"") | P10: =IF($B10=739,SUM($G10-(SUM($H10:$I10))),"") | Q10: =IF($B10=714,SUM($G10-(SUM($H10:$I10))),"") | R10: =IF($B10=710,SUM($G10-(SUM($H10:$I10))),"") | S10: =IF($B10=711,SUM($G10-(SUM($H10:$I10))),"") | T10: =IF($B10=712,SUM($G10-(SUM($H10:$I10))),"") | U10: =IF($B10=713,SUM($G10-(SUM($H10:$I10))),"") | V10: =IF($B10=715,SUM($G10-(SUM($H10:$I10))),"") | W10: =IF($B10=724,SUM($G10-(SUM($H10:$I10))),"") | X10: =IF($B10=725,SUM($G10-(SUM($H10:$I10))),"") | Y10: =IF($B10=726,SUM($G10-(SUM($H10:$I10))),"") | Z10: =IF($B10=727,SUM($G10-(SUM($H10:$I10))),"") -> 0 | AA10: =IF($B10=728,SUM($G10-(SUM($H10:$I10))),"") | AB10: =IF($B10=729,SUM($G10-(SUM($H10:$I10))),"") | AC10: =IF($B10=730,SUM($G10-(SUM($H10:$I10))),"") | AD10: =IF($B10=732,SUM($G10-(SUM($H10:$I10))),"") | AE10: =IF($B10=733,SUM($G10-(SUM($H10:$I10))),"") | AF10: =IF($B10=734,SUM($G10-(SUM($H10:$I10))),"") | AG10: =IF($B10=705,SUM($G10-(SUM($H10:$I10))),"") | AH10: =IF($B10=735,SUM($G10-(SUM($H10:$I10))),"") | AI10: =IF($B10=736,SUM($G10-(SUM($H10:$I10))),"") | AJ10: =IF($B10=737,SUM($G10-(SUM($H10:$I10))),"") | AK10: =IF($B10=725,SUM($G10-(SUM($H10:$I10))),"") | AL10: =IF($B10=735,SUM($G10-(SUM($H10:$I10))),"") | AM10: =IF($B10=727,SUM($G10-(SUM($H10:$I10))),"") -> 0 | AN10: =IF($B10=718,SUM($G10-(SUM($H10:$I10))),"") | AO10: =IF($B10=719,SUM($G10-(SUM($H10:$I10))),"") | AP10: =IF($B10=717,SUM($G10-(SUM($H10:$I10))),"") | AQ10: =IF($B10=722,SUM($G10-(SUM($H10:$I10))),"") | AR10: =IF($B10=708,SUM($G10-(SUM($H10:$I10))),"") | AS10: =IF($B10=701,SUM($G10-(SUM($H10:$I10))),"") | AT10: =IF($B10=702,SUM($G10-(SUM($H10:$I10))),"") | AU10: =IF($B10=731,SUM($G10-(SUM($H10:$I10))),"") | AV10: =IF($B10=730,SUM($G10-(SUM($H10:$I10))),"")
B11: 728 | C11: Mobile Plan - Tui Mobile NZ | D11: =D10+G11 -> 0 | F11: =SUM(H11:AV11)-G11 -> 0 | G11: 0 | H11: =IF(G11/23*3>0,SUM(G11/23*3),"") | I11: =IF(G11/23*3<0,SUM(G11/23*3),"") | J11: =IF($B11=707,SUM($G11-(SUM($H11:$I11))),"") | K11: =IF($B11=706,SUM($G11-(SUM($H11:$I11))),"") | L11: =IF($B11=703,SUM($G11-(SUM($H11:$I11))),"") | M11: =IF($B11=704,SUM($G11-(SUM($H11:$I11))),"") | N11: =IF($B11=709,SUM($G11-(SUM($H11:$I11))),"") | O11: =IF($B11=738,SUM($G11-(SUM($H11:$I11))),"") | P11: =IF($B11=739,SUM($G11-(SUM($H11:$I11))),"") | Q11: =IF($B11=714,SUM($G11-(SUM($H11:$I11))),"") | R11: =IF($B11=710,SUM($G11-(SUM($H11:$I11))),"") | S11: =IF($B11=711,SUM($G11-(SUM($H11:$I11))),"") | T11: =IF($B11=712,SUM($G11-(SUM($H11:$I11))),"") | U11: =IF($B11=713,SUM($G11-(SUM($H11:$I11))),"") | V11: =IF($B11=715,SUM($G11-(SUM($H11:$I11))),"") | W11: =IF($B11=724,SUM($G11-(SUM($H11:$I11))),"") | X11: =IF($B11=725,SUM($G11-(SUM($H11:$I11))),"") | Y11: =IF($B11=726,SUM($G11-(SUM($H11:$I11))),"") | Z11: =IF($B11=727,SUM($G11-(SUM($H11:$I11))),"") | AA11: =IF($B11=728,SUM($G11-(SUM($H11:$I11))),"") -> 0 | AB11: =IF($B11=729,SUM($G11-(SUM($H11:$I11))),"") | AC11: =IF($B11=730,SUM($G11-(SUM($H11:$I11))),"") | AD11: =IF($B11=732,SUM($G11-(SUM($H11:$I11))),"") | AE11: =IF($B11=733,SUM($G11-(SUM($H11:$I11))),"") | AF11: =IF($B11=734,SUM($G11-(SUM($H11:$I11))),"") | AG11: =IF($B11=705,SUM($G11-(SUM($H11:$I11))),"") | AH11: =IF($B11=735,SUM($G11-(SUM($H11:$I11))),"") | AI11: =IF($B11=736,SUM($G11-(SUM($H11:$I11))),"") | AJ11: =IF($B11=737,SUM($G11-(SUM($H11:$I11))),"") | AK11: =IF($B11=725,SUM($G11-(SUM($H11:$I11))),"") | AL11: =IF($B11=735,SUM($G11-(SUM($H11:$I11))),"") | AM11: =IF($B11=727,SUM($G11-(SUM($H11:$I11))),"") | AN11: =IF($B11=718,SUM($G11-(SUM($H11:$I11))),"") | AO11: =IF($B11=719,SUM($G11-(SUM($H11:$I11))),"") | AP11: =IF($B11=717,SUM($G11-(SUM($H11:$I11))),"") | AQ11: =IF($B11=722,SUM($G11-(SUM($H11:$I11))),"") | AR11: =IF($B11=708,SUM($G11-(SUM($H11:$I11))),"") | AS11: =IF($B11=701,SUM($G11-(SUM($H11:$I11))),"") | AT11: =IF($B11=702,SUM($G11-(SUM($H11:$I11))),"") | AU11: =IF($B11=731,SUM($G11-(SUM($H11:$I11))),"") | AV11: =IF($B11=730,SUM($G11-(SUM($H11:$I11))),"")
B12: 729 | C12: Car Park Fees | D12: =D11+G12 -> 0 | F12: =SUM(H12:AV12)-G12 -> 0 | G12: 0 | H12: =IF(G12/23*3>0,SUM(G12/23*3),"") | I12: =IF(G12/23*3<0,SUM(G12/23*3),"") | J12: =IF($B12=707,SUM($G12-(SUM($H12:$I12))),"") | K12: =IF($B12=706,SUM($G12-(SUM($H12:$I12))),"") | L12: =IF($B12=703,SUM($G12-(SUM($H12:$I12))),"") | M12: =IF($B12=704,SUM($G12-(SUM($H12:$I12))),"") | N12: =IF($B12=709,SUM($G12-(SUM($H12:$I12))),"") | O12: =IF($B12=738,SUM($G12-(SUM($H12:$I12))),"") | P12: =IF($B12=739,SUM($G12-(SUM($H12:$I12))),"") | Q12: =IF($B12=714,SUM($G12-(SUM($H12:$I12))),"") | R12: =IF($B12=710,SUM($G12-(SUM($H12:$I12))),"") | S12: =IF($B12=711,SUM($G12-(SUM($H12:$I12))),"") | T12: =IF($B12=712,SUM($G12-(SUM($H12:$I12))),"") | U12: =IF($B12=713,SUM($G12-(SUM($H12:$I12))),"") | V12: =IF($B12=715,SUM($G12-(SUM($H12:$I12))),"") | W12: =IF($B12=724,SUM($G12-(SUM($H12:$I12))),"") | X12: =IF($B12=725,SUM($G12-(SUM($H12:$I12))),"") | Y12: =IF($B12=726,SUM($G12-(SUM($H12:$I12))),"") | Z12: =IF($B12=727,SUM($G12-(SUM($H12:$I12))),"") | AA12: =IF($B12=728,SUM($G12-(SUM($H12:$I12))),"") | AB12: =IF($B12=729,SUM($G12-(SUM($H12:$I12))),"") -> 0 | AC12: =IF($B12=730,SUM($G12-(SUM($H12:$I12))),"") | AD12: =IF($B12=732,SUM($G12-(SUM($H12:$I12))),"") | AE12: =IF($B12=733,SUM($G12-(SUM($H12:$I12))),"") | AF12: =IF($B12=734,SUM($G12-(SUM($H12:$I12))),"") | AG12: =IF($B12=705,SUM($G12-(SUM($H12:$I12))),"") | AH12: =IF($B12=735,SUM($G12-(SUM($H12:$I12))),"") | AI12: =IF($B12=736,SUM($G12-(SUM($H12:$I12))),"") | AJ12: =IF($B12=737,SUM($G12-(SUM($H12:$I12))),"") | AK12: =IF($B12=725,SUM($G12-(SUM($H12:$I12))),"") | AL12: =IF($B12=735,SUM($G12-(SUM($H12:$I12))),"") | AM12: =IF($B12=727,SUM($G12-(SUM($H12:$I12))),"") | AN12: =IF($B12=718,SUM($G12-(SUM($H12:$I12))),"") | AO12: =IF($B12=719,SUM($G12-(SUM($H12:$I12))),"") | AP12: =IF($B12=717,SUM($G12-(SUM($H12:$I12))),"") | AQ12: =IF($B12=722,SUM($G12-(SUM($H12:$I12))),"") | AR12: =IF($B12=708,SUM($G12-(SUM($H12:$I12))),"") | AS12: =IF($B12=701,SUM($G12-(SUM($H12:$I12))),"") | AT12: =IF($B12=702,SUM($G12-(SUM($H12:$I12))),"") | AU12: =IF($B12=731,SUM($G12-(SUM($H12:$I12))),"") | AV12: =IF($B12=730,SUM($G12-(SUM($H12:$I12))),"")
B13: 734 | C13: Home Office Expenses | D13: =D12+G13 -> 0 | F13: =SUM(H13:AV13)-G13 -> 0 | G13: 0 | H13: =IF(G13/23*3>0,SUM(G13/23*3),"") | I13: =IF(G13/23*3<0,SUM(G13/23*3),"") | J13: =IF($B13=707,SUM($G13-(SUM($H13:$I13))),"") | K13: =IF($B13=706,SUM($G13-(SUM($H13:$I13))),"") | L13: =IF($B13=703,SUM($G13-(SUM($H13:$I13))),"") | M13: =IF($B13=704,SUM($G13-(SUM($H13:$I13))),"") | N13: =IF($B13=709,SUM($G13-(SUM($H13:$I13))),"") | O13: =IF($B13=738,SUM($G13-(SUM($H13:$I13))),"") | P13: =IF($B13=739,SUM($G13-(SUM($H13:$I13))),"") | Q13: =IF($B13=714,SUM($G13-(SUM($H13:$I13))),"") | R13: =IF($B13=710,SUM($G13-(SUM($H13:$I13))),"") | S13: =IF($B13=711,SUM($G13-(SUM($H13:$I13))),"") | T13: =IF($B13=712,SUM($G13-(SUM($H13:$I13))),"") | U13: =IF($B13=713,SUM($G13-(SUM($H13:$I13))),"") | V13: =IF($B13=715,SUM($G13-(SUM($H13:$I13))),"") | W13: =IF($B13=724,SUM($G13-(SUM($H13:$I13))),"") | X13: =IF($B13=725,SUM($G13-(SUM($H13:$I13))),"") | Y13: =IF($B13=726,SUM($G13-(SUM($H13:$I13))),"") | Z13: =IF($B13=727,SUM($G13-(SUM($H13:$I13))),"") | AA13: =IF($B13=728,SUM($G13-(SUM($H13:$I13))),"") | AB13: =IF($B13=729,SUM($G13-(SUM($H13:$I13))),"") | AC13: =IF($B13=730,SUM($G13-(SUM($H13:$I13))),"") | AD13: =IF($B13=732,SUM($G13-(SUM($H13:$I13))),"") | AE13: =IF($B13=733,SUM($G13-(SUM($H13:$I13))),"") | AF13: =IF($B13=734,SUM($G13-(SUM($H13:$I13))),"") -> 0 | AG13: =IF($B13=705,SUM($G13-(SUM($H13:$I13))),"") | AH13: =IF($B13=735,SUM($G13-(SUM($H13:$I13))),"") | AI13: =IF($B13=736,SUM($G13-(SUM($H13:$I13))),"") | AJ13: =IF($B13=737,SUM($G13-(SUM($H13:$I13))),"") | AK13: =IF($B13=725,SUM($G13-(SUM($H13:$I13))),"") | AL13: =IF($B13=735,SUM($G13-(SUM($H13:$I13))),"") | AM13: =IF($B13=727,SUM($G13-(SUM($H13:$I13))),"") | AN13: =IF($B13=718,SUM($G13-(SUM($H13:$I13))),"") | AO13: =IF($B13=719,SUM($G13-(SUM($H13:$I13))),"") | AP13: =IF($B13=717,SUM($G13-(SUM($H13:$I13))),"") | AQ13: =IF($B13=722,SUM($G13-(SUM($H13:$I13))),"") | AR13: =IF($B13=708,SUM($G13-(SUM($H13:$I13))),"") | AS13: =IF($B13=701,SUM($G13-(SUM($H13:$I13))),"") | AT13: =IF($B13=702,SUM($G13-(SUM($H13:$I13))),"") | AU13: =IF($B13=731,SUM($G13-(SUM($H13:$I13))),"") | AV13: =IF($B13=730,SUM($G13-(SUM($H13:$I13))),"")
B14: 734 | C14: Home Office Expenses | D14: =D13+G14 -> 0 | F14: =SUM(H14:AV14)-G14 -> 0 | G14: 0 | H14: =IF(G14/23*3>0,SUM(G14/23*3),"") | I14: =IF(G14/23*3<0,SUM(G14/23*3),"") | J14: =IF($B14=707,SUM($G14-(SUM($H14:$I14))),"") | K14: =IF($B14=706,SUM($G14-(SUM($H14:$I14))),"") | L14: =IF($B14=703,SUM($G14-(SUM($H14:$I14))),"") | M14: =IF($B14=704,SUM($G14-(SUM($H14:$I14))),"") | N14: =IF($B14=709,SUM($G14-(SUM($H14:$I14))),"") | O14: =IF($B14=738,SUM($G14-(SUM($H14:$I14))),"") | P14: =IF($B14=739,SUM($G14-(SUM($H14:$I14))),"") | Q14: =IF($B14=714,SUM($G14-(SUM($H14:$I14))),"") | R14: =IF($B14=710,SUM($G14-(SUM($H14:$I14))),"") | S14: =IF($B14=711,SUM($G14-(SUM($H14:$I14))),"") | T14: =IF($B14=712,SUM($G14-(SUM($H14:$I14))),"") | U14: =IF($B14=713,SUM($G14-(SUM($H14:$I14))),"") | V14: =IF($B14=715,SUM($G14-(SUM($H14:$I14))),"") | W14: =IF($B14=724,SUM($G14-(SUM($H14:$I14))),"") | X14: =IF($B14=725,SUM($G14-(SUM($H14:$I14))),"") | Y14: =IF($B14=726,SUM($G14-(SUM($H14:$I14))),"") | Z14: =IF($B14=727,SUM($G14-(SUM($H14:$I14))),"") | AA14: =IF($B14=728,SUM($G14-(SUM($H14:$I14))),"") | AB14: =IF($B14=729,SUM($G14-(SUM($H14:$I14))),"") | AC14: =IF($B14=730,SUM($G14-(SUM($H14:$I14))),"") | AD14: =IF($B14=732,SUM($G14-(SUM($H14:$I14))),"") | AE14: =IF($B14=733,SUM($G14-(SUM($H14:$I14))),"") | AF14: =IF($B14=734,SUM($G14-(SUM($H14:$I14))),"") -> 0 | AG14: =IF($B14=705,SUM($G14-(SUM($H14:$I14))),"") | AH14: =IF($B14=735,SUM($G14-(SUM($H14:$I14))),"") | AI14: =IF($B14=736,SUM($G14-(SUM($H14:$I14))),"") | AJ14: =IF($B14=737,SUM($G14-(SUM($H14:$I14))),"") | AK14: =IF($B14=725,SUM($G14-(SUM($H14:$I14))),"") | AL14: =IF($B14=735,SUM($G14-(SUM($H14:$I14))),"") | AM14: =IF($B14=727,SUM($G14-(SUM($H14:$I14))),"") | AN14: =IF($B14=718,SUM($G14-(SUM($H14:$I14))),"") | AO14: =IF($B14=719,SUM($G14-(SUM($H14:$I14))),"") | AP14: =IF($B14=717,SUM($G14-(SUM($H14:$I14))),"") | AQ14: =IF($B14=722,SUM($G14-(SUM($H14:$I14))),"") | AR14: =IF($B14=708,SUM($G14-(SUM($H14:$I14))),"") | AS14: =IF($B14=701,SUM($G14-(SUM($H14:$I14))),"") | AT14: =IF($B14=702,SUM($G14-(SUM($H14:$I14))),"") | AU14: =IF($B14=731,SUM($G14-(SUM($H14:$I14))),"") | AV14: =IF($B14=730,SUM($G14-(SUM($H14:$I14))),"")
B15: 734 | C15: Home Office Expenses | D15: =D14+G15 -> 0 | F15: =SUM(H15:AV15)-G15 -> 0 | G15: 0 | H15: =IF(G15/23*3>0,SUM(G15/23*3),"") | I15: =IF(G15/23*3<0,SUM(G15/23*3),"") | J15: =IF($B15=707,SUM($G15-(SUM($H15:$I15))),"") | K15: =IF($B15=706,SUM($G15-(SUM($H15:$I15))),"") | L15: =IF($B15=703,SUM($G15-(SUM($H15:$I15))),"") | M15: =IF($B15=704,SUM($G15-(SUM($H15:$I15))),"") | N15: =IF($B15=709,SUM($G15-(SUM($H15:$I15))),"") | O15: =IF($B15=738,SUM($G15-(SUM($H15:$I15))),"") | P15: =IF($B15=739,SUM($G15-(SUM($H15:$I15))),"") | Q15: =IF($B15=714,SUM($G15-(SUM($H15:$I15))),"") | R15: =IF($B15=710,SUM($G15-(SUM($H15:$I15))),"") | S15: =IF($B15=711,SUM($G15-(SUM($H15:$I15))),"") | T15: =IF($B15=712,SUM($G15-(SUM($H15:$I15))),"") | U15: =IF($B15=713,SUM($G15-(SUM($H15:$I15))),"") | V15: =IF($B15=715,SUM($G15-(SUM($H15:$I15))),"") | W15: =IF($B15=724,SUM($G15-(SUM($H15:$I15))),"") | X15: =IF($B15=725,SUM($G15-(SUM($H15:$I15))),"") | Y15: =IF($B15=726,SUM($G15-(SUM($H15:$I15))),"") | Z15: =IF($B15=727,SUM($G15-(SUM($H15:$I15))),"") | AA15: =IF($B15=728,SUM($G15-(SUM($H15:$I15))),"") | AB15: =IF($B15=729,SUM($G15-(SUM($H15:$I15))),"") | AC15: =IF($B15=730,SUM($G15-(SUM($H15:$I15))),"") | AD15: =IF($B15=732,SUM($G15-(SUM($H15:$I15))),"") | AE15: =IF($B15=733,SUM($G15-(SUM($H15:$I15))),"") | AF15: =IF($B15=734,SUM($G15-(SUM($H15:$I15))),"") -> 0 | AG15: =IF($B15=705,SUM($G15-(SUM($H15:$I15))),"") | AH15: =IF($B15=735,SUM($G15-(SUM($H15:$I15))),"") | AI15: =IF($B15=736,SUM($G15-(SUM($H15:$I15))),"") | AJ15: =IF($B15=737,SUM($G15-(SUM($H15:$I15))),"") | AK15: =IF($B15=725,SUM($G15-(SUM($H15:$I15))),"") | AL15: =IF($B15=735,SUM($G15-(SUM($H15:$I15))),"") | AM15: =IF($B15=727,SUM($G15-(SUM($H15:$I15))),"") | AN15: =IF($B15=718,SUM($G15-(SUM($H15:$I15))),"") | AO15: =IF($B15=719,SUM($G15-(SUM($H15:$I15))),"") | AP15: =IF($B15=717,SUM($G15-(SUM($H15:$I15))),"") | AQ15: =IF($B15=722,SUM($G15-(SUM($H15:$I15))),"") | AR15: =IF($B15=708,SUM($G15-(SUM($H15:$I15))),"") | AS15: =IF($B15=701,SUM($G15-(SUM($H15:$I15))),"") | AT15: =IF($B15=702,SUM($G15-(SUM($H15:$I15))),"") | AU15: =IF($B15=731,SUM($G15-(SUM($H15:$I15))),"") | AV15: =IF($B15=730,SUM($G15-(SUM($H15:$I15))),"")
B16: 724 | C16: Apartment Rent | D16: =D15+G16 -> 0 | F16: =SUM(H16:AV16)-G16 -> 0 | G16: 0 | H16: =IF(G16/23*3>0,SUM(G16/23*3),"") | J16: =IF($B16=707,SUM($G16-(SUM($H16:$I16))),"") | K16: =IF($B16=706,SUM($G16-(SUM($H16:$I16))),"") | L16: =IF($B16=703,SUM($G16-(SUM($H16:$I16))),"") | M16: =IF($B16=704,SUM($G16-(SUM($H16:$I16))),"") | N16: =IF($B16=709,SUM($G16-(SUM($H16:$I16))),"") | O16: =IF($B16=738,SUM($G16-(SUM($H16:$I16))),"") | P16: =IF($B16=739,SUM($G16-(SUM($H16:$I16))),"") | Q16: =IF($B16=714,SUM($G16-(SUM($H16:$I16))),"") | R16: =IF($B16=710,SUM($G16-(SUM($H16:$I16))),"") | S16: =IF($B16=711,SUM($G16-(SUM($H16:$I16))),"") | T16: =IF($B16=712,SUM($G16-(SUM($H16:$I16))),"") | U16: =IF($B16=713,SUM($G16-(SUM($H16:$I16))),"") | V16: =IF($B16=715,SUM($G16-(SUM($H16:$I16))),"") | W16: =IF($B16=724,SUM($G16-(SUM($H16:$I16))),"") -> 0 | X16: =IF($B16=725,SUM($G16-(SUM($H16:$I16))),"") | Y16: =IF($B16=726,SUM($G16-(SUM($H16:$I16))),"") | Z16: =IF($B16=727,SUM($G16-(SUM($H16:$I16))),"") | AA16: =IF($B16=728,SUM($G16-(SUM($H16:$I16))),"") | AB16: =IF($B16=729,SUM($G16-(SUM($H16:$I16))),"") | AC16: =IF($B16=730,SUM($G16-(SUM($H16:$I16))),"") | AD16: =IF($B16=732,SUM($G16-(SUM($H16:$I16))),"") | AE16: =IF($B16=733,SUM($G16-(SUM($H16:$I16))),"") | AF16: =IF($B16=734,SUM($G16-(SUM($H16:$I16))),"") | AG16: =IF($B16=705,SUM($G16-(SUM($H16:$I16))),"") | AH16: =IF($B16=735,SUM($G16-(SUM($H16:$I16))),"") | AI16: =IF($B16=736,SUM($G16-(SUM($H16:$I16))),"") | AJ16: =IF($B16=737,SUM($G16-(SUM($H16:$I16))),"") | AK16: =IF($B16=725,SUM($G16-(SUM($H16:$I16))),"") | AL16: =IF($B16=735,SUM($G16-(SUM($H16:$I16))),"") | AM16: =IF($B16=727,SUM($G16-(SUM($H16:$I16))),"") | AN16: =IF($B16=718,SUM($G16-(SUM($H16:$I16))),"") | AO16: =IF($B16=719,SUM($G16-(SUM($H16:$I16))),"") | AP16: =IF($B16=717,SUM($G16-(SUM($H16:$I16))),"") | AQ16: =IF($B16=722,SUM($G16-(SUM($H16:$I16))),"") | AR16: =IF($B16=708,SUM($G16-(SUM($H16:$I16))),"") | AS16: =IF($B16=701,SUM($G16-(SUM($H16:$I16))),"") | AT16: =IF($B16=702,SUM($G16-(SUM($H16:$I16))),"") | AU16: =IF($B16=731,SUM($G16-(SUM($H16:$I16))),"") | AV16: =IF($B16=730,SUM($G16-(SUM($H16:$I16))),"")
B17: 710 | C17: Bank Fees | D17: =D16+G17 -> 0 | F17: =SUM(H17:AV17)-G17 -> 0 | G17: 0 | H17: =IF(G17/23*3>0,SUM(G17/23*3),"") | J17: =IF($B17=707,SUM($G17-(SUM($H17:$I17))),"") | K17: =IF($B17=706,SUM($G17-(SUM($H17:$I17))),"") | L17: =IF($B17=703,SUM($G17-(SUM($H17:$I17))),"") | M17: =IF($B17=704,SUM($G17-(SUM($H17:$I17))),"") | N17: =IF($B17=709,SUM($G17-(SUM($H17:$I17))),"") | O17: =IF($B17=738,SUM($G17-(SUM($H17:$I17))),"") | P17: =IF($B17=739,SUM($G17-(SUM($H17:$I17))),"") | Q17: =IF($B17=714,SUM($G17-(SUM($H17:$I17))),"") | R17: =IF($B17=710,SUM($G17-(SUM($H17:$I17))),"") -> 0 | S17: =IF($B17=711,SUM($G17-(SUM($H17:$I17))),"") | T17: =IF($B17=712,SUM($G17-(SUM($H17:$I17))),"") | U17: =IF($B17=713,SUM($G17-(SUM($H17:$I17))),"") | V17: =IF($B17=715,SUM($G17-(SUM($H17:$I17))),"") | W17: =IF($B17=724,SUM($G17-(SUM($H17:$I17))),"") | X17: =IF($B17=725,SUM($G17-(SUM($H17:$I17))),"") | Y17: =IF($B17=726,SUM($G17-(SUM($H17:$I17))),"") | Z17: =IF($B17=727,SUM($G17-(SUM($H17:$I17))),"") | AA17: =IF($B17=728,SUM($G17-(SUM($H17:$I17))),"") | AB17: =IF($B17=729,SUM($G17-(SUM($H17:$I17))),"") | AC17: =IF($B17=730,SUM($G17-(SUM($H17:$I17))),"") | AD17: =IF($B17=732,SUM($G17-(SUM($H17:$I17))),"") | AE17: =IF($B17=733,SUM($G17-(SUM($H17:$I17))),"") | AF17: =IF($B17=734,SUM($G17-(SUM($H17:$I17))),"") | AG17: =IF($B17=705,SUM($G17-(SUM($H17:$I17))),"") | AH17: =IF($B17=735,SUM($G17-(SUM($H17:$I17))),"") | AI17: =IF($B17=736,SUM($G17-(SUM($H17:$I17))),"") | AJ17: =IF($B17=737,SUM($G17-(SUM($H17:$I17))),"") | AK17: =IF($B17=725,SUM($G17-(SUM($H17:$I17))),"") | AL17: =IF($B17=735,SUM($G17-(SUM($H17:$I17))),"") | AM17: =IF($B17=727,SUM($G17-(SUM($H17:$I17))),"") | AN17: =IF($B17=718,SUM($G17-(SUM($H17:$I17))),"") | AO17: =IF($B17=719,SUM($G17-(SUM($H17:$I17))),"") | AP17: =IF($B17=717,SUM($G17-(SUM($H17:$I17))),"") | AQ17: =IF($B17=722,SUM($G17-(SUM($H17:$I17))),"") | AR17: =IF($B17=708,SUM($G17-(SUM($H17:$I17))),"") | AS17: =IF($B17=701,SUM($G17-(SUM($H17:$I17))),"") | AT17: =IF($B17=702,SUM($G17-(SUM($H17:$I17))),"") | AU17: =IF($B17=731,SUM($G17-(SUM($H17:$I17))),"") | AV17: =IF($B17=730,SUM($G17-(SUM($H17:$I17))),"")
B18: 711 | C18: Accountant Fee (Accountancy) | D18: =D17+G18 -> 0 | F18: =SUM(H18:AV18)-G18 -> 0 | G18: 0 | H18: =IF(G18/23*3>0,SUM(G18/23*3),"") | I18: =IF(G18/23*3<0,SUM(G18/23*3),"") | J18: =IF($B18=707,SUM($G18-(SUM($H18:$I18))),"") | K18: =IF($B18=706,SUM($G18-(SUM($H18:$I18))),"") | L18: =IF($B18=703,SUM($G18-(SUM($H18:$I18))),"") | M18: =IF($B18=704,SUM($G18-(SUM($H18:$I18))),"") | N18: =IF($B18=709,SUM($G18-(SUM($H18:$I18))),"") | O18: =IF($B18=738,SUM($G18-(SUM($H18:$I18))),"") | P18: =IF($B18=739,SUM($G18-(SUM($H18:$I18))),"") | Q18: =IF($B18=714,SUM($G18-(SUM($H18:$I18))),"") | R18: =IF($B18=710,SUM($G18-(SUM($H18:$I18))),"") | S18: =IF($B18=711,SUM($G18-(SUM($H18:$I18))),"") -> 0 | T18: =IF($B18=712,SUM($G18-(SUM($H18:$I18))),"") | U18: =IF($B18=713,SUM($G18-(SUM($H18:$I18))),"") | V18: =IF($B18=715,SUM($G18-(SUM($H18:$I18))),"") | W18: =IF($B18=724,SUM($G18-(SUM($H18:$I18))),"") | X18: =IF($B18=725,SUM($G18-(SUM($H18:$I18))),"") | Y18: =IF($B18=726,SUM($G18-(SUM($H18:$I18))),"") | Z18: =IF($B18=727,SUM($G18-(SUM($H18:$I18))),"") | AA18: =IF($B18=728,SUM($G18-(SUM($H18:$I18))),"") | AB18: =IF($B18=729,SUM($G18-(SUM($H18:$I18))),"") | AC18: =IF($B18=730,SUM($G18-(SUM($H18:$I18))),"") | AD18: =IF($B18=732,SUM($G18-(SUM($H18:$I18))),"") | AE18: =IF($B18=733,SUM($G18-(SUM($H18:$I18))),"") | AF18: =IF($B18=734,SUM($G18-(SUM($H18:$I18))),"") | AG18: =IF($B18=705,SUM($G18-(SUM($H18:$I18))),"") | AH18: =IF($B18=735,SUM($G18-(SUM($H18:$I18))),"") | AI18: =IF($B18=736,SUM($G18-(SUM($H18:$I18))),"") | AJ18: =IF($B18=737,SUM($G18-(SUM($H18:$I18))),"") | AK18: =IF($B18=725,SUM($G18-(SUM($H18:$I18))),"") | AL18: =IF($B18=735,SUM($G18-(SUM($H18:$I18))),"") | AM18: =IF($B18=727,SUM($G18-(SUM($H18:$I18))),"") | AN18: =IF($B18=718,SUM($G18-(SUM($H18:$I18))),"") | AO18: =IF($B18=719,SUM($G18-(SUM($H18:$I18))),"") | AP18: =IF($B18=717,SUM($G18-(SUM($H18:$I18))),"") | AQ18: =IF($B18=722,SUM($G18-(SUM($H18:$I18))),"") | AR18: =IF($B18=708,SUM($G18-(SUM($H18:$I18))),"") | AS18: =IF($B18=701,SUM($G18-(SUM($H18:$I18))),"") | AT18: =IF($B18=702,SUM($G18-(SUM($H18:$I18))),"") | AU18: =IF($B18=731,SUM($G18-(SUM($H18:$I18))),"") | AV18: =IF($B18=730,SUM($G18-(SUM($H18:$I18))),"")
B19: 733 | C19: Body Corp Fees / Council Rates | D19: =D18+G19 -> 0 | F19: =SUM(H19:AV19)-G19 -> 0 | G19: 0 | H19: =IF(G19/23*3>0,SUM(G19/23*3),"") | I19: =IF(G19/23*3<0,SUM(G19/23*3),"") | J19: =IF($B19=707,SUM($G19-(SUM($H19:$I19))),"") | K19: =IF($B19=706,SUM($G19-(SUM($H19:$I19))),"") | L19: =IF($B19=703,SUM($G19-(SUM($H19:$I19))),"") | M19: =IF($B19=704,SUM($G19-(SUM($H19:$I19))),"") | N19: =IF($B19=709,SUM($G19-(SUM($H19:$I19))),"") | O19: =IF($B19=738,SUM($G19-(SUM($H19:$I19))),"") | P19: =IF($B19=739,SUM($G19-(SUM($H19:$I19))),"") | Q19: =IF($B19=714,SUM($G19-(SUM($H19:$I19))),"") | R19: =IF($B19=710,SUM($G19-(SUM($H19:$I19))),"") | S19: =IF($B19=711,SUM($G19-(SUM($H19:$I19))),"") | T19: =IF($B19=712,SUM($G19-(SUM($H19:$I19))),"") | U19: =IF($B19=713,SUM($G19-(SUM($H19:$I19))),"") | V19: =IF($B19=715,SUM($G19-(SUM($H19:$I19))),"") | W19: =IF($B19=724,SUM($G19-(SUM($H19:$I19))),"") | X19: =IF($B19=725,SUM($G19-(SUM($H19:$I19))),"") | Y19: =IF($B19=726,SUM($G19-(SUM($H19:$I19))),"") | Z19: =IF($B19=727,SUM($G19-(SUM($H19:$I19))),"") | AA19: =IF($B19=728,SUM($G19-(SUM($H19:$I19))),"") | AB19: =IF($B19=729,SUM($G19-(SUM($H19:$I19))),"") | AC19: =IF($B19=730,SUM($G19-(SUM($H19:$I19))),"") | AD19: =IF($B19=732,SUM($G19-(SUM($H19:$I19))),"") | AE19: =IF($B19=733,SUM($G19-(SUM($H19:$I19))),"") -> 0 | AF19: =IF($B19=734,SUM($G19-(SUM($H19:$I19))),"") | AG19: =IF($B19=705,SUM($G19-(SUM($H19:$I19))),"") | AH19: =IF($B19=735,SUM($G19-(SUM($H19:$I19))),"") | AI19: =IF($B19=736,SUM($G19-(SUM($H19:$I19))),"") | AJ19: =IF($B19=737,SUM($G19-(SUM($H19:$I19))),"") | AK19: =IF($B19=725,SUM($G19-(SUM($H19:$I19))),"") | AL19: =IF($B19=735,SUM($G19-(SUM($H19:$I19))),"") | AM19: =IF($B19=727,SUM($G19-(SUM($H19:$I19))),"") | AN19: =IF($B19=718,SUM($G19-(SUM($H19:$I19))),"") | AO19: =IF($B19=719,SUM($G19-(SUM($H19:$I19))),"") | AP19: =IF($B19=717,SUM($G19-(SUM($H19:$I19))),"") | AQ19: =IF($B19=722,SUM($G19-(SUM($H19:$I19))),"") | AR19: =IF($B19=708,SUM($G19-(SUM($H19:$I19))),"") | AS19: =IF($B19=701,SUM($G19-(SUM($H19:$I19))),"") | AT19: =IF($B19=702,SUM($G19-(SUM($H19:$I19))),"") | AU19: =IF($B19=731,SUM($G19-(SUM($H19:$I19))),"") | AV19: =IF($B19=730,SUM($G19-(SUM($H19:$I19))),"")
B20: 739 | C20: Online Tech Subscriptions (NO GST) | D20: =D19+G20 -> 0 | F20: =SUM(H20:AV20)-G20 -> 0 | G20: 0 | H20: =IF(G20/23*3>0,SUM(G20/23*3),"") | I20: 0 | J20: =IF($B20=707,SUM($G20-(SUM($H20:$I20))),"") | K20: =IF($B20=706,SUM($G20-(SUM($H20:$I20))),"") | L20: =IF($B20=703,SUM($G20-(SUM($H20:$I20))),"") | M20: =IF($B20=704,SUM($G20-(SUM($H20:$I20))),"") | N20: =IF($B20=709,SUM($G20-(SUM($H20:$I20))),"") | O20: =IF($B20=738,SUM($G20-(SUM($H20:$I20))),"") | P20: =IF($B20=739,SUM($G20-(SUM($H20:$I20))),"") -> 0 | Q20: =IF($B20=714,SUM($G20-(SUM($H20:$I20))),"") | R20: =IF($B20=710,SUM($G20-(SUM($H20:$I20))),"") | S20: =IF($B20=711,SUM($G20-(SUM($H20:$I20))),"") | T20: =IF($B20=712,SUM($G20-(SUM($H20:$I20))),"") | U20: =IF($B20=713,SUM($G20-(SUM($H20:$I20))),"") | V20: =IF($B20=715,SUM($G20-(SUM($H20:$I20))),"") | W20: =IF($B20=724,SUM($G20-(SUM($H20:$I20))),"") | X20: =IF($B20=725,SUM($G20-(SUM($H20:$I20))),"") | Y20: =IF($B20=726,SUM($G20-(SUM($H20:$I20))),"") | Z20: =IF($B20=727,SUM($G20-(SUM($H20:$I20))),"") | AA20: =IF($B20=728,SUM($G20-(SUM($H20:$I20))),"") | AB20: =IF($B20=729,SUM($G20-(SUM($H20:$I20))),"") | AC20: =IF($B20=730,SUM($G20-(SUM($H20:$I20))),"") | AD20: =IF($B20=732,SUM($G20-(SUM($H20:$I20))),"") | AE20: =IF($B20=733,SUM($G20-(SUM($H20:$I20))),"") | AF20: =IF($B20=734,SUM($G20-(SUM($H20:$I20))),"") | AG20: =IF($B20=705,SUM($G20-(SUM($H20:$I20))),"") | AH20: =IF($B20=735,SUM($G20-(SUM($H20:$I20))),"") | AI20: =IF($B20=736,SUM($G20-(SUM($H20:$I20))),"") | AJ20: =IF($B20=737,SUM($G20-(SUM($H20:$I20))),"") | AK20: =IF($B20=725,SUM($G20-(SUM($H20:$I20))),"") | AL20: =IF($B20=735,SUM($G20-(SUM($H20:$I20))),"") | AM20: =IF($B20=727,SUM($G20-(SUM($H20:$I20))),"") | AN20: =IF($B20=718,SUM($G20-(SUM($H20:$I20))),"") | AO20: =IF($B20=719,SUM($G20-(SUM($H20:$I20))),"") | AP20: =IF($B20=717,SUM($G20-(SUM($H20:$I20))),"") | AQ20: =IF($B20=722,SUM($G20-(SUM($H20:$I20))),"") | AR20: =IF($B20=708,SUM($G20-(SUM($H20:$I20))),"") | AS20: =IF($B20=701,SUM($G20-(SUM($H20:$I20))),"") | AT20: =IF($B20=702,SUM($G20-(SUM($H20:$I20))),"") | AU20: =IF($B20=731,SUM($G20-(SUM($H20:$I20))),"") | AV20: =IF($B20=730,SUM($G20-(SUM($H20:$I20))),"")
B21: 739 | C21: Online Tech Subscriptions (NO GST) | D21: =D20+G21 -> 0 | F21: =SUM(H21:AV21)-G21 -> 0 | G21: 0 | H21: =IF(G21/23*3>0,SUM(G21/23*3),"") | I21: 0 | J21: =IF($B21=707,SUM($G21-(SUM($H21:$I21))),"") | K21: =IF($B21=706,SUM($G21-(SUM($H21:$I21))),"") | L21: =IF($B21=703,SUM($G21-(SUM($H21:$I21))),"") | M21: =IF($B21=704,SUM($G21-(SUM($H21:$I21))),"") | N21: =IF($B21=709,SUM($G21-(SUM($H21:$I21))),"") | O21: =IF($B21=738,SUM($G21-(SUM($H21:$I21))),"") | P21: =IF($B21=739,SUM($G21-(SUM($H21:$I21))),"") -> 0 | Q21: =IF($B21=714,SUM($G21-(SUM($H21:$I21))),"") | R21: =IF($B21=710,SUM($G21-(SUM($H21:$I21))),"") | S21: =IF($B21=711,SUM($G21-(SUM($H21:$I21))),"") | T21: =IF($B21=712,SUM($G21-(SUM($H21:$I21))),"") | U21: =IF($B21=713,SUM($G21-(SUM($H21:$I21))),"") | V21: =IF($B21=715,SUM($G21-(SUM($H21:$I21))),"") | W21: =IF($B21=724,SUM($G21-(SUM($H21:$I21))),"") | X21: =IF($B21=725,SUM($G21-(SUM($H21:$I21))),"") | Y21: =IF($B21=726,SUM($G21-(SUM($H21:$I21))),"") | Z21: =IF($B21=727,SUM($G21-(SUM($H21:$I21))),"") | AA21: =IF($B21=728,SUM($G21-(SUM($H21:$I21))),"") | AB21: =IF($B21=729,SUM($G21-(SUM($H21:$I21))),"") | AC21: =IF($B21=730,SUM($G21-(SUM($H21:$I21))),"") | AD21: =IF($B21=732,SUM($G21-(SUM($H21:$I21))),"") | AE21: =IF($B21=733,SUM($G21-(SUM($H21:$I21))),"") | AF21: =IF($B21=734,SUM($G21-(SUM($H21:$I21))),"") | AG21: =IF($B21=705,SUM($G21-(SUM($H21:$I21))),"") | AH21: =IF($B21=735,SUM($G21-(SUM($H21:$I21))),"") | AI21: =IF($B21=736,SUM($G21-(SUM($H21:$I21))),"") | AJ21: =IF($B21=737,SUM($G21-(SUM($H21:$I21))),"") | AK21: =IF($B21=725,SUM($G21-(SUM($H21:$I21))),"") | AL21: =IF($B21=735,SUM($G21-(SUM($H21:$I21))),"") | AM21: =IF($B21=727,SUM($G21-(SUM($H21:$I21))),"") | AN21: =IF($B21=718,SUM($G21-(SUM($H21:$I21))),"") | AO21: =IF($B21=719,SUM($G21-(SUM($H21:$I21))),"") | AP21: =IF($B21=717,SUM($G21-(SUM($H21:$I21))),"") | AQ21: =IF($B21=722,SUM($G21-(SUM($H21:$I21))),"") | AR21: =IF($B21=708,SUM($G21-(SUM($H21:$I21))),"") | AS21: =IF($B21=701,SUM($G21-(SUM($H21:$I21))),"") | AT21: =IF($B21=702,SUM($G21-(SUM($H21:$I21))),"") | AU21: =IF($B21=731,SUM($G21-(SUM($H21:$I21))),"") | AV21: =IF($B21=730,SUM($G21-(SUM($H21:$I21))),"")
B22: 730 | C22: Home Contents Insurance | D22: =D21+G22 -> 0 | F22: =SUM(H22:AV22)-G22 -> 0 | G22: 0 | H22: =IF(G22/23*3>0,SUM(G22/23*3),"") | I22: =IF(G22/23*3<0,SUM(G22/23*3),"") | J22: =IF($B22=707,SUM($G22-(SUM($H22:$I22))),"") | K22: =IF($B22=706,SUM($G22-(SUM($H22:$I22))),"") | L22: =IF($B22=703,SUM($G22-(SUM($H22:$I22))),"") | M22: =IF($B22=704,SUM($G22-(SUM($H22:$I22))),"") | N22: =IF($B22=709,SUM($G22-(SUM($H22:$I22))),"") | O22: =IF($B22=738,SUM($G22-(SUM($H22:$I22))),"") | P22: =IF($B22=739,SUM($G22-(SUM($H22:$I22))),"") | Q22: =IF($B22=714,SUM($G22-(SUM($H22:$I22))),"") | R22: =IF($B22=710,SUM($G22-(SUM($H22:$I22))),"") | S22: =IF($B22=711,SUM($G22-(SUM($H22:$I22))),"") | T22: =IF($B22=712,SUM($G22-(SUM($H22:$I22))),"") | U22: =IF($B22=713,SUM($G22-(SUM($H22:$I22))),"") | V22: =IF($B22=715,SUM($G22-(SUM($H22:$I22))),"") | W22: =IF($B22=724,SUM($G22-(SUM($H22:$I22))),"") | X22: =IF($B22=725,SUM($G22-(SUM($H22:$I22))),"") | Y22: =IF($B22=726,SUM($G22-(SUM($H22:$I22))),"") | Z22: =IF($B22=727,SUM($G22-(SUM($H22:$I22))),"") | AA22: =IF($B22=728,SUM($G22-(SUM($H22:$I22))),"") | AB22: =IF($B22=729,SUM($G22-(SUM($H22:$I22))),"") | AC22: =IF($B22=730,SUM($G22-(SUM($H22:$I22))),"") -> 0 | AD22: =IF($B22=732,SUM($G22-(SUM($H22:$I22))),"") | AE22: =IF($B22=733,SUM($G22-(SUM($H22:$I22))),"") | AF22: =IF($B22=734,SUM($G22-(SUM($H22:$I22))),"") | AG22: =IF($B22=705,SUM($G22-(SUM($H22:$I22))),"") | AH22: =IF($B22=735,SUM($G22-(SUM($H22:$I22))),"") | AI22: =IF($B22=736,SUM($G22-(SUM($H22:$I22))),"") | AJ22: =IF($B22=737,SUM($G22-(SUM($H22:$I22))),"") | AK22: =IF($B22=725,SUM($G22-(SUM($H22:$I22))),"") | AL22: =IF($B22=735,SUM($G22-(SUM($H22:$I22))),"") | AM22: =IF($B22=727,SUM($G22-(SUM($H22:$I22))),"") | AN22: =IF($B22=718,SUM($G22-(SUM($H22:$I22))),"") | AO22: =IF($B22=719,SUM($G22-(SUM($H22:$I22))),"") | AP22: =IF($B22=717,SUM($G22-(SUM($H22:$I22))),"") | AQ22: =IF($B22=722,SUM($G22-(SUM($H22:$I22))),"") | AR22: =IF($B22=708,SUM($G22-(SUM($H22:$I22))),"") | AS22: =IF($B22=701,SUM($G22-(SUM($H22:$I22))),"") | AT22: =IF($B22=702,SUM($G22-(SUM($H22:$I22))),"") | AU22: =IF($B22=731,SUM($G22-(SUM($H22:$I22))),"") | AV22: =IF($B22=730,SUM($G22-(SUM($H22:$I22))),"") -> 0
D23: =D22+G23 -> 0 | F23: =SUM(H23:AV23)-G23 -> 0 | H23: =IF(G23/23*3>0,SUM(G23/23*3),"") | I23: =IF(G23/23*3<0,SUM(G23/23*3),"") | J23: =IF($B23=707,SUM($G23-(SUM($H23:$I23))),"") | K23: =IF($B23=706,SUM($G23-(SUM($H23:$I23))),"") | L23: =IF($B23=703,SUM($G23-(SUM($H23:$I23))),"") | M23: =IF($B23=704,SUM($G23-(SUM($H23:$I23))),"") | N23: =IF($B23=709,SUM($G23-(SUM($H23:$I23))),"") | O23: =IF($B23=738,SUM($G23-(SUM($H23:$I23))),"") | P23: =IF($B23=739,SUM($G23-(SUM($H23:$I23))),"") | Q23: =IF($B23=714,SUM($G23-(SUM($H23:$I23))),"") | R23: =IF($B23=710,SUM($G23-(SUM($H23:$I23))),"") | S23: =IF($B23=711,SUM($G23-(SUM($H23:$I23))),"") | T23: =IF($B23=712,SUM($G23-(SUM($H23:$I23))),"") | U23: =IF($B23=713,SUM($G23-(SUM($H23:$I23))),"") | V23: =IF($B23=715,SUM($G23-(SUM($H23:$I23))),"") | W23: =IF($B23=724,SUM($G23-(SUM($H23:$I23))),"") | X23: =IF($B23=725,SUM($G23-(SUM($H23:$I23))),"") | Y23: =IF($B23=726,SUM($G23-(SUM($H23:$I23))),"") | Z23: =IF($B23=727,SUM($G23-(SUM($H23:$I23))),"") | AA23: =IF($B23=728,SUM($G23-(SUM($H23:$I23))),"") | AB23: =IF($B23=729,SUM($G23-(SUM($H23:$I23))),"") | AC23: =IF($B23=730,SUM($G23-(SUM($H23:$I23))),"") | AD23: =IF($B23=732,SUM($G23-(SUM($H23:$I23))),"") | AE23: =IF($B23=733,SUM($G23-(SUM($H23:$I23))),"") | AF23: =IF($B23=734,SUM($G23-(SUM($H23:$I23))),"") | AG23: =IF($B23=705,SUM($G23-(SUM($H23:$I23))),"") | AH23: =IF($B23=735,SUM($G23-(SUM($H23:$I23))),"") | AI23: =IF($B23=736,SUM($G23-(SUM($H23:$I23))),"") | AJ23: =IF($B23=737,SUM($G23-(SUM($H23:$I23))),"") | AK23: =IF($B23=725,SUM($G23-(SUM($H23:$I23))),"") | AL23: =IF($B23=735,SUM($G23-(SUM($H23:$I23))),"") | AM23: =IF($B23=727,SUM($G23-(SUM($H23:$I23))),"") | AN23: =IF($B23=718,SUM($G23-(SUM($H23:$I23))),"") | AO23: =IF($B23=719,SUM($G23-(SUM($H23:$I23))),"") | AP23: =IF($B23=717,SUM($G23-(SUM($H23:$I23))),"") | AQ23: =IF($B23=722,SUM($G23-(SUM($H23:$I23))),"") | AR23: =IF($B23=708,SUM($G23-(SUM($H23:$I23))),"") | AS23: =IF($B23=701,SUM($G23-(SUM($H23:$I23))),"") | AT23: =IF($B23=702,SUM($G23-(SUM($H23:$I23))),"") | AU23: =IF($B23=731,SUM($G23-(SUM($H23:$I23))),"") | AV23: =IF($B23=730,SUM($G23-(SUM($H23:$I23))),"")
B24: 707 | C24: Income - November - Client (50% progress payment received) | D24: =D23+G24 -> 0 | F24: =SUM(H24:AV24)-G24 -> 0 | G24: 0 | H24: =IF(G24/23*3>0,SUM(G24/23*3),"") | I24: =IF(G24/23*3<0,SUM(G24/23*3),"") | J24: =IF($B24=707,SUM($G24-(SUM($H24:$I24))),"") -> 0 | K24: =IF($B24=706,SUM($G24-(SUM($H24:$I24))),"") | L24: =IF($B24=703,SUM($G24-(SUM($H24:$I24))),"") | M24: =IF($B24=704,SUM($G24-(SUM($H24:$I24))),"") | N24: =IF($B24=709,SUM($G24-(SUM($H24:$I24))),"") | O24: =IF($B24=738,SUM($G24-(SUM($H24:$I24))),"") | P24: =IF($B24=739,SUM($G24-(SUM($H24:$I24))),"") | Q24: =IF($B24=714,SUM($G24-(SUM($H24:$I24))),"") | R24: =IF($B24=710,SUM($G24-(SUM($H24:$I24))),"") | S24: =IF($B24=711,SUM($G24-(SUM($H24:$I24))),"") | T24: =IF($B24=712,SUM($G24-(SUM($H24:$I24))),"") | U24: =IF($B24=713,SUM($G24-(SUM($H24:$I24))),"") | V24: =IF($B24=715,SUM($G24-(SUM($H24:$I24))),"") | W24: =IF($B24=724,SUM($G24-(SUM($H24:$I24))),"") | X24: =IF($B24=725,SUM($G24-(SUM($H24:$I24))),"") | Y24: =IF($B24=726,SUM($G24-(SUM($H24:$I24))),"") | Z24: =IF($B24=727,SUM($G24-(SUM($H24:$I24))),"") | AA24: =IF($B24=728,SUM($G24-(SUM($H24:$I24))),"") | AB24: =IF($B24=729,SUM($G24-(SUM($H24:$I24))),"") | AC24: =IF($B24=730,SUM($G24-(SUM($H24:$I24))),"") | AD24: =IF($B24=732,SUM($G24-(SUM($H24:$I24))),"") | AE24: =IF($B24=733,SUM($G24-(SUM($H24:$I24))),"") | AF24: =IF($B24=734,SUM($G24-(SUM($H24:$I24))),"") | AG24: =IF($B24=705,SUM($G24-(SUM($H24:$I24))),"") | AH24: =IF($B24=735,SUM($G24-(SUM($H24:$I24))),"") | AI24: =IF($B24=736,SUM($G24-(SUM($H24:$I24))),"") | AJ24: =IF($B24=737,SUM($G24-(SUM($H24:$I24))),"") | AK24: =IF($B24=725,SUM($G24-(SUM($H24:$I24))),"") | AL24: =IF($B24=735,SUM($G24-(SUM($H24:$I24))),"") | AM24: =IF($B24=727,SUM($G24-(SUM($H24:$I24))),"") | AN24: =IF($B24=718,SUM($G24-(SUM($H24:$I24))),"") | AO24: =IF($B24=719,SUM($G24-(SUM($H24:$I24))),"") | AP24: =IF($B24=717,SUM($G24-(SUM($H24:$I24))),"") | AQ24: =IF($B24=722,SUM($G24-(SUM($H24:$I24))),"") | AR24: =IF($B24=708,SUM($G24-(SUM($H24:$I24))),"") | AS24: =IF($B24=701,SUM($G24-(SUM($H24:$I24))),"") | AT24: =IF($B24=702,SUM($G24-(SUM($H24:$I24))),"") | AU24: =IF($B24=731,SUM($G24-(SUM($H24:$I24))),"") | AV24: =IF($B24=730,SUM($G24-(SUM($H24:$I24))),"")
B25: 725 | C25: Power - Fibrewave | D25: =D24+G25 -> 0 | F25: =SUM(H25:AV25)-G25 -> 0 | G25: 0 | H25: =IF(G25/23*3>0,SUM(G25/23*3),"") | I25: =IF(G25/23*3<0,SUM(G25/23*3),"") | J25: =IF($B25=707,SUM($G25-(SUM($H25:$I25))),"") | K25: =IF($B25=706,SUM($G25-(SUM($H25:$I25))),"") | L25: =IF($B25=703,SUM($G25-(SUM($H25:$I25))),"") | M25: =IF($B25=704,SUM($G25-(SUM($H25:$I25))),"") | N25: =IF($B25=709,SUM($G25-(SUM($H25:$I25))),"") | O25: =IF($B25=738,SUM($G25-(SUM($H25:$I25))),"") | P25: =IF($B25=739,SUM($G25-(SUM($H25:$I25))),"") | Q25: =IF($B25=714,SUM($G25-(SUM($H25:$I25))),"") | R25: =IF($B25=710,SUM($G25-(SUM($H25:$I25))),"") | S25: =IF($B25=711,SUM($G25-(SUM($H25:$I25))),"") | T25: =IF($B25=712,SUM($G25-(SUM($H25:$I25))),"") | U25: =IF($B25=713,SUM($G25-(SUM($H25:$I25))),"") | V25: =IF($B25=715,SUM($G25-(SUM($H25:$I25))),"") | W25: =IF($B25=724,SUM($G25-(SUM($H25:$I25))),"") | X25: =IF($B25=725,SUM($G25-(SUM($H25:$I25))),"") -> 0 | Y25: =IF($B25=726,SUM($G25-(SUM($H25:$I25))),"") | Z25: =IF($B25=727,SUM($G25-(SUM($H25:$I25))),"") | AA25: =IF($B25=728,SUM($G25-(SUM($H25:$I25))),"") | AB25: =IF($B25=729,SUM($G25-(SUM($H25:$I25))),"") | AC25: =IF($B25=730,SUM($G25-(SUM($H25:$I25))),"") | AD25: =IF($B25=732,SUM($G25-(SUM($H25:$I25))),"") | AE25: =IF($B25=733,SUM($G25-(SUM($H25:$I25))),"") | AF25: =IF($B25=734,SUM($G25-(SUM($H25:$I25))),"") | AG25: =IF($B25=705,SUM($G25-(SUM($H25:$I25))),"") | AH25: =IF($B25=735,SUM($G25-(SUM($H25:$I25))),"") | AI25: =IF($B25=736,SUM($G25-(SUM($H25:$I25))),"") | AJ25: =IF($B25=737,SUM($G25-(SUM($H25:$I25))),"") | AK25: =IF($B25=725,SUM($G25-(SUM($H25:$I25))),"") -> 0 | AL25: =IF($B25=735,SUM($G25-(SUM($H25:$I25))),"") | AM25: =IF($B25=727,SUM($G25-(SUM($H25:$I25))),"") | AN25: =IF($B25=718,SUM($G25-(SUM($H25:$I25))),"") | AO25: =IF($B25=719,SUM($G25-(SUM($H25:$I25))),"") | AP25: =IF($B25=717,SUM($G25-(SUM($H25:$I25))),"") | AQ25: =IF($B25=722,SUM($G25-(SUM($H25:$I25))),"") | AR25: =IF($B25=708,SUM($G25-(SUM($H25:$I25))),"") | AS25: =IF($B25=701,SUM($G25-(SUM($H25:$I25))),"") | AT25: =IF($B25=702,SUM($G25-(SUM($H25:$I25))),"") | AU25: =IF($B25=731,SUM($G25-(SUM($H25:$I25))),"") | AV25: =IF($B25=730,SUM($G25-(SUM($H25:$I25))),"")
B26: 726 | C26: Entertainment (Business Lunch/Coffee/Meals/Drinks) | D26: =D25+G26 -> 0 | F26: =SUM(H26:AV26)-G26 -> 0 | G26: =-(OtherCalculation!C6) -> 0 | H26: =IF(G26/23*3>0,SUM(G26/23*3),"") | I26: =IF(G26/23*3<0,SUM(G26/23*3),"") | J26: =IF($B26=707,SUM($G26-(SUM($H26:$I26))),"") | K26: =IF($B26=706,SUM($G26-(SUM($H26:$I26))),"") | L26: =IF($B26=703,SUM($G26-(SUM($H26:$I26))),"") | M26: =IF($B26=704,SUM($G26-(SUM($H26:$I26))),"") | N26: =IF($B26=709,SUM($G26-(SUM($H26:$I26))),"") | O26: =IF($B26=738,SUM($G26-(SUM($H26:$I26))),"") | P26: =IF($B26=739,SUM($G26-(SUM($H26:$I26))),"") | Q26: =IF($B26=714,SUM($G26-(SUM($H26:$I26))),"") | R26: =IF($B26=710,SUM($G26-(SUM($H26:$I26))),"") | S26: =IF($B26=711,SUM($G26-(SUM($H26:$I26))),"") | T26: =IF($B26=712,SUM($G26-(SUM($H26:$I26))),"") | U26: =IF($B26=713,SUM($G26-(SUM($H26:$I26))),"") | V26: =IF($B26=715,SUM($G26-(SUM($H26:$I26))),"") | W26: =IF($B26=724,SUM($G26-(SUM($H26:$I26))),"") | X26: =IF($B26=725,SUM($G26-(SUM($H26:$I26))),"") | Y26: =IF($B26=726,SUM($G26-(SUM($H26:$I26))),"") -> 0 | Z26: =IF($B26=727,SUM($G26-(SUM($H26:$I26))),"") | AA26: =IF($B26=728,SUM($G26-(SUM($H26:$I26))),"") | AB26: =IF($B26=729,SUM($G26-(SUM($H26:$I26))),"") | AC26: =IF($B26=730,SUM($G26-(SUM($H26:$I26))),"") | AD26: =IF($B26=732,SUM($G26-(SUM($H26:$I26))),"") | AE26: =IF($B26=733,SUM($G26-(SUM($H26:$I26))),"") | AF26: =IF($B26=734,SUM($G26-(SUM($H26:$I26))),"") | AG26: =IF($B26=705,SUM($G26-(SUM($H26:$I26))),"") | AH26: =IF($B26=735,SUM($G26-(SUM($H26:$I26))),"") | AI26: =IF($B26=736,SUM($G26-(SUM($H26:$I26))),"") | AJ26: =IF($B26=737,SUM($G26-(SUM($H26:$I26))),"") | AK26: =IF($B26=725,SUM($G26-(SUM($H26:$I26))),"") | AL26: =IF($B26=735,SUM($G26-(SUM($H26:$I26))),"") | AM26: =IF($B26=727,SUM($G26-(SUM($H26:$I26))),"") | AN26: =IF($B26=718,SUM($G26-(SUM($H26:$I26))),"") | AO26: =IF($B26=719,SUM($G26-(SUM($H26:$I26))),"") | AP26: =IF($B26=717,SUM($G26-(SUM($H26:$I26))),"") | AQ26: =IF($B26=722,SUM($G26-(SUM($H26:$I26))),"") | AR26: =IF($B26=708,SUM($G26-(SUM($H26:$I26))),"") | AS26: =IF($B26=701,SUM($G26-(SUM($H26:$I26))),"") | AT26: =IF($B26=702,SUM($G26-(SUM($H26:$I26))),"") | AU26: =IF($B26=731,SUM($G26-(SUM($H26:$I26))),"") | AV26: =IF($B26=730,SUM($G26-(SUM($H26:$I26))),"")
B27: 727 | C27: Internet - Fibrewave | D27: =D26+G27 -> 0 | F27: =SUM(H27:AV27)-G27 -> 0 | G27: 0 | H27: =IF(G27/23*3>0,SUM(G27/23*3),"") | I27: =IF(G27/23*3<0,SUM(G27/23*3),"") | J27: =IF($B27=707,SUM($G27-(SUM($H27:$I27))),"") | K27: =IF($B27=706,SUM($G27-(SUM($H27:$I27))),"") | L27: =IF($B27=703,SUM($G27-(SUM($H27:$I27))),"") | M27: =IF($B27=704,SUM($G27-(SUM($H27:$I27))),"") | N27: =IF($B27=709,SUM($G27-(SUM($H27:$I27))),"") | O27: =IF($B27=738,SUM($G27-(SUM($H27:$I27))),"") | P27: =IF($B27=739,SUM($G27-(SUM($H27:$I27))),"") | Q27: =IF($B27=714,SUM($G27-(SUM($H27:$I27))),"") | R27: =IF($B27=710,SUM($G27-(SUM($H27:$I27))),"") | S27: =IF($B27=711,SUM($G27-(SUM($H27:$I27))),"") | T27: =IF($B27=712,SUM($G27-(SUM($H27:$I27))),"") | U27: =IF($B27=713,SUM($G27-(SUM($H27:$I27))),"") | V27: =IF($B27=715,SUM($G27-(SUM($H27:$I27))),"") | W27: =IF($B27=724,SUM($G27-(SUM($H27:$I27))),"") | X27: =IF($B27=725,SUM($G27-(SUM($H27:$I27))),"") | Y27: =IF($B27=726,SUM($G27-(SUM($H27:$I27))),"") | Z27: =IF($B27=727,SUM($G27-(SUM($H27:$I27))),"") -> 0 | AA27: =IF($B27=728,SUM($G27-(SUM($H27:$I27))),"") | AB27: =IF($B27=729,SUM($G27-(SUM($H27:$I27))),"") | AC27: =IF($B27=730,SUM($G27-(SUM($H27:$I27))),"") | AD27: =IF($B27=732,SUM($G27-(SUM($H27:$I27))),"") | AE27: =IF($B27=733,SUM($G27-(SUM($H27:$I27))),"") | AF27: =IF($B27=734,SUM($G27-(SUM($H27:$I27))),"") | AG27: =IF($B27=705,SUM($G27-(SUM($H27:$I27))),"") | AH27: =IF($B27=735,SUM($G27-(SUM($H27:$I27))),"") | AI27: =IF($B27=736,SUM($G27-(SUM($H27:$I27))),"") | AJ27: =IF($B27=737,SUM($G27-(SUM($H27:$I27))),"") | AK27: =IF($B27=725,SUM($G27-(SUM($H27:$I27))),"") | AL27: =IF($B27=735,SUM($G27-(SUM($H27:$I27))),"") | AM27: =IF($B27=727,SUM($G27-(SUM($H27:$I27))),"") -> 0 | AN27: =IF($B27=718,SUM($G27-(SUM($H27:$I27))),"") | AO27: =IF($B27=719,SUM($G27-(SUM($H27:$I27))),"") | AP27: =IF($B27=717,SUM($G27-(SUM($H27:$I27))),"") | AQ27: =IF($B27=722,SUM($G27-(SUM($H27:$I27))),"") | AR27: =IF($B27=708,SUM($G27-(SUM($H27:$I27))),"") | AS27: =IF($B27=701,SUM($G27-(SUM($H27:$I27))),"") | AT27: =IF($B27=702,SUM($G27-(SUM($H27:$I27))),"") | AU27: =IF($B27=731,SUM($G27-(SUM($H27:$I27))),"") | AV27: =IF($B27=730,SUM($G27-(SUM($H27:$I27))),"")
B28: 728 | C28: Mobile Plan - Tui Mobile NZ | D28: =D27+G28 -> 0 | F28: =SUM(H28:AV28)-G28 -> 0 | G28: 0 | H28: =IF(G28/23*3>0,SUM(G28/23*3),"") | I28: =IF(G28/23*3<0,SUM(G28/23*3),"") | J28: =IF($B28=707,SUM($G28-(SUM($H28:$I28))),"") | K28: =IF($B28=706,SUM($G28-(SUM($H28:$I28))),"") | L28: =IF($B28=703,SUM($G28-(SUM($H28:$I28))),"") | M28: =IF($B28=704,SUM($G28-(SUM($H28:$I28))),"") | N28: =IF($B28=709,SUM($G28-(SUM($H28:$I28))),"") | O28: =IF($B28=738,SUM($G28-(SUM($H28:$I28))),"") | P28: =IF($B28=739,SUM($G28-(SUM($H28:$I28))),"") | Q28: =IF($B28=714,SUM($G28-(SUM($H28:$I28))),"") | R28: =IF($B28=710,SUM($G28-(SUM($H28:$I28))),"") | S28: =IF($B28=711,SUM($G28-(SUM($H28:$I28))),"") | T28: =IF($B28=712,SUM($G28-(SUM($H28:$I28))),"") | U28: =IF($B28=713,SUM($G28-(SUM($H28:$I28))),"") | V28: =IF($B28=715,SUM($G28-(SUM($H28:$I28))),"") | W28: =IF($B28=724,SUM($G28-(SUM($H28:$I28))),"") | X28: =IF($B28=725,SUM($G28-(SUM($H28:$I28))),"") | Y28: =IF($B28=726,SUM($G28-(SUM($H28:$I28))),"") | Z28: =IF($B28=727,SUM($G28-(SUM($H28:$I28))),"") | AA28: =IF($B28=728,SUM($G28-(SUM($H28:$I28))),"") -> 0 | AB28: =IF($B28=729,SUM($G28-(SUM($H28:$I28))),"") | AC28: =IF($B28=730,SUM($G28-(SUM($H28:$I28))),"") | AD28: =IF($B28=732,SUM($G28-(SUM($H28:$I28))),"") | AE28: =IF($B28=733,SUM($G28-(SUM($H28:$I28))),"") | AF28: =IF($B28=734,SUM($G28-(SUM($H28:$I28))),"") | AG28: =IF($B28=705,SUM($G28-(SUM($H28:$I28))),"") | AH28: =IF($B28=735,SUM($G28-(SUM($H28:$I28))),"") | AI28: =IF($B28=736,SUM($G28-(SUM($H28:$I28))),"") | AJ28: =IF($B28=737,SUM($G28-(SUM($H28:$I28))),"") | AK28: =IF($B28=725,SUM($G28-(SUM($H28:$I28))),"") | AL28: =IF($B28=735,SUM($G28-(SUM($H28:$I28))),"") | AM28: =IF($B28=727,SUM($G28-(SUM($H28:$I28))),"") | AN28: =IF($B28=718,SUM($G28-(SUM($H28:$I28))),"") | AO28: =IF($B28=719,SUM($G28-(SUM($H28:$I28))),"") | AP28: =IF($B28=717,SUM($G28-(SUM($H28:$I28))),"") | AQ28: =IF($B28=722,SUM($G28-(SUM($H28:$I28))),"") | AR28: =IF($B28=708,SUM($G28-(SUM($H28:$I28))),"") | AS28: =IF($B28=701,SUM($G28-(SUM($H28:$I28))),"") | AT28: =IF($B28=702,SUM($G28-(SUM($H28:$I28))),"") | AU28: =IF($B28=731,SUM($G28-(SUM($H28:$I28))),"") | AV28: =IF($B28=730,SUM($G28-(SUM($H28:$I28))),"")
B29: 729 | C29: Car Park Fees | D29: =D28+G29 -> 0 | F29: =SUM(H29:AV29)-G29 -> 0 | G29: 0 | H29: =IF(G29/23*3>0,SUM(G29/23*3),"") | I29: =IF(G29/23*3<0,SUM(G29/23*3),"") | J29: =IF($B29=707,SUM($G29-(SUM($H29:$I29))),"") | K29: =IF($B29=706,SUM($G29-(SUM($H29:$I29))),"") | L29: =IF($B29=703,SUM($G29-(SUM($H29:$I29))),"") | M29: =IF($B29=704,SUM($G29-(SUM($H29:$I29))),"") | N29: =IF($B29=709,SUM($G29-(SUM($H29:$I29))),"") | O29: =IF($B29=738,SUM($G29-(SUM($H29:$I29))),"") | P29: =IF($B29=739,SUM($G29-(SUM($H29:$I29))),"") | Q29: =IF($B29=714,SUM($G29-(SUM($H29:$I29))),"") | R29: =IF($B29=710,SUM($G29-(SUM($H29:$I29))),"") | S29: =IF($B29=711,SUM($G29-(SUM($H29:$I29))),"") | T29: =IF($B29=712,SUM($G29-(SUM($H29:$I29))),"") | U29: =IF($B29=713,SUM($G29-(SUM($H29:$I29))),"") | V29: =IF($B29=715,SUM($G29-(SUM($H29:$I29))),"") | W29: =IF($B29=724,SUM($G29-(SUM($H29:$I29))),"") | X29: =IF($B29=725,SUM($G29-(SUM($H29:$I29))),"") | Y29: =IF($B29=726,SUM($G29-(SUM($H29:$I29))),"") | Z29: =IF($B29=727,SUM($G29-(SUM($H29:$I29))),"") | AA29: =IF($B29=728,SUM($G29-(SUM($H29:$I29))),"") | AB29: =IF($B29=729,SUM($G29-(SUM($H29:$I29))),"") -> 0 | AC29: =IF($B29=730,SUM($G29-(SUM($H29:$I29))),"") | AD29: =IF($B29=732,SUM($G29-(SUM($H29:$I29))),"") | AE29: =IF($B29=733,SUM($G29-(SUM($H29:$I29))),"") | AF29: =IF($B29=734,SUM($G29-(SUM($H29:$I29))),"") | AG29: =IF($B29=705,SUM($G29-(SUM($H29:$I29))),"") | AH29: =IF($B29=735,SUM($G29-(SUM($H29:$I29))),"") | AI29: =IF($B29=736,SUM($G29-(SUM($H29:$I29))),"") | AJ29: =IF($B29=737,SUM($G29-(SUM($H29:$I29))),"") | AK29: =IF($B29=725,SUM($G29-(SUM($H29:$I29))),"") | AL29: =IF($B29=735,SUM($G29-(SUM($H29:$I29))),"") | AM29: =IF($B29=727,SUM($G29-(SUM($H29:$I29))),"") | AN29: =IF($B29=718,SUM($G29-(SUM($H29:$I29))),"") | AO29: =IF($B29=719,SUM($G29-(SUM($H29:$I29))),"") | AP29: =IF($B29=717,SUM($G29-(SUM($H29:$I29))),"") | AQ29: =IF($B29=722,SUM($G29-(SUM($H29:$I29))),"") | AR29: =IF($B29=708,SUM($G29-(SUM($H29:$I29))),"") | AS29: =IF($B29=701,SUM($G29-(SUM($H29:$I29))),"") | AT29: =IF($B29=702,SUM($G29-(SUM($H29:$I29))),"") | AU29: =IF($B29=731,SUM($G29-(SUM($H29:$I29))),"") | AV29: =IF($B29=730,SUM($G29-(SUM($H29:$I29))),"")
B30: 734 | C30: Home Office Expenses | D30: =D29+G30 -> 0 | F30: =SUM(H30:AV30)-G30 -> 0 | G30: 0 | H30: =IF(G30/23*3>0,SUM(G30/23*3),"") | I30: =IF(G30/23*3<0,SUM(G30/23*3),"") | J30: =IF($B30=707,SUM($G30-(SUM($H30:$I30))),"") | K30: =IF($B30=706,SUM($G30-(SUM($H30:$I30))),"") | L30: =IF($B30=703,SUM($G30-(SUM($H30:$I30))),"") | M30: =IF($B30=704,SUM($G30-(SUM($H30:$I30))),"") | N30: =IF($B30=709,SUM($G30-(SUM($H30:$I30))),"") | O30: =IF($B30=738,SUM($G30-(SUM($H30:$I30))),"") | P30: =IF($B30=739,SUM($G30-(SUM($H30:$I30))),"") | Q30: =IF($B30=714,SUM($G30-(SUM($H30:$I30))),"") | R30: =IF($B30=710,SUM($G30-(SUM($H30:$I30))),"") | S30: =IF($B30=711,SUM($G30-(SUM($H30:$I30))),"") | T30: =IF($B30=712,SUM($G30-(SUM($H30:$I30))),"") | U30: =IF($B30=713,SUM($G30-(SUM($H30:$I30))),"") | V30: =IF($B30=715,SUM($G30-(SUM($H30:$I30))),"") | W30: =IF($B30=724,SUM($G30-(SUM($H30:$I30))),"") | X30: =IF($B30=725,SUM($G30-(SUM($H30:$I30))),"") | Y30: =IF($B30=726,SUM($G30-(SUM($H30:$I30))),"") | Z30: =IF($B30=727,SUM($G30-(SUM($H30:$I30))),"") | AA30: =IF($B30=728,SUM($G30-(SUM($H30:$I30))),"") | AB30: =IF($B30=729,SUM($G30-(SUM($H30:$I30))),"") | AC30: =IF($B30=730,SUM($G30-(SUM($H30:$I30))),"") | AD30: =IF($B30=732,SUM($G30-(SUM($H30:$I30))),"") | AE30: =IF($B30=733,SUM($G30-(SUM($H30:$I30))),"") | AF30: =IF($B30=734,SUM($G30-(SUM($H30:$I30))),"") -> 0 | AG30: =IF($B30=705,SUM($G30-(SUM($H30:$I30))),"") | AH30: =IF($B30=735,SUM($G30-(SUM($H30:$I30))),"") | AI30: =IF($B30=736,SUM($G30-(SUM($H30:$I30))),"") | AJ30: =IF($B30=737,SUM($G30-(SUM($H30:$I30))),"") | AK30: =IF($B30=725,SUM($G30-(SUM($H30:$I30))),"") | AL30: =IF($B30=735,SUM($G30-(SUM($H30:$I30))),"") | AM30: =IF($B30=727,SUM($G30-(SUM($H30:$I30))),"") | AN30: =IF($B30=718,SUM($G30-(SUM($H30:$I30))),"") | AO30: =IF($B30=719,SUM($G30-(SUM($H30:$I30))),"") | AP30: =IF($B30=717,SUM($G30-(SUM($H30:$I30))),"") | AQ30: =IF($B30=722,SUM($G30-(SUM($H30:$I30))),"") | AR30: =IF($B30=708,SUM($G30-(SUM($H30:$I30))),"") | AS30: =IF($B30=701,SUM($G30-(SUM($H30:$I30))),"") | AT30: =IF($B30=702,SUM($G30-(SUM($H30:$I30))),"") | AU30: =IF($B30=731,SUM($G30-(SUM($H30:$I30))),"") | AV30: =IF($B30=730,SUM($G30-(SUM($H30:$I30))),"")
B31: 724 | C31: Apartment Rent | D31: =D30+G31 -> 0 | F31: =SUM(H31:AV31)-G31 -> 0 | G31: 0 | H31: =IF(G31/23*3>0,SUM(G31/23*3),"") | J31: =IF($B31=707,SUM($G31-(SUM($H31:$I31))),"") | K31: =IF($B31=706,SUM($G31-(SUM($H31:$I31))),"") | L31: =IF($B31=703,SUM($G31-(SUM($H31:$I31))),"") | M31: =IF($B31=704,SUM($G31-(SUM($H31:$I31))),"") | N31: =IF($B31=709,SUM($G31-(SUM($H31:$I31))),"") | O31: =IF($B31=738,SUM($G31-(SUM($H31:$I31))),"") | P31: =IF($B31=739,SUM($G31-(SUM($H31:$I31))),"") | Q31: =IF($B31=714,SUM($G31-(SUM($H31:$I31))),"") | R31: =IF($B31=710,SUM($G31-(SUM($H31:$I31))),"") | S31: =IF($B31=711,SUM($G31-(SUM($H31:$I31))),"") | T31: =IF($B31=712,SUM($G31-(SUM($H31:$I31))),"") | U31: =IF($B31=713,SUM($G31-(SUM($H31:$I31))),"") | V31: =IF($B31=715,SUM($G31-(SUM($H31:$I31))),"") | W31: =IF($B31=724,SUM($G31-(SUM($H31:$I31))),"") -> 0 | X31: =IF($B31=725,SUM($G31-(SUM($H31:$I31))),"") | Y31: =IF($B31=726,SUM($G31-(SUM($H31:$I31))),"") | Z31: =IF($B31=727,SUM($G31-(SUM($H31:$I31))),"") | AA31: =IF($B31=728,SUM($G31-(SUM($H31:$I31))),"") | AB31: =IF($B31=729,SUM($G31-(SUM($H31:$I31))),"") | AC31: =IF($B31=730,SUM($G31-(SUM($H31:$I31))),"") | AD31: =IF($B31=732,SUM($G31-(SUM($H31:$I31))),"") | AE31: =IF($B31=733,SUM($G31-(SUM($H31:$I31))),"") | AF31: =IF($B31=734,SUM($G31-(SUM($H31:$I31))),"") | AG31: =IF($B31=705,SUM($G31-(SUM($H31:$I31))),"") | AH31: =IF($B31=735,SUM($G31-(SUM($H31:$I31))),"") | AI31: =IF($B31=736,SUM($G31-(SUM($H31:$I31))),"") | AJ31: =IF($B31=737,SUM($G31-(SUM($H31:$I31))),"") | AK31: =IF($B31=725,SUM($G31-(SUM($H31:$I31))),"") | AL31: =IF($B31=735,SUM($G31-(SUM($H31:$I31))),"") | AM31: =IF($B31=727,SUM($G31-(SUM($H31:$I31))),"") | AN31: =IF($B31=718,SUM($G31-(SUM($H31:$I31))),"") | AO31: =IF($B31=719,SUM($G31-(SUM($H31:$I31))),"") | AP31: =IF($B31=717,SUM($G31-(SUM($H31:$I31))),"") | AQ31: =IF($B31=722,SUM($G31-(SUM($H31:$I31))),"") | AR31: =IF($B31=708,SUM($G31-(SUM($H31:$I31))),"") | AS31: =IF($B31=701,SUM($G31-(SUM($H31:$I31))),"") | AT31: =IF($B31=702,SUM($G31-(SUM($H31:$I31))),"") | AU31: =IF($B31=731,SUM($G31-(SUM($H31:$I31))),"") | AV31: =IF($B31=730,SUM($G31-(SUM($H31:$I31))),"")
B32: 710 | C32: Bank Fees | D32: =D31+G32 -> 0 | F32: =SUM(H32:AV32)-G32 -> 0 | G32: 0 | H32: =IF(G32/23*3>0,SUM(G32/23*3),"") | J32: =IF($B32=707,SUM($G32-(SUM($H32:$I32))),"") | K32: =IF($B32=706,SUM($G32-(SUM($H32:$I32))),"") | L32: =IF($B32=703,SUM($G32-(SUM($H32:$I32))),"") | M32: =IF($B32=704,SUM($G32-(SUM($H32:$I32))),"") | N32: =IF($B32=709,SUM($G32-(SUM($H32:$I32))),"") | O32: =IF($B32=738,SUM($G32-(SUM($H32:$I32))),"") | P32: =IF($B32=739,SUM($G32-(SUM($H32:$I32))),"") | Q32: =IF($B32=714,SUM($G32-(SUM($H32:$I32))),"") | R32: =IF($B32=710,SUM($G32-(SUM($H32:$I32))),"") -> 0 | S32: =IF($B32=711,SUM($G32-(SUM($H32:$I32))),"") | T32: =IF($B32=712,SUM($G32-(SUM($H32:$I32))),"") | U32: =IF($B32=713,SUM($G32-(SUM($H32:$I32))),"") | V32: =IF($B32=715,SUM($G32-(SUM($H32:$I32))),"") | W32: =IF($B32=724,SUM($G32-(SUM($H32:$I32))),"") | X32: =IF($B32=725,SUM($G32-(SUM($H32:$I32))),"") | Y32: =IF($B32=726,SUM($G32-(SUM($H32:$I32))),"") | Z32: =IF($B32=727,SUM($G32-(SUM($H32:$I32))),"") | AA32: =IF($B32=728,SUM($G32-(SUM($H32:$I32))),"") | AB32: =IF($B32=729,SUM($G32-(SUM($H32:$I32))),"") | AC32: =IF($B32=730,SUM($G32-(SUM($H32:$I32))),"") | AD32: =IF($B32=732,SUM($G32-(SUM($H32:$I32))),"") | AE32: =IF($B32=733,SUM($G32-(SUM($H32:$I32))),"") | AF32: =IF($B32=734,SUM($G32-(SUM($H32:$I32))),"") | AG32: =IF($B32=705,SUM($G32-(SUM($H32:$I32))),"") | AH32: =IF($B32=735,SUM($G32-(SUM($H32:$I32))),"") | AI32: =IF($B32=736,SUM($G32-(SUM($H32:$I32))),"") | AJ32: =IF($B32=737,SUM($G32-(SUM($H32:$I32))),"") | AK32: =IF($B32=725,SUM($G32-(SUM($H32:$I32))),"") | AL32: =IF($B32=735,SUM($G32-(SUM($H32:$I32))),"") | AM32: =IF($B32=727,SUM($G32-(SUM($H32:$I32))),"") | AN32: =IF($B32=718,SUM($G32-(SUM($H32:$I32))),"") | AO32: =IF($B32=719,SUM($G32-(SUM($H32:$I32))),"") | AP32: =IF($B32=717,SUM($G32-(SUM($H32:$I32))),"") | AQ32: =IF($B32=722,SUM($G32-(SUM($H32:$I32))),"") | AR32: =IF($B32=708,SUM($G32-(SUM($H32:$I32))),"") | AS32: =IF($B32=701,SUM($G32-(SUM($H32:$I32))),"") | AT32: =IF($B32=702,SUM($G32-(SUM($H32:$I32))),"") | AU32: =IF($B32=731,SUM($G32-(SUM($H32:$I32))),"") | AV32: =IF($B32=730,SUM($G32-(SUM($H32:$I32))),"")
B33: 730 | C33: Home Contents Insurance | D33: =D32+G33 -> 0 | F33: =SUM(H33:AV33)-G33 -> 0 | G33: 0 | H33: =IF(G33/23*3>0,SUM(G33/23*3),"") | I33: =IF(G33/23*3<0,SUM(G33/23*3),"") | J33: =IF($B33=707,SUM($G33-(SUM($H33:$I33))),"") | K33: =IF($B33=706,SUM($G33-(SUM($H33:$I33))),"") | L33: =IF($B33=703,SUM($G33-(SUM($H33:$I33))),"") | M33: =IF($B33=704,SUM($G33-(SUM($H33:$I33))),"") | N33: =IF($B33=709,SUM($G33-(SUM($H33:$I33))),"") | O33: =IF($B33=738,SUM($G33-(SUM($H33:$I33))),"") | P33: =IF($B33=739,SUM($G33-(SUM($H33:$I33))),"") | Q33: =IF($B33=714,SUM($G33-(SUM($H33:$I33))),"") | R33: =IF($B33=710,SUM($G33-(SUM($H33:$I33))),"") | S33: =IF($B33=711,SUM($G33-(SUM($H33:$I33))),"") | T33: =IF($B33=712,SUM($G33-(SUM($H33:$I33))),"") | U33: =IF($B33=713,SUM($G33-(SUM($H33:$I33))),"") | V33: =IF($B33=715,SUM($G33-(SUM($H33:$I33))),"") | W33: =IF($B33=724,SUM($G33-(SUM($H33:$I33))),"") | X33: =IF($B33=725,SUM($G33-(SUM($H33:$I33))),"") | Y33: =IF($B33=726,SUM($G33-(SUM($H33:$I33))),"") | Z33: =IF($B33=727,SUM($G33-(SUM($H33:$I33))),"") | AA33: =IF($B33=728,SUM($G33-(SUM($H33:$I33))),"") | AB33: =IF($B33=729,SUM($G33-(SUM($H33:$I33))),"") | AC33: =IF($B33=730,SUM($G33-(SUM($H33:$I33))),"") -> 0 | AD33: =IF($B33=732,SUM($G33-(SUM($H33:$I33))),"") | AE33: =IF($B33=733,SUM($G33-(SUM($H33:$I33))),"") | AF33: =IF($B33=734,SUM($G33-(SUM($H33:$I33))),"") | AG33: =IF($B33=705,SUM($G33-(SUM($H33:$I33))),"") | AH33: =IF($B33=735,SUM($G33-(SUM($H33:$I33))),"") | AI33: =IF($B33=736,SUM($G33-(SUM($H33:$I33))),"") | AJ33: =IF($B33=737,SUM($G33-(SUM($H33:$I33))),"") | AK33: =IF($B33=725,SUM($G33-(SUM($H33:$I33))),"") | AL33: =IF($B33=735,SUM($G33-(SUM($H33:$I33))),"") | AM33: =IF($B33=727,SUM($G33-(SUM($H33:$I33))),"") | AN33: =IF($B33=718,SUM($G33-(SUM($H33:$I33))),"") | AO33: =IF($B33=719,SUM($G33-(SUM($H33:$I33))),"") | AP33: =IF($B33=717,SUM($G33-(SUM($H33:$I33))),"") | AQ33: =IF($B33=722,SUM($G33-(SUM($H33:$I33))),"") | AR33: =IF($B33=708,SUM($G33-(SUM($H33:$I33))),"") | AS33: =IF($B33=701,SUM($G33-(SUM($H33:$I33))),"") | AT33: =IF($B33=702,SUM($G33-(SUM($H33:$I33))),"") | AU33: =IF($B33=731,SUM($G33-(SUM($H33:$I33))),"") | AV33: =IF($B33=730,SUM($G33-(SUM($H33:$I33))),"") -> 0
B34: 711 | C34: Accountant Fee (Accountancy) | D34: =D33+G34 -> 0 | F34: =SUM(H34:AV34)-G34 -> 0 | G34: 0 | H34: =IF(G34/23*3>0,SUM(G34/23*3),"") | I34: =IF(G34/23*3<0,SUM(G34/23*3),"") | J34: =IF($B34=707,SUM($G34-(SUM($H34:$I34))),"") | K34: =IF($B34=706,SUM($G34-(SUM($H34:$I34))),"") | L34: =IF($B34=703,SUM($G34-(SUM($H34:$I34))),"") | M34: =IF($B34=704,SUM($G34-(SUM($H34:$I34))),"") | N34: =IF($B34=709,SUM($G34-(SUM($H34:$I34))),"") | O34: =IF($B34=738,SUM($G34-(SUM($H34:$I34))),"") | P34: =IF($B34=739,SUM($G34-(SUM($H34:$I34))),"") | Q34: =IF($B34=714,SUM($G34-(SUM($H34:$I34))),"") | R34: =IF($B34=710,SUM($G34-(SUM($H34:$I34))),"") | S34: =IF($B34=711,SUM($G34-(SUM($H34:$I34))),"") -> 0 | T34: =IF($B34=712,SUM($G34-(SUM($H34:$I34))),"") | U34: =IF($B34=713,SUM($G34-(SUM($H34:$I34))),"") | V34: =IF($B34=715,SUM($G34-(SUM($H34:$I34))),"") | W34: =IF($B34=724,SUM($G34-(SUM($H34:$I34))),"") | X34: =IF($B34=725,SUM($G34-(SUM($H34:$I34))),"") | Y34: =IF($B34=726,SUM($G34-(SUM($H34:$I34))),"") | Z34: =IF($B34=727,SUM($G34-(SUM($H34:$I34))),"") | AA34: =IF($B34=728,SUM($G34-(SUM($H34:$I34))),"") | AB34: =IF($B34=729,SUM($G34-(SUM($H34:$I34))),"") | AC34: =IF($B34=730,SUM($G34-(SUM($H34:$I34))),"") | AD34: =IF($B34=732,SUM($G34-(SUM($H34:$I34))),"") | AE34: =IF($B34=733,SUM($G34-(SUM($H34:$I34))),"") | AF34: =IF($B34=734,SUM($G34-(SUM($H34:$I34))),"") | AG34: =IF($B34=705,SUM($G34-(SUM($H34:$I34))),"") | AH34: =IF($B34=735,SUM($G34-(SUM($H34:$I34))),"") | AI34: =IF($B34=736,SUM($G34-(SUM($H34:$I34))),"") | AJ34: =IF($B34=737,SUM($G34-(SUM($H34:$I34))),"") | AK34: =IF($B34=725,SUM($G34-(SUM($H34:$I34))),"") | AL34: =IF($B34=735,SUM($G34-(SUM($H34:$I34))),"") | AM34: =IF($B34=727,SUM($G34-(SUM($H34:$I34))),"") | AN34: =IF($B34=718,SUM($G34-(SUM($H34:$I34))),"") | AO34: =IF($B34=719,SUM($G34-(SUM($H34:$I34))),"") | AP34: =IF($B34=717,SUM($G34-(SUM($H34:$I34))),"") | AQ34: =IF($B34=722,SUM($G34-(SUM($H34:$I34))),"") | AR34: =IF($B34=708,SUM($G34-(SUM($H34:$I34))),"") | AS34: =IF($B34=701,SUM($G34-(SUM($H34:$I34))),"") | AT34: =IF($B34=702,SUM($G34-(SUM($H34:$I34))),"") | AU34: =IF($B34=731,SUM($G34-(SUM($H34:$I34))),"") | AV34: =IF($B34=730,SUM($G34-(SUM($H34:$I34))),"")
B35: 732 | C35: Indemnity Insurance - Shield (annual) | D35: =D34+G35 -> 0 | F35: =SUM(H35:AV35)-G35 -> 0 | G35: 0 | H35: =IF(G35/23*3>0,SUM(G35/23*3),"") | I35: =IF(G35/23*3<0,SUM(G35/23*3),"") | J35: =IF($B35=707,SUM($G35-(SUM($H35:$I35))),"") | K35: =IF($B35=706,SUM($G35-(SUM($H35:$I35))),"") | L35: =IF($B35=703,SUM($G35-(SUM($H35:$I35))),"") | M35: =IF($B35=704,SUM($G35-(SUM($H35:$I35))),"") | N35: =IF($B35=709,SUM($G35-(SUM($H35:$I35))),"") | O35: =IF($B35=738,SUM($G35-(SUM($H35:$I35))),"") | P35: =IF($B35=739,SUM($G35-(SUM($H35:$I35))),"") | Q35: =IF($B35=714,SUM($G35-(SUM($H35:$I35))),"") | R35: =IF($B35=710,SUM($G35-(SUM($H35:$I35))),"") | S35: =IF($B35=711,SUM($G35-(SUM($H35:$I35))),"") | T35: =IF($B35=712,SUM($G35-(SUM($H35:$I35))),"") | U35: =IF($B35=713,SUM($G35-(SUM($H35:$I35))),"") | V35: =IF($B35=715,SUM($G35-(SUM($H35:$I35))),"") | W35: =IF($B35=724,SUM($G35-(SUM($H35:$I35))),"") | X35: =IF($B35=725,SUM($G35-(SUM($H35:$I35))),"") | Y35: =IF($B35=726,SUM($G35-(SUM($H35:$I35))),"") | Z35: =IF($B35=727,SUM($G35-(SUM($H35:$I35))),"") | AA35: =IF($B35=728,SUM($G35-(SUM($H35:$I35))),"") | AB35: =IF($B35=729,SUM($G35-(SUM($H35:$I35))),"") | AC35: =IF($B35=730,SUM($G35-(SUM($H35:$I35))),"") | AD35: =IF($B35=732,SUM($G35-(SUM($H35:$I35))),"") -> 0 | AE35: =IF($B35=733,SUM($G35-(SUM($H35:$I35))),"") | AF35: =IF($B35=734,SUM($G35-(SUM($H35:$I35))),"") | AG35: =IF($B35=705,SUM($G35-(SUM($H35:$I35))),"") | AH35: =IF($B35=735,SUM($G35-(SUM($H35:$I35))),"") | AI35: =IF($B35=736,SUM($G35-(SUM($H35:$I35))),"") | AJ35: =IF($B35=737,SUM($G35-(SUM($H35:$I35))),"") | AK35: =IF($B35=725,SUM($G35-(SUM($H35:$I35))),"") | AL35: =IF($B35=735,SUM($G35-(SUM($H35:$I35))),"") | AM35: =IF($B35=727,SUM($G35-(SUM($H35:$I35))),"") | AN35: =IF($B35=718,SUM($G35-(SUM($H35:$I35))),"") | AO35: =IF($B35=719,SUM($G35-(SUM($H35:$I35))),"") | AP35: =IF($B35=717,SUM($G35-(SUM($H35:$I35))),"") | AQ35: =IF($B35=722,SUM($G35-(SUM($H35:$I35))),"") | AR35: =IF($B35=708,SUM($G35-(SUM($H35:$I35))),"") | AS35: =IF($B35=701,SUM($G35-(SUM($H35:$I35))),"") | AT35: =IF($B35=702,SUM($G35-(SUM($H35:$I35))),"") | AU35: =IF($B35=731,SUM($G35-(SUM($H35:$I35))),"") | AV35: =IF($B35=730,SUM($G35-(SUM($H35:$I35))),"")
B36: 739 | C36: Online Tech Subscriptions (NO GST) | D36: =D35+G36 -> 0 | F36: =SUM(H36:AV36)-G36 -> 0 | G36: 0 | H36: =IF(G36/23*3>0,SUM(G36/23*3),"") | I36: 0 | J36: =IF($B36=707,SUM($G36-(SUM($H36:$I36))),"") | K36: =IF($B36=706,SUM($G36-(SUM($H36:$I36))),"") | L36: =IF($B36=703,SUM($G36-(SUM($H36:$I36))),"") | M36: =IF($B36=704,SUM($G36-(SUM($H36:$I36))),"") | N36: =IF($B36=709,SUM($G36-(SUM($H36:$I36))),"") | O36: =IF($B36=738,SUM($G36-(SUM($H36:$I36))),"") | P36: =IF($B36=739,SUM($G36-(SUM($H36:$I36))),"") -> 0 | Q36: =IF($B36=714,SUM($G36-(SUM($H36:$I36))),"") | R36: =IF($B36=710,SUM($G36-(SUM($H36:$I36))),"") | S36: =IF($B36=711,SUM($G36-(SUM($H36:$I36))),"") | T36: =IF($B36=712,SUM($G36-(SUM($H36:$I36))),"") | U36: =IF($B36=713,SUM($G36-(SUM($H36:$I36))),"") | V36: =IF($B36=715,SUM($G36-(SUM($H36:$I36))),"") | W36: =IF($B36=724,SUM($G36-(SUM($H36:$I36))),"") | X36: =IF($B36=725,SUM($G36-(SUM($H36:$I36))),"") | Y36: =IF($B36=726,SUM($G36-(SUM($H36:$I36))),"") | Z36: =IF($B36=727,SUM($G36-(SUM($H36:$I36))),"") | AA36: =IF($B36=728,SUM($G36-(SUM($H36:$I36))),"") | AB36: =IF($B36=729,SUM($G36-(SUM($H36:$I36))),"") | AC36: =IF($B36=730,SUM($G36-(SUM($H36:$I36))),"") | AD36: =IF($B36=732,SUM($G36-(SUM($H36:$I36))),"") | AE36: =IF($B36=733,SUM($G36-(SUM($H36:$I36))),"") | AF36: =IF($B36=734,SUM($G36-(SUM($H36:$I36))),"") | AG36: =IF($B36=705,SUM($G36-(SUM($H36:$I36))),"") | AH36: =IF($B36=735,SUM($G36-(SUM($H36:$I36))),"") | AI36: =IF($B36=736,SUM($G36-(SUM($H36:$I36))),"") | AJ36: =IF($B36=737,SUM($G36-(SUM($H36:$I36))),"") | AK36: =IF($B36=725,SUM($G36-(SUM($H36:$I36))),"") | AL36: =IF($B36=735,SUM($G36-(SUM($H36:$I36))),"") | AM36: =IF($B36=727,SUM($G36-(SUM($H36:$I36))),"") | AN36: =IF($B36=718,SUM($G36-(SUM($H36:$I36))),"") | AO36: =IF($B36=719,SUM($G36-(SUM($H36:$I36))),"") | AP36: =IF($B36=717,SUM($G36-(SUM($H36:$I36))),"") | AQ36: =IF($B36=722,SUM($G36-(SUM($H36:$I36))),"") | AR36: =IF($B36=708,SUM($G36-(SUM($H36:$I36))),"") | AS36: =IF($B36=701,SUM($G36-(SUM($H36:$I36))),"") | AT36: =IF($B36=702,SUM($G36-(SUM($H36:$I36))),"") | AU36: =IF($B36=731,SUM($G36-(SUM($H36:$I36))),"") | AV36: =IF($B36=730,SUM($G36-(SUM($H36:$I36))),"")
B37: 733 | C37: Body Corp Fees / Council Rates | D37: =D36+G37 -> 0 | F37: =SUM(H37:AV37)-G37 -> 0 | G37: 0 | H37: =IF(G37/23*3>0,SUM(G37/23*3),"") | I37: =IF(G37/23*3<0,SUM(G37/23*3),"") | J37: =IF($B37=707,SUM($G37-(SUM($H37:$I37))),"") | K37: =IF($B37=706,SUM($G37-(SUM($H37:$I37))),"") | L37: =IF($B37=703,SUM($G37-(SUM($H37:$I37))),"") | M37: =IF($B37=704,SUM($G37-(SUM($H37:$I37))),"") | N37: =IF($B37=709,SUM($G37-(SUM($H37:$I37))),"") | O37: =IF($B37=738,SUM($G37-(SUM($H37:$I37))),"") | P37: =IF($B37=739,SUM($G37-(SUM($H37:$I37))),"") | Q37: =IF($B37=714,SUM($G37-(SUM($H37:$I37))),"") | R37: =IF($B37=710,SUM($G37-(SUM($H37:$I37))),"") | S37: =IF($B37=711,SUM($G37-(SUM($H37:$I37))),"") | T37: =IF($B37=712,SUM($G37-(SUM($H37:$I37))),"") | U37: =IF($B37=713,SUM($G37-(SUM($H37:$I37))),"") | V37: =IF($B37=715,SUM($G37-(SUM($H37:$I37))),"") | W37: =IF($B37=724,SUM($G37-(SUM($H37:$I37))),"") | X37: =IF($B37=725,SUM($G37-(SUM($H37:$I37))),"") | Y37: =IF($B37=726,SUM($G37-(SUM($H37:$I37))),"") | Z37: =IF($B37=727,SUM($G37-(SUM($H37:$I37))),"") | AA37: =IF($B37=728,SUM($G37-(SUM($H37:$I37))),"") | AB37: =IF($B37=729,SUM($G37-(SUM($H37:$I37))),"") | AC37: =IF($B37=730,SUM($G37-(SUM($H37:$I37))),"") | AD37: =IF($B37=732,SUM($G37-(SUM($H37:$I37))),"") | AE37: =IF($B37=733,SUM($G37-(SUM($H37:$I37))),"") -> 0 | AF37: =IF($B37=734,SUM($G37-(SUM($H37:$I37))),"") | AG37: =IF($B37=705,SUM($G37-(SUM($H37:$I37))),"") | AH37: =IF($B37=735,SUM($G37-(SUM($H37:$I37))),"") | AI37: =IF($B37=736,SUM($G37-(SUM($H37:$I37))),"") | AJ37: =IF($B37=737,SUM($G37-(SUM($H37:$I37))),"") | AK37: =IF($B37=725,SUM($G37-(SUM($H37:$I37))),"") | AL37: =IF($B37=735,SUM($G37-(SUM($H37:$I37))),"") | AM37: =IF($B37=727,SUM($G37-(SUM($H37:$I37))),"") | AN37: =IF($B37=718,SUM($G37-(SUM($H37:$I37))),"") | AO37: =IF($B37=719,SUM($G37-(SUM($H37:$I37))),"") | AP37: =IF($B37=717,SUM($G37-(SUM($H37:$I37))),"") | AQ37: =IF($B37=722,SUM($G37-(SUM($H37:$I37))),"") | AR37: =IF($B37=708,SUM($G37-(SUM($H37:$I37))),"") | AS37: =IF($B37=701,SUM($G37-(SUM($H37:$I37))),"") | AT37: =IF($B37=702,SUM($G37-(SUM($H37:$I37))),"") | AU37: =IF($B37=731,SUM($G37-(SUM($H37:$I37))),"") | AV37: =IF($B37=730,SUM($G37-(SUM($H37:$I37))),"")
D38: =D37+G38 -> 0 | F38: =SUM(H38:AV38)-G38 -> 0 | H38: =IF(G38/23*3>0,SUM(G38/23*3),"") | I38: =IF(G38/23*3<0,SUM(G38/23*3),"") | J38: =IF($B38=707,SUM($G38-(SUM($H38:$I38))),"") | K38: =IF($B38=706,SUM($G38-(SUM($H38:$I38))),"") | L38: =IF($B38=703,SUM($G38-(SUM($H38:$I38))),"") | M38: =IF($B38=704,SUM($G38-(SUM($H38:$I38))),"") | N38: =IF($B38=709,SUM($G38-(SUM($H38:$I38))),"") | O38: =IF($B38=738,SUM($G38-(SUM($H38:$I38))),"") | P38: =IF($B38=739,SUM($G38-(SUM($H38:$I38))),"") | Q38: =IF($B38=714,SUM($G38-(SUM($H38:$I38))),"") | R38: =IF($B38=710,SUM($G38-(SUM($H38:$I38))),"") | S38: =IF($B38=711,SUM($G38-(SUM($H38:$I38))),"") | T38: =IF($B38=712,SUM($G38-(SUM($H38:$I38))),"") | U38: =IF($B38=713,SUM($G38-(SUM($H38:$I38))),"") | V38: =IF($B38=715,SUM($G38-(SUM($H38:$I38))),"") | W38: =IF($B38=724,SUM($G38-(SUM($H38:$I38))),"") | X38: =IF($B38=725,SUM($G38-(SUM($H38:$I38))),"") | Y38: =IF($B38=726,SUM($G38-(SUM($H38:$I38))),"") | Z38: =IF($B38=727,SUM($G38-(SUM($H38:$I38))),"") | AA38: =IF($B38=728,SUM($G38-(SUM($H38:$I38))),"") | AB38: =IF($B38=729,SUM($G38-(SUM($H38:$I38))),"") | AC38: =IF($B38=730,SUM($G38-(SUM($H38:$I38))),"") | AD38: =IF($B38=732,SUM($G38-(SUM($H38:$I38))),"") | AE38: =IF($B38=733,SUM($G38-(SUM($H38:$I38))),"") | AF38: =IF($B38=734,SUM($G38-(SUM($H38:$I38))),"") | AG38: =IF($B38=705,SUM($G38-(SUM($H38:$I38))),"") | AH38: =IF($B38=735,SUM($G38-(SUM($H38:$I38))),"") | AI38: =IF($B38=736,SUM($G38-(SUM($H38:$I38))),"") | AJ38: =IF($B38=737,SUM($G38-(SUM($H38:$I38))),"") | AK38: =IF($B38=725,SUM($G38-(SUM($H38:$I38))),"") | AL38: =IF($B38=735,SUM($G38-(SUM($H38:$I38))),"") | AM38: =IF($B38=727,SUM($G38-(SUM($H38:$I38))),"") | AN38: =IF($B38=718,SUM($G38-(SUM($H38:$I38))),"") | AO38: =IF($B38=719,SUM($G38-(SUM($H38:$I38))),"") | AP38: =IF($B38=717,SUM($G38-(SUM($H38:$I38))),"") | AQ38: =IF($B38=722,SUM($G38-(SUM($H38:$I38))),"") | AR38: =IF($B38=708,SUM($G38-(SUM($H38:$I38))),"") | AS38: =IF($B38=701,SUM($G38-(SUM($H38:$I38))),"") | AT38: =IF($B38=702,SUM($G38-(SUM($H38:$I38))),"") | AU38: =IF($B38=731,SUM($G38-(SUM($H38:$I38))),"") | AV38: =IF($B38=730,SUM($G38-(SUM($H38:$I38))),"")
B39: 707 | C39: Income - December - Client (50% progress payment received) | D39: =D38+G39 -> 0 | F39: =SUM(H39:AV39)-G39 -> 0 | G39: 0 | H39: =IF(G39/23*3>0,SUM(G39/23*3),"") | I39: =IF(G39/23*3<0,SUM(G39/23*3),"") | J39: =IF($B39=707,SUM($G39-(SUM($H39:$I39))),"") -> 0 | K39: =IF($B39=706,SUM($G39-(SUM($H39:$I39))),"") | L39: =IF($B39=703,SUM($G39-(SUM($H39:$I39))),"") | M39: =IF($B39=704,SUM($G39-(SUM($H39:$I39))),"") | N39: =IF($B39=709,SUM($G39-(SUM($H39:$I39))),"") | O39: =IF($B39=738,SUM($G39-(SUM($H39:$I39))),"") | P39: =IF($B39=739,SUM($G39-(SUM($H39:$I39))),"") | Q39: =IF($B39=714,SUM($G39-(SUM($H39:$I39))),"") | R39: =IF($B39=710,SUM($G39-(SUM($H39:$I39))),"") | S39: =IF($B39=711,SUM($G39-(SUM($H39:$I39))),"") | T39: =IF($B39=712,SUM($G39-(SUM($H39:$I39))),"") | U39: =IF($B39=713,SUM($G39-(SUM($H39:$I39))),"") | V39: =IF($B39=715,SUM($G39-(SUM($H39:$I39))),"") | W39: =IF($B39=724,SUM($G39-(SUM($H39:$I39))),"") | X39: =IF($B39=725,SUM($G39-(SUM($H39:$I39))),"") | Y39: =IF($B39=726,SUM($G39-(SUM($H39:$I39))),"") | Z39: =IF($B39=727,SUM($G39-(SUM($H39:$I39))),"") | AA39: =IF($B39=728,SUM($G39-(SUM($H39:$I39))),"") | AB39: =IF($B39=729,SUM($G39-(SUM($H39:$I39))),"") | AC39: =IF($B39=730,SUM($G39-(SUM($H39:$I39))),"") | AD39: =IF($B39=732,SUM($G39-(SUM($H39:$I39))),"") | AE39: =IF($B39=733,SUM($G39-(SUM($H39:$I39))),"") | AF39: =IF($B39=734,SUM($G39-(SUM($H39:$I39))),"") | AG39: =IF($B39=705,SUM($G39-(SUM($H39:$I39))),"") | AH39: =IF($B39=735,SUM($G39-(SUM($H39:$I39))),"") | AI39: =IF($B39=736,SUM($G39-(SUM($H39:$I39))),"") | AJ39: =IF($B39=737,SUM($G39-(SUM($H39:$I39))),"") | AK39: =IF($B39=725,SUM($G39-(SUM($H39:$I39))),"") | AL39: =IF($B39=735,SUM($G39-(SUM($H39:$I39))),"") | AM39: =IF($B39=727,SUM($G39-(SUM($H39:$I39))),"") | AN39: =IF($B39=718,SUM($G39-(SUM($H39:$I39))),"") | AO39: =IF($B39=719,SUM($G39-(SUM($H39:$I39))),"") | AP39: =IF($B39=717,SUM($G39-(SUM($H39:$I39))),"") | AQ39: =IF($B39=722,SUM($G39-(SUM($H39:$I39))),"") | AR39: =IF($B39=708,SUM($G39-(SUM($H39:$I39))),"") | AS39: =IF($B39=701,SUM($G39-(SUM($H39:$I39))),"") | AT39: =IF($B39=702,SUM($G39-(SUM($H39:$I39))),"") | AU39: =IF($B39=731,SUM($G39-(SUM($H39:$I39))),"") | AV39: =IF($B39=730,SUM($G39-(SUM($H39:$I39))),"")
B40: 726 | C40: Entertainment (Business Lunch/Coffee/Meals/Drinks) | D40: =D39+G40 -> 0 | F40: =SUM(H40:AV40)-G40 -> 0 | G40: =-(OtherCalculation!C7) -> 0 | H40: =IF(G40/23*3>0,SUM(G40/23*3),"") | I40: =IF(G40/23*3<0,SUM(G40/23*3),"") | J40: =IF($B40=707,SUM($G40-(SUM($H40:$I40))),"") | K40: =IF($B40=706,SUM($G40-(SUM($H40:$I40))),"") | L40: =IF($B40=703,SUM($G40-(SUM($H40:$I40))),"") | M40: =IF($B40=704,SUM($G40-(SUM($H40:$I40))),"") | N40: =IF($B40=709,SUM($G40-(SUM($H40:$I40))),"") | O40: =IF($B40=738,SUM($G40-(SUM($H40:$I40))),"") | P40: =IF($B40=739,SUM($G40-(SUM($H40:$I40))),"") | Q40: =IF($B40=714,SUM($G40-(SUM($H40:$I40))),"") | R40: =IF($B40=710,SUM($G40-(SUM($H40:$I40))),"") | S40: =IF($B40=711,SUM($G40-(SUM($H40:$I40))),"") | T40: =IF($B40=712,SUM($G40-(SUM($H40:$I40))),"") | U40: =IF($B40=713,SUM($G40-(SUM($H40:$I40))),"") | V40: =IF($B40=715,SUM($G40-(SUM($H40:$I40))),"") | W40: =IF($B40=724,SUM($G40-(SUM($H40:$I40))),"") | X40: =IF($B40=725,SUM($G40-(SUM($H40:$I40))),"") | Y40: =IF($B40=726,SUM($G40-(SUM($H40:$I40))),"") -> 0 | Z40: =IF($B40=727,SUM($G40-(SUM($H40:$I40))),"") | AA40: =IF($B40=728,SUM($G40-(SUM($H40:$I40))),"") | AB40: =IF($B40=729,SUM($G40-(SUM($H40:$I40))),"") | AC40: =IF($B40=730,SUM($G40-(SUM($H40:$I40))),"") | AD40: =IF($B40=732,SUM($G40-(SUM($H40:$I40))),"") | AE40: =IF($B40=733,SUM($G40-(SUM($H40:$I40))),"") | AF40: =IF($B40=734,SUM($G40-(SUM($H40:$I40))),"") | AG40: =IF($B40=705,SUM($G40-(SUM($H40:$I40))),"") | AH40: =IF($B40=735,SUM($G40-(SUM($H40:$I40))),"") | AI40: =IF($B40=736,SUM($G40-(SUM($H40:$I40))),"") | AJ40: =IF($B40=737,SUM($G40-(SUM($H40:$I40))),"") | AK40: =IF($B40=725,SUM($G40-(SUM($H40:$I40))),"") | AL40: =IF($B40=735,SUM($G40-(SUM($H40:$I40))),"") | AM40: =IF($B40=727,SUM($G40-(SUM($H40:$I40))),"") | AN40: =IF($B40=718,SUM($G40-(SUM($H40:$I40))),"") | AO40: =IF($B40=719,SUM($G40-(SUM($H40:$I40))),"") | AP40: =IF($B40=717,SUM($G40-(SUM($H40:$I40))),"") | AQ40: =IF($B40=722,SUM($G40-(SUM($H40:$I40))),"") | AR40: =IF($B40=708,SUM($G40-(SUM($H40:$I40))),"") | AS40: =IF($B40=701,SUM($G40-(SUM($H40:$I40))),"") | AT40: =IF($B40=702,SUM($G40-(SUM($H40:$I40))),"") | AU40: =IF($B40=731,SUM($G40-(SUM($H40:$I40))),"") | AV40: =IF($B40=730,SUM($G40-(SUM($H40:$I40))),"")
B41: 725 | C41: Power - Fibrewave | D41: =D40+G41 -> 0 | F41: =SUM(H41:AV41)-G41 -> 0 | G41: 0 | H41: =IF(G41/23*3>0,SUM(G41/23*3),"") | I41: =IF(G41/23*3<0,SUM(G41/23*3),"") | J41: =IF($B41=707,SUM($G41-(SUM($H41:$I41))),"") | K41: =IF($B41=706,SUM($G41-(SUM($H41:$I41))),"") | L41: =IF($B41=703,SUM($G41-(SUM($H41:$I41))),"") | M41: =IF($B41=704,SUM($G41-(SUM($H41:$I41))),"") | N41: =IF($B41=709,SUM($G41-(SUM($H41:$I41))),"") | O41: =IF($B41=738,SUM($G41-(SUM($H41:$I41))),"") | P41: =IF($B41=739,SUM($G41-(SUM($H41:$I41))),"") | Q41: =IF($B41=714,SUM($G41-(SUM($H41:$I41))),"") | R41: =IF($B41=710,SUM($G41-(SUM($H41:$I41))),"") | S41: =IF($B41=711,SUM($G41-(SUM($H41:$I41))),"") | T41: =IF($B41=712,SUM($G41-(SUM($H41:$I41))),"") | U41: =IF($B41=713,SUM($G41-(SUM($H41:$I41))),"") | V41: =IF($B41=715,SUM($G41-(SUM($H41:$I41))),"") | W41: =IF($B41=724,SUM($G41-(SUM($H41:$I41))),"") | X41: =IF($B41=725,SUM($G41-(SUM($H41:$I41))),"") -> 0 | Y41: =IF($B41=726,SUM($G41-(SUM($H41:$I41))),"") | Z41: =IF($B41=727,SUM($G41-(SUM($H41:$I41))),"") | AA41: =IF($B41=728,SUM($G41-(SUM($H41:$I41))),"") | AB41: =IF($B41=729,SUM($G41-(SUM($H41:$I41))),"") | AC41: =IF($B41=730,SUM($G41-(SUM($H41:$I41))),"") | AD41: =IF($B41=732,SUM($G41-(SUM($H41:$I41))),"") | AE41: =IF($B41=733,SUM($G41-(SUM($H41:$I41))),"") | AF41: =IF($B41=734,SUM($G41-(SUM($H41:$I41))),"") | AG41: =IF($B41=705,SUM($G41-(SUM($H41:$I41))),"") | AH41: =IF($B41=735,SUM($G41-(SUM($H41:$I41))),"") | AI41: =IF($B41=736,SUM($G41-(SUM($H41:$I41))),"") | AJ41: =IF($B41=737,SUM($G41-(SUM($H41:$I41))),"") | AK41: =IF($B41=725,SUM($G41-(SUM($H41:$I41))),"") -> 0 | AL41: =IF($B41=735,SUM($G41-(SUM($H41:$I41))),"") | AM41: =IF($B41=727,SUM($G41-(SUM($H41:$I41))),"") | AN41: =IF($B41=718,SUM($G41-(SUM($H41:$I41))),"") | AO41: =IF($B41=719,SUM($G41-(SUM($H41:$I41))),"") | AP41: =IF($B41=717,SUM($G41-(SUM($H41:$I41))),"") | AQ41: =IF($B41=722,SUM($G41-(SUM($H41:$I41))),"") | AR41: =IF($B41=708,SUM($G41-(SUM($H41:$I41))),"") | AS41: =IF($B41=701,SUM($G41-(SUM($H41:$I41))),"") | AT41: =IF($B41=702,SUM($G41-(SUM($H41:$I41))),"") | AU41: =IF($B41=731,SUM($G41-(SUM($H41:$I41))),"") | AV41: =IF($B41=730,SUM($G41-(SUM($H41:$I41))),"")
B42: 733 | C42: Body Corp Fees / Council Rates | D42: =D41+G42 -> 0 | F42: =SUM(H42:AV42)-G42 -> 0 | G42: 0 | H42: =IF(G42/23*3>0,SUM(G42/23*3),"") | I42: =IF(G42/23*3<0,SUM(G42/23*3),"") | J42: =IF($B42=707,SUM($G42-(SUM($H42:$I42))),"") | K42: =IF($B42=706,SUM($G42-(SUM($H42:$I42))),"") | L42: =IF($B42=703,SUM($G42-(SUM($H42:$I42))),"") | M42: =IF($B42=704,SUM($G42-(SUM($H42:$I42))),"") | N42: =IF($B42=709,SUM($G42-(SUM($H42:$I42))),"") | O42: =IF($B42=738,SUM($G42-(SUM($H42:$I42))),"") | P42: =IF($B42=739,SUM($G42-(SUM($H42:$I42))),"") | Q42: =IF($B42=714,SUM($G42-(SUM($H42:$I42))),"") | R42: =IF($B42=710,SUM($G42-(SUM($H42:$I42))),"") | S42: =IF($B42=711,SUM($G42-(SUM($H42:$I42))),"") | T42: =IF($B42=712,SUM($G42-(SUM($H42:$I42))),"") | U42: =IF($B42=713,SUM($G42-(SUM($H42:$I42))),"") | V42: =IF($B42=715,SUM($G42-(SUM($H42:$I42))),"") | W42: =IF($B42=724,SUM($G42-(SUM($H42:$I42))),"") | X42: =IF($B42=725,SUM($G42-(SUM($H42:$I42))),"") | Y42: =IF($B42=726,SUM($G42-(SUM($H42:$I42))),"") | Z42: =IF($B42=727,SUM($G42-(SUM($H42:$I42))),"") | AA42: =IF($B42=728,SUM($G42-(SUM($H42:$I42))),"") | AB42: =IF($B42=729,SUM($G42-(SUM($H42:$I42))),"") | AC42: =IF($B42=730,SUM($G42-(SUM($H42:$I42))),"") | AD42: =IF($B42=732,SUM($G42-(SUM($H42:$I42))),"") | AE42: =IF($B42=733,SUM($G42-(SUM($H42:$I42))),"") -> 0 | AF42: =IF($B42=734,SUM($G42-(SUM($H42:$I42))),"") | AG42: =IF($B42=705,SUM($G42-(SUM($H42:$I42))),"") | AH42: =IF($B42=735,SUM($G42-(SUM($H42:$I42))),"") | AI42: =IF($B42=736,SUM($G42-(SUM($H42:$I42))),"") | AJ42: =IF($B42=737,SUM($G42-(SUM($H42:$I42))),"") | AK42: =IF($B42=725,SUM($G42-(SUM($H42:$I42))),"") | AL42: =IF($B42=735,SUM($G42-(SUM($H42:$I42))),"") | AM42: =IF($B42=727,SUM($G42-(SUM($H42:$I42))),"") | AN42: =IF($B42=718,SUM($G42-(SUM($H42:$I42))),"") | AO42: =IF($B42=719,SUM($G42-(SUM($H42:$I42))),"") | AP42: =IF($B42=717,SUM($G42-(SUM($H42:$I42))),"") | AQ42: =IF($B42=722,SUM($G42-(SUM($H42:$I42))),"") | AR42: =IF($B42=708,SUM($G42-(SUM($H42:$I42))),"") | AS42: =IF($B42=701,SUM($G42-(SUM($H42:$I42))),"") | AT42: =IF($B42=702,SUM($G42-(SUM($H42:$I42))),"") | AU42: =IF($B42=731,SUM($G42-(SUM($H42:$I42))),"") | AV42: =IF($B42=730,SUM($G42-(SUM($H42:$I42))),"")
B43: 727 | C43: Internet - Fibrewave | D43: =D42+G43 -> 0 | F43: =SUM(H43:AV43)-G43 -> 0 | G43: 0 | H43: =IF(G43/23*3>0,SUM(G43/23*3),"") | I43: =IF(G43/23*3<0,SUM(G43/23*3),"") | J43: =IF($B43=707,SUM($G43-(SUM($H43:$I43))),"") | K43: =IF($B43=706,SUM($G43-(SUM($H43:$I43))),"") | L43: =IF($B43=703,SUM($G43-(SUM($H43:$I43))),"") | M43: =IF($B43=704,SUM($G43-(SUM($H43:$I43))),"") | N43: =IF($B43=709,SUM($G43-(SUM($H43:$I43))),"") | O43: =IF($B43=738,SUM($G43-(SUM($H43:$I43))),"") | P43: =IF($B43=739,SUM($G43-(SUM($H43:$I43))),"") | Q43: =IF($B43=714,SUM($G43-(SUM($H43:$I43))),"") | R43: =IF($B43=710,SUM($G43-(SUM($H43:$I43))),"") | S43: =IF($B43=711,SUM($G43-(SUM($H43:$I43))),"") | T43: =IF($B43=712,SUM($G43-(SUM($H43:$I43))),"") | U43: =IF($B43=713,SUM($G43-(SUM($H43:$I43))),"") | V43: =IF($B43=715,SUM($G43-(SUM($H43:$I43))),"") | W43: =IF($B43=724,SUM($G43-(SUM($H43:$I43))),"") | X43: =IF($B43=725,SUM($G43-(SUM($H43:$I43))),"") | Y43: =IF($B43=726,SUM($G43-(SUM($H43:$I43))),"") | Z43: =IF($B43=727,SUM($G43-(SUM($H43:$I43))),"") -> 0 | AA43: =IF($B43=728,SUM($G43-(SUM($H43:$I43))),"") | AB43: =IF($B43=729,SUM($G43-(SUM($H43:$I43))),"") | AC43: =IF($B43=730,SUM($G43-(SUM($H43:$I43))),"") | AD43: =IF($B43=732,SUM($G43-(SUM($H43:$I43))),"") | AE43: =IF($B43=733,SUM($G43-(SUM($H43:$I43))),"") | AF43: =IF($B43=734,SUM($G43-(SUM($H43:$I43))),"") | AG43: =IF($B43=705,SUM($G43-(SUM($H43:$I43))),"") | AH43: =IF($B43=735,SUM($G43-(SUM($H43:$I43))),"") | AI43: =IF($B43=736,SUM($G43-(SUM($H43:$I43))),"") | AJ43: =IF($B43=737,SUM($G43-(SUM($H43:$I43))),"") | AK43: =IF($B43=725,SUM($G43-(SUM($H43:$I43))),"") | AL43: =IF($B43=735,SUM($G43-(SUM($H43:$I43))),"") | AM43: =IF($B43=727,SUM($G43-(SUM($H43:$I43))),"") -> 0 | AN43: =IF($B43=718,SUM($G43-(SUM($H43:$I43))),"") | AO43: =IF($B43=719,SUM($G43-(SUM($H43:$I43))),"") | AP43: =IF($B43=717,SUM($G43-(SUM($H43:$I43))),"") | AQ43: =IF($B43=722,SUM($G43-(SUM($H43:$I43))),"") | AR43: =IF($B43=708,SUM($G43-(SUM($H43:$I43))),"") | AS43: =IF($B43=701,SUM($G43-(SUM($H43:$I43))),"") | AT43: =IF($B43=702,SUM($G43-(SUM($H43:$I43))),"") | AU43: =IF($B43=731,SUM($G43-(SUM($H43:$I43))),"") | AV43: =IF($B43=730,SUM($G43-(SUM($H43:$I43))),"")
B44: 728 | C44: Mobile Plan - Tui Mobile NZ | D44: =D43+G44 -> 0 | F44: =SUM(H44:AV44)-G44 -> 0 | G44: 0 | H44: =IF(G44/23*3>0,SUM(G44/23*3),"") | I44: =IF(G44/23*3<0,SUM(G44/23*3),"") | J44: =IF($B44=707,SUM($G44-(SUM($H44:$I44))),"") | K44: =IF($B44=706,SUM($G44-(SUM($H44:$I44))),"") | L44: =IF($B44=703,SUM($G44-(SUM($H44:$I44))),"") | M44: =IF($B44=704,SUM($G44-(SUM($H44:$I44))),"") | N44: =IF($B44=709,SUM($G44-(SUM($H44:$I44))),"") | O44: =IF($B44=738,SUM($G44-(SUM($H44:$I44))),"") | P44: =IF($B44=739,SUM($G44-(SUM($H44:$I44))),"") | Q44: =IF($B44=714,SUM($G44-(SUM($H44:$I44))),"") | R44: =IF($B44=710,SUM($G44-(SUM($H44:$I44))),"") | S44: =IF($B44=711,SUM($G44-(SUM($H44:$I44))),"") | T44: =IF($B44=712,SUM($G44-(SUM($H44:$I44))),"") | U44: =IF($B44=713,SUM($G44-(SUM($H44:$I44))),"") | V44: =IF($B44=715,SUM($G44-(SUM($H44:$I44))),"") | W44: =IF($B44=724,SUM($G44-(SUM($H44:$I44))),"") | X44: =IF($B44=725,SUM($G44-(SUM($H44:$I44))),"") | Y44: =IF($B44=726,SUM($G44-(SUM($H44:$I44))),"") | Z44: =IF($B44=727,SUM($G44-(SUM($H44:$I44))),"") | AA44: =IF($B44=728,SUM($G44-(SUM($H44:$I44))),"") -> 0 | AB44: =IF($B44=729,SUM($G44-(SUM($H44:$I44))),"") | AC44: =IF($B44=730,SUM($G44-(SUM($H44:$I44))),"") | AD44: =IF($B44=732,SUM($G44-(SUM($H44:$I44))),"") | AE44: =IF($B44=733,SUM($G44-(SUM($H44:$I44))),"") | AF44: =IF($B44=734,SUM($G44-(SUM($H44:$I44))),"") | AG44: =IF($B44=705,SUM($G44-(SUM($H44:$I44))),"") | AH44: =IF($B44=735,SUM($G44-(SUM($H44:$I44))),"") | AI44: =IF($B44=736,SUM($G44-(SUM($H44:$I44))),"") | AJ44: =IF($B44=737,SUM($G44-(SUM($H44:$I44))),"") | AK44: =IF($B44=725,SUM($G44-(SUM($H44:$I44))),"") | AL44: =IF($B44=735,SUM($G44-(SUM($H44:$I44))),"") | AM44: =IF($B44=727,SUM($G44-(SUM($H44:$I44))),"") | AN44: =IF($B44=718,SUM($G44-(SUM($H44:$I44))),"") | AO44: =IF($B44=719,SUM($G44-(SUM($H44:$I44))),"") | AP44: =IF($B44=717,SUM($G44-(SUM($H44:$I44))),"") | AQ44: =IF($B44=722,SUM($G44-(SUM($H44:$I44))),"") | AR44: =IF($B44=708,SUM($G44-(SUM($H44:$I44))),"") | AS44: =IF($B44=701,SUM($G44-(SUM($H44:$I44))),"") | AT44: =IF($B44=702,SUM($G44-(SUM($H44:$I44))),"") | AU44: =IF($B44=731,SUM($G44-(SUM($H44:$I44))),"") | AV44: =IF($B44=730,SUM($G44-(SUM($H44:$I44))),"")
B45: 729 | C45: Car Park Fees | D45: =D44+G45 -> 0 | F45: =SUM(H45:AV45)-G45 -> 0 | G45: 0 | H45: =IF(G45/23*3>0,SUM(G45/23*3),"") | I45: =IF(G45/23*3<0,SUM(G45/23*3),"") | J45: =IF($B45=707,SUM($G45-(SUM($H45:$I45))),"") | K45: =IF($B45=706,SUM($G45-(SUM($H45:$I45))),"") | L45: =IF($B45=703,SUM($G45-(SUM($H45:$I45))),"") | M45: =IF($B45=704,SUM($G45-(SUM($H45:$I45))),"") | N45: =IF($B45=709,SUM($G45-(SUM($H45:$I45))),"") | O45: =IF($B45=738,SUM($G45-(SUM($H45:$I45))),"") | P45: =IF($B45=739,SUM($G45-(SUM($H45:$I45))),"") | Q45: =IF($B45=714,SUM($G45-(SUM($H45:$I45))),"") | R45: =IF($B45=710,SUM($G45-(SUM($H45:$I45))),"") | S45: =IF($B45=711,SUM($G45-(SUM($H45:$I45))),"") | T45: =IF($B45=712,SUM($G45-(SUM($H45:$I45))),"") | U45: =IF($B45=713,SUM($G45-(SUM($H45:$I45))),"") | V45: =IF($B45=715,SUM($G45-(SUM($H45:$I45))),"") | W45: =IF($B45=724,SUM($G45-(SUM($H45:$I45))),"") | X45: =IF($B45=725,SUM($G45-(SUM($H45:$I45))),"") | Y45: =IF($B45=726,SUM($G45-(SUM($H45:$I45))),"") | Z45: =IF($B45=727,SUM($G45-(SUM($H45:$I45))),"") | AA45: =IF($B45=728,SUM($G45-(SUM($H45:$I45))),"") | AB45: =IF($B45=729,SUM($G45-(SUM($H45:$I45))),"") -> 0 | AC45: =IF($B45=730,SUM($G45-(SUM($H45:$I45))),"") | AD45: =IF($B45=732,SUM($G45-(SUM($H45:$I45))),"") | AE45: =IF($B45=733,SUM($G45-(SUM($H45:$I45))),"") | AF45: =IF($B45=734,SUM($G45-(SUM($H45:$I45))),"") | AG45: =IF($B45=705,SUM($G45-(SUM($H45:$I45))),"") | AH45: =IF($B45=735,SUM($G45-(SUM($H45:$I45))),"") | AI45: =IF($B45=736,SUM($G45-(SUM($H45:$I45))),"") | AJ45: =IF($B45=737,SUM($G45-(SUM($H45:$I45))),"") | AK45: =IF($B45=725,SUM($G45-(SUM($H45:$I45))),"") | AL45: =IF($B45=735,SUM($G45-(SUM($H45:$I45))),"") | AM45: =IF($B45=727,SUM($G45-(SUM($H45:$I45))),"") | AN45: =IF($B45=718,SUM($G45-(SUM($H45:$I45))),"") | AO45: =IF($B45=719,SUM($G45-(SUM($H45:$I45))),"") | AP45: =IF($B45=717,SUM($G45-(SUM($H45:$I45))),"") | AQ45: =IF($B45=722,SUM($G45-(SUM($H45:$I45))),"") | AR45: =IF($B45=708,SUM($G45-(SUM($H45:$I45))),"") | AS45: =IF($B45=701,SUM($G45-(SUM($H45:$I45))),"") | AT45: =IF($B45=702,SUM($G45-(SUM($H45:$I45))),"") | AU45: =IF($B45=731,SUM($G45-(SUM($H45:$I45))),"") | AV45: =IF($B45=730,SUM($G45-(SUM($H45:$I45))),"")
B46: 734 | C46: Home Office Expenses | D46: =D45+G46 -> 0 | F46: =SUM(H46:AV46)-G46 -> 0 | G46: 0 | H46: =IF(G46/23*3>0,SUM(G46/23*3),"") | I46: =IF(G46/23*3<0,SUM(G46/23*3),"") | J46: =IF($B46=707,SUM($G46-(SUM($H46:$I46))),"") | K46: =IF($B46=706,SUM($G46-(SUM($H46:$I46))),"") | L46: =IF($B46=703,SUM($G46-(SUM($H46:$I46))),"") | M46: =IF($B46=704,SUM($G46-(SUM($H46:$I46))),"") | N46: =IF($B46=709,SUM($G46-(SUM($H46:$I46))),"") | O46: =IF($B46=738,SUM($G46-(SUM($H46:$I46))),"") | P46: =IF($B46=739,SUM($G46-(SUM($H46:$I46))),"") | Q46: =IF($B46=714,SUM($G46-(SUM($H46:$I46))),"") | R46: =IF($B46=710,SUM($G46-(SUM($H46:$I46))),"") | S46: =IF($B46=711,SUM($G46-(SUM($H46:$I46))),"") | T46: =IF($B46=712,SUM($G46-(SUM($H46:$I46))),"") | U46: =IF($B46=713,SUM($G46-(SUM($H46:$I46))),"") | V46: =IF($B46=715,SUM($G46-(SUM($H46:$I46))),"") | W46: =IF($B46=724,SUM($G46-(SUM($H46:$I46))),"") | X46: =IF($B46=725,SUM($G46-(SUM($H46:$I46))),"") | Y46: =IF($B46=726,SUM($G46-(SUM($H46:$I46))),"") | Z46: =IF($B46=727,SUM($G46-(SUM($H46:$I46))),"") | AA46: =IF($B46=728,SUM($G46-(SUM($H46:$I46))),"") | AB46: =IF($B46=729,SUM($G46-(SUM($H46:$I46))),"") | AC46: =IF($B46=730,SUM($G46-(SUM($H46:$I46))),"") | AD46: =IF($B46=732,SUM($G46-(SUM($H46:$I46))),"") | AE46: =IF($B46=733,SUM($G46-(SUM($H46:$I46))),"") | AF46: =IF($B46=734,SUM($G46-(SUM($H46:$I46))),"") -> 0 | AG46: =IF($B46=705,SUM($G46-(SUM($H46:$I46))),"") | AH46: =IF($B46=735,SUM($G46-(SUM($H46:$I46))),"") | AI46: =IF($B46=736,SUM($G46-(SUM($H46:$I46))),"") | AJ46: =IF($B46=737,SUM($G46-(SUM($H46:$I46))),"") | AK46: =IF($B46=725,SUM($G46-(SUM($H46:$I46))),"") | AL46: =IF($B46=735,SUM($G46-(SUM($H46:$I46))),"") | AM46: =IF($B46=727,SUM($G46-(SUM($H46:$I46))),"") | AN46: =IF($B46=718,SUM($G46-(SUM($H46:$I46))),"") | AO46: =IF($B46=719,SUM($G46-(SUM($H46:$I46))),"") | AP46: =IF($B46=717,SUM($G46-(SUM($H46:$I46))),"") | AQ46: =IF($B46=722,SUM($G46-(SUM($H46:$I46))),"") | AR46: =IF($B46=708,SUM($G46-(SUM($H46:$I46))),"") | AS46: =IF($B46=701,SUM($G46-(SUM($H46:$I46))),"") | AT46: =IF($B46=702,SUM($G46-(SUM($H46:$I46))),"") | AU46: =IF($B46=731,SUM($G46-(SUM($H46:$I46))),"") | AV46: =IF($B46=730,SUM($G46-(SUM($H46:$I46))),"")
B47: 734 | C47: Home Office Expenses | D47: =D46+G47 -> 0 | F47: =SUM(H47:AV47)-G47 -> 0 | G47: 0 | H47: =IF(G47/23*3>0,SUM(G47/23*3),"") | I47: =IF(G47/23*3<0,SUM(G47/23*3),"") | J47: =IF($B47=707,SUM($G47-(SUM($H47:$I47))),"") | K47: =IF($B47=706,SUM($G47-(SUM($H47:$I47))),"") | L47: =IF($B47=703,SUM($G47-(SUM($H47:$I47))),"") | M47: =IF($B47=704,SUM($G47-(SUM($H47:$I47))),"") | N47: =IF($B47=709,SUM($G47-(SUM($H47:$I47))),"") | O47: =IF($B47=738,SUM($G47-(SUM($H47:$I47))),"") | P47: =IF($B47=739,SUM($G47-(SUM($H47:$I47))),"") | Q47: =IF($B47=714,SUM($G47-(SUM($H47:$I47))),"") | R47: =IF($B47=710,SUM($G47-(SUM($H47:$I47))),"") | S47: =IF($B47=711,SUM($G47-(SUM($H47:$I47))),"") | T47: =IF($B47=712,SUM($G47-(SUM($H47:$I47))),"") | U47: =IF($B47=713,SUM($G47-(SUM($H47:$I47))),"") | V47: =IF($B47=715,SUM($G47-(SUM($H47:$I47))),"") | W47: =IF($B47=724,SUM($G47-(SUM($H47:$I47))),"") | X47: =IF($B47=725,SUM($G47-(SUM($H47:$I47))),"") | Y47: =IF($B47=726,SUM($G47-(SUM($H47:$I47))),"") | Z47: =IF($B47=727,SUM($G47-(SUM($H47:$I47))),"") | AA47: =IF($B47=728,SUM($G47-(SUM($H47:$I47))),"") | AB47: =IF($B47=729,SUM($G47-(SUM($H47:$I47))),"") | AC47: =IF($B47=730,SUM($G47-(SUM($H47:$I47))),"") | AD47: =IF($B47=732,SUM($G47-(SUM($H47:$I47))),"") | AE47: =IF($B47=733,SUM($G47-(SUM($H47:$I47))),"") | AF47: =IF($B47=734,SUM($G47-(SUM($H47:$I47))),"") -> 0 | AG47: =IF($B47=705,SUM($G47-(SUM($H47:$I47))),"") | AH47: =IF($B47=735,SUM($G47-(SUM($H47:$I47))),"") | AI47: =IF($B47=736,SUM($G47-(SUM($H47:$I47))),"") | AJ47: =IF($B47=737,SUM($G47-(SUM($H47:$I47))),"") | AK47: =IF($B47=725,SUM($G47-(SUM($H47:$I47))),"") | AL47: =IF($B47=735,SUM($G47-(SUM($H47:$I47))),"") | AM47: =IF($B47=727,SUM($G47-(SUM($H47:$I47))),"") | AN47: =IF($B47=718,SUM($G47-(SUM($H47:$I47))),"") | AO47: =IF($B47=719,SUM($G47-(SUM($H47:$I47))),"") | AP47: =IF($B47=717,SUM($G47-(SUM($H47:$I47))),"") | AQ47: =IF($B47=722,SUM($G47-(SUM($H47:$I47))),"") | AR47: =IF($B47=708,SUM($G47-(SUM($H47:$I47))),"") | AS47: =IF($B47=701,SUM($G47-(SUM($H47:$I47))),"") | AT47: =IF($B47=702,SUM($G47-(SUM($H47:$I47))),"") | AU47: =IF($B47=731,SUM($G47-(SUM($H47:$I47))),"") | AV47: =IF($B47=730,SUM($G47-(SUM($H47:$I47))),"")
B48: 734 | C48: Home Office Expenses | D48: =D47+G48 -> 0 | F48: =SUM(H48:AV48)-G48 -> 0 | G48: 0 | H48: =IF(G48/23*3>0,SUM(G48/23*3),"") | I48: =IF(G48/23*3<0,SUM(G48/23*3),"") | J48: =IF($B48=707,SUM($G48-(SUM($H48:$I48))),"") | K48: =IF($B48=706,SUM($G48-(SUM($H48:$I48))),"") | L48: =IF($B48=703,SUM($G48-(SUM($H48:$I48))),"") | M48: =IF($B48=704,SUM($G48-(SUM($H48:$I48))),"") | N48: =IF($B48=709,SUM($G48-(SUM($H48:$I48))),"") | O48: =IF($B48=738,SUM($G48-(SUM($H48:$I48))),"") | P48: =IF($B48=739,SUM($G48-(SUM($H48:$I48))),"") | Q48: =IF($B48=714,SUM($G48-(SUM($H48:$I48))),"") | R48: =IF($B48=710,SUM($G48-(SUM($H48:$I48))),"") | S48: =IF($B48=711,SUM($G48-(SUM($H48:$I48))),"") | T48: =IF($B48=712,SUM($G48-(SUM($H48:$I48))),"") | U48: =IF($B48=713,SUM($G48-(SUM($H48:$I48))),"") | V48: =IF($B48=715,SUM($G48-(SUM($H48:$I48))),"") | W48: =IF($B48=724,SUM($G48-(SUM($H48:$I48))),"") | X48: =IF($B48=725,SUM($G48-(SUM($H48:$I48))),"") | Y48: =IF($B48=726,SUM($G48-(SUM($H48:$I48))),"") | Z48: =IF($B48=727,SUM($G48-(SUM($H48:$I48))),"") | AA48: =IF($B48=728,SUM($G48-(SUM($H48:$I48))),"") | AB48: =IF($B48=729,SUM($G48-(SUM($H48:$I48))),"") | AC48: =IF($B48=730,SUM($G48-(SUM($H48:$I48))),"") | AD48: =IF($B48=732,SUM($G48-(SUM($H48:$I48))),"") | AE48: =IF($B48=733,SUM($G48-(SUM($H48:$I48))),"") | AF48: =IF($B48=734,SUM($G48-(SUM($H48:$I48))),"") -> 0 | AG48: =IF($B48=705,SUM($G48-(SUM($H48:$I48))),"") | AH48: =IF($B48=735,SUM($G48-(SUM($H48:$I48))),"") | AI48: =IF($B48=736,SUM($G48-(SUM($H48:$I48))),"") | AJ48: =IF($B48=737,SUM($G48-(SUM($H48:$I48))),"") | AK48: =IF($B48=725,SUM($G48-(SUM($H48:$I48))),"") | AL48: =IF($B48=735,SUM($G48-(SUM($H48:$I48))),"") | AM48: =IF($B48=727,SUM($G48-(SUM($H48:$I48))),"") | AN48: =IF($B48=718,SUM($G48-(SUM($H48:$I48))),"") | AO48: =IF($B48=719,SUM($G48-(SUM($H48:$I48))),"") | AP48: =IF($B48=717,SUM($G48-(SUM($H48:$I48))),"") | AQ48: =IF($B48=722,SUM($G48-(SUM($H48:$I48))),"") | AR48: =IF($B48=708,SUM($G48-(SUM($H48:$I48))),"") | AS48: =IF($B48=701,SUM($G48-(SUM($H48:$I48))),"") | AT48: =IF($B48=702,SUM($G48-(SUM($H48:$I48))),"") | AU48: =IF($B48=731,SUM($G48-(SUM($H48:$I48))),"") | AV48: =IF($B48=730,SUM($G48-(SUM($H48:$I48))),"")
B49: 734 | C49: Home Office Expenses | D49: =D48+G49 -> 0 | F49: =SUM(H49:AV49)-G49 -> 0 | G49: 0 | H49: =IF(G49/23*3>0,SUM(G49/23*3),"") | I49: =IF(G49/23*3<0,SUM(G49/23*3),"") | J49: =IF($B49=707,SUM($G49-(SUM($H49:$I49))),"") | K49: =IF($B49=706,SUM($G49-(SUM($H49:$I49))),"") | L49: =IF($B49=703,SUM($G49-(SUM($H49:$I49))),"") | M49: =IF($B49=704,SUM($G49-(SUM($H49:$I49))),"") | N49: =IF($B49=709,SUM($G49-(SUM($H49:$I49))),"") | O49: =IF($B49=738,SUM($G49-(SUM($H49:$I49))),"") | P49: =IF($B49=739,SUM($G49-(SUM($H49:$I49))),"") | Q49: =IF($B49=714,SUM($G49-(SUM($H49:$I49))),"") | R49: =IF($B49=710,SUM($G49-(SUM($H49:$I49))),"") | S49: =IF($B49=711,SUM($G49-(SUM($H49:$I49))),"") | T49: =IF($B49=712,SUM($G49-(SUM($H49:$I49))),"") | U49: =IF($B49=713,SUM($G49-(SUM($H49:$I49))),"") | V49: =IF($B49=715,SUM($G49-(SUM($H49:$I49))),"") | W49: =IF($B49=724,SUM($G49-(SUM($H49:$I49))),"") | X49: =IF($B49=725,SUM($G49-(SUM($H49:$I49))),"") | Y49: =IF($B49=726,SUM($G49-(SUM($H49:$I49))),"") | Z49: =IF($B49=727,SUM($G49-(SUM($H49:$I49))),"") | AA49: =IF($B49=728,SUM($G49-(SUM($H49:$I49))),"") | AB49: =IF($B49=729,SUM($G49-(SUM($H49:$I49))),"") | AC49: =IF($B49=730,SUM($G49-(SUM($H49:$I49))),"") | AD49: =IF($B49=732,SUM($G49-(SUM($H49:$I49))),"") | AE49: =IF($B49=733,SUM($G49-(SUM($H49:$I49))),"") | AF49: =IF($B49=734,SUM($G49-(SUM($H49:$I49))),"") -> 0 | AG49: =IF($B49=705,SUM($G49-(SUM($H49:$I49))),"") | AH49: =IF($B49=735,SUM($G49-(SUM($H49:$I49))),"") | AI49: =IF($B49=736,SUM($G49-(SUM($H49:$I49))),"") | AJ49: =IF($B49=737,SUM($G49-(SUM($H49:$I49))),"") | AK49: =IF($B49=725,SUM($G49-(SUM($H49:$I49))),"") | AL49: =IF($B49=735,SUM($G49-(SUM($H49:$I49))),"") | AM49: =IF($B49=727,SUM($G49-(SUM($H49:$I49))),"") | AN49: =IF($B49=718,SUM($G49-(SUM($H49:$I49))),"") | AO49: =IF($B49=719,SUM($G49-(SUM($H49:$I49))),"") | AP49: =IF($B49=717,SUM($G49-(SUM($H49:$I49))),"") | AQ49: =IF($B49=722,SUM($G49-(SUM($H49:$I49))),"") | AR49: =IF($B49=708,SUM($G49-(SUM($H49:$I49))),"") | AS49: =IF($B49=701,SUM($G49-(SUM($H49:$I49))),"") | AT49: =IF($B49=702,SUM($G49-(SUM($H49:$I49))),"") | AU49: =IF($B49=731,SUM($G49-(SUM($H49:$I49))),"") | AV49: =IF($B49=730,SUM($G49-(SUM($H49:$I49))),"")
B50: 724 | C50: Apartment Rent | D50: =D49+G50 -> 0 | F50: =SUM(H50:AV50)-G50 -> 0 | G50: 0 | H50: =IF(G50/23*3>0,SUM(G50/23*3),"") | J50: =IF($B50=707,SUM($G50-(SUM($H50:$I50))),"") | K50: =IF($B50=706,SUM($G50-(SUM($H50:$I50))),"") | L50: =IF($B50=703,SUM($G50-(SUM($H50:$I50))),"") | M50: =IF($B50=704,SUM($G50-(SUM($H50:$I50))),"") | N50: =IF($B50=709,SUM($G50-(SUM($H50:$I50))),"") | O50: =IF($B50=738,SUM($G50-(SUM($H50:$I50))),"") | P50: =IF($B50=739,SUM($G50-(SUM($H50:$I50))),"") | Q50: =IF($B50=714,SUM($G50-(SUM($H50:$I50))),"") | R50: =IF($B50=710,SUM($G50-(SUM($H50:$I50))),"") | S50: =IF($B50=711,SUM($G50-(SUM($H50:$I50))),"") | T50: =IF($B50=712,SUM($G50-(SUM($H50:$I50))),"") | U50: =IF($B50=713,SUM($G50-(SUM($H50:$I50))),"") | V50: =IF($B50=715,SUM($G50-(SUM($H50:$I50))),"") | W50: =IF($B50=724,SUM($G50-(SUM($H50:$I50))),"") -> 0 | X50: =IF($B50=725,SUM($G50-(SUM($H50:$I50))),"") | Y50: =IF($B50=726,SUM($G50-(SUM($H50:$I50))),"") | Z50: =IF($B50=727,SUM($G50-(SUM($H50:$I50))),"") | AA50: =IF($B50=728,SUM($G50-(SUM($H50:$I50))),"") | AB50: =IF($B50=729,SUM($G50-(SUM($H50:$I50))),"") | AC50: =IF($B50=730,SUM($G50-(SUM($H50:$I50))),"") | AD50: =IF($B50=732,SUM($G50-(SUM($H50:$I50))),"") | AE50: =IF($B50=733,SUM($G50-(SUM($H50:$I50))),"") | AF50: =IF($B50=734,SUM($G50-(SUM($H50:$I50))),"") | AG50: =IF($B50=705,SUM($G50-(SUM($H50:$I50))),"") | AH50: =IF($B50=735,SUM($G50-(SUM($H50:$I50))),"") | AI50: =IF($B50=736,SUM($G50-(SUM($H50:$I50))),"") | AJ50: =IF($B50=737,SUM($G50-(SUM($H50:$I50))),"") | AK50: =IF($B50=725,SUM($G50-(SUM($H50:$I50))),"") | AL50: =IF($B50=735,SUM($G50-(SUM($H50:$I50))),"") | AM50: =IF($B50=727,SUM($G50-(SUM($H50:$I50))),"") | AN50: =IF($B50=718,SUM($G50-(SUM($H50:$I50))),"") | AO50: =IF($B50=719,SUM($G50-(SUM($H50:$I50))),"") | AP50: =IF($B50=717,SUM($G50-(SUM($H50:$I50))),"") | AQ50: =IF($B50=722,SUM($G50-(SUM($H50:$I50))),"") | AR50: =IF($B50=708,SUM($G50-(SUM($H50:$I50))),"") | AS50: =IF($B50=701,SUM($G50-(SUM($H50:$I50))),"") | AT50: =IF($B50=702,SUM($G50-(SUM($H50:$I50))),"") | AU50: =IF($B50=731,SUM($G50-(SUM($H50:$I50))),"") | AV50: =IF($B50=730,SUM($G50-(SUM($H50:$I50))),"")
B51: 710 | C51: Bank Fees | D51: =D50+G51 -> 0 | F51: =SUM(H51:AV51)-G51 -> 0 | G51: 0 | H51: =IF(G51/23*3>0,SUM(G51/23*3),"") | J51: =IF($B51=707,SUM($G51-(SUM($H51:$I51))),"") | K51: =IF($B51=706,SUM($G51-(SUM($H51:$I51))),"") | L51: =IF($B51=703,SUM($G51-(SUM($H51:$I51))),"") | M51: =IF($B51=704,SUM($G51-(SUM($H51:$I51))),"") | N51: =IF($B51=709,SUM($G51-(SUM($H51:$I51))),"") | O51: =IF($B51=738,SUM($G51-(SUM($H51:$I51))),"") | P51: =IF($B51=739,SUM($G51-(SUM($H51:$I51))),"") | Q51: =IF($B51=714,SUM($G51-(SUM($H51:$I51))),"") | R51: =IF($B51=710,SUM($G51-(SUM($H51:$I51))),"") -> 0 | S51: =IF($B51=711,SUM($G51-(SUM($H51:$I51))),"") | T51: =IF($B51=712,SUM($G51-(SUM($H51:$I51))),"") | U51: =IF($B51=713,SUM($G51-(SUM($H51:$I51))),"") | V51: =IF($B51=715,SUM($G51-(SUM($H51:$I51))),"") | W51: =IF($B51=724,SUM($G51-(SUM($H51:$I51))),"") | X51: =IF($B51=725,SUM($G51-(SUM($H51:$I51))),"") | Y51: =IF($B51=726,SUM($G51-(SUM($H51:$I51))),"") | Z51: =IF($B51=727,SUM($G51-(SUM($H51:$I51))),"") | AA51: =IF($B51=728,SUM($G51-(SUM($H51:$I51))),"") | AB51: =IF($B51=729,SUM($G51-(SUM($H51:$I51))),"") | AC51: =IF($B51=730,SUM($G51-(SUM($H51:$I51))),"") | AD51: =IF($B51=732,SUM($G51-(SUM($H51:$I51))),"") | AE51: =IF($B51=733,SUM($G51-(SUM($H51:$I51))),"") | AF51: =IF($B51=734,SUM($G51-(SUM($H51:$I51))),"") | AG51: =IF($B51=705,SUM($G51-(SUM($H51:$I51))),"") | AH51: =IF($B51=735,SUM($G51-(SUM($H51:$I51))),"") | AI51: =IF($B51=736,SUM($G51-(SUM($H51:$I51))),"") | AJ51: =IF($B51=737,SUM($G51-(SUM($H51:$I51))),"") | AK51: =IF($B51=725,SUM($G51-(SUM($H51:$I51))),"") | AL51: =IF($B51=735,SUM($G51-(SUM($H51:$I51))),"") | AM51: =IF($B51=727,SUM($G51-(SUM($H51:$I51))),"") | AN51: =IF($B51=718,SUM($G51-(SUM($H51:$I51))),"") | AO51: =IF($B51=719,SUM($G51-(SUM($H51:$I51))),"") | AP51: =IF($B51=717,SUM($G51-(SUM($H51:$I51))),"") | AQ51: =IF($B51=722,SUM($G51-(SUM($H51:$I51))),"") | AR51: =IF($B51=708,SUM($G51-(SUM($H51:$I51))),"") | AS51: =IF($B51=701,SUM($G51-(SUM($H51:$I51))),"") | AT51: =IF($B51=702,SUM($G51-(SUM($H51:$I51))),"") | AU51: =IF($B51=731,SUM($G51-(SUM($H51:$I51))),"") | AV51: =IF($B51=730,SUM($G51-(SUM($H51:$I51))),"")
B52: 739 | C52: Online Tech Subscriptions (NO GST) | D52: =D51+G52 -> 0 | F52: =SUM(H52:AV52)-G52 -> 0 | G52: 0 | H52: =IF(G52/23*3>0,SUM(G52/23*3),"") | I52: 0 | J52: =IF($B52=707,SUM($G52-(SUM($H52:$I52))),"") | K52: =IF($B52=706,SUM($G52-(SUM($H52:$I52))),"") | L52: =IF($B52=703,SUM($G52-(SUM($H52:$I52))),"") | M52: =IF($B52=704,SUM($G52-(SUM($H52:$I52))),"") | N52: =IF($B52=709,SUM($G52-(SUM($H52:$I52))),"") | O52: =IF($B52=738,SUM($G52-(SUM($H52:$I52))),"") | P52: =IF($B52=739,SUM($G52-(SUM($H52:$I52))),"") -> 0 | Q52: =IF($B52=714,SUM($G52-(SUM($H52:$I52))),"") | R52: =IF($B52=710,SUM($G52-(SUM($H52:$I52))),"") | S52: =IF($B52=711,SUM($G52-(SUM($H52:$I52))),"") | T52: =IF($B52=712,SUM($G52-(SUM($H52:$I52))),"") | U52: =IF($B52=713,SUM($G52-(SUM($H52:$I52))),"") | V52: =IF($B52=715,SUM($G52-(SUM($H52:$I52))),"") | W52: =IF($B52=724,SUM($G52-(SUM($H52:$I52))),"") | X52: =IF($B52=725,SUM($G52-(SUM($H52:$I52))),"") | Y52: =IF($B52=726,SUM($G52-(SUM($H52:$I52))),"") | Z52: =IF($B52=727,SUM($G52-(SUM($H52:$I52))),"") | AA52: =IF($B52=728,SUM($G52-(SUM($H52:$I52))),"") | AB52: =IF($B52=729,SUM($G52-(SUM($H52:$I52))),"") | AC52: =IF($B52=730,SUM($G52-(SUM($H52:$I52))),"") | AD52: =IF($B52=732,SUM($G52-(SUM($H52:$I52))),"") | AE52: =IF($B52=733,SUM($G52-(SUM($H52:$I52))),"") | AF52: =IF($B52=734,SUM($G52-(SUM($H52:$I52))),"") | AG52: =IF($B52=705,SUM($G52-(SUM($H52:$I52))),"") | AH52: =IF($B52=735,SUM($G52-(SUM($H52:$I52))),"") | AI52: =IF($B52=736,SUM($G52-(SUM($H52:$I52))),"") | AJ52: =IF($B52=737,SUM($G52-(SUM($H52:$I52))),"") | AK52: =IF($B52=725,SUM($G52-(SUM($H52:$I52))),"") | AL52: =IF($B52=735,SUM($G52-(SUM($H52:$I52))),"") | AM52: =IF($B52=727,SUM($G52-(SUM($H52:$I52))),"") | AN52: =IF($B52=718,SUM($G52-(SUM($H52:$I52))),"") | AO52: =IF($B52=719,SUM($G52-(SUM($H52:$I52))),"") | AP52: =IF($B52=717,SUM($G52-(SUM($H52:$I52))),"") | AQ52: =IF($B52=722,SUM($G52-(SUM($H52:$I52))),"") | AR52: =IF($B52=708,SUM($G52-(SUM($H52:$I52))),"") | AS52: =IF($B52=701,SUM($G52-(SUM($H52:$I52))),"") | AT52: =IF($B52=702,SUM($G52-(SUM($H52:$I52))),"") | AU52: =IF($B52=731,SUM($G52-(SUM($H52:$I52))),"") | AV52: =IF($B52=730,SUM($G52-(SUM($H52:$I52))),"")
B53: 739 | C53: Online Tech Subscriptions (NO GST) | D53: =D52+G53 -> 0 | F53: =SUM(H53:AV53)-G53 -> 0 | G53: 0 | H53: =IF(G53/23*3>0,SUM(G53/23*3),"") | I53: 0 | J53: =IF($B53=707,SUM($G53-(SUM($H53:$I53))),"") | K53: =IF($B53=706,SUM($G53-(SUM($H53:$I53))),"") | L53: =IF($B53=703,SUM($G53-(SUM($H53:$I53))),"") | M53: =IF($B53=704,SUM($G53-(SUM($H53:$I53))),"") | N53: =IF($B53=709,SUM($G53-(SUM($H53:$I53))),"") | O53: =IF($B53=738,SUM($G53-(SUM($H53:$I53))),"") | P53: =IF($B53=739,SUM($G53-(SUM($H53:$I53))),"") -> 0 | Q53: =IF($B53=714,SUM($G53-(SUM($H53:$I53))),"") | R53: =IF($B53=710,SUM($G53-(SUM($H53:$I53))),"") | S53: =IF($B53=711,SUM($G53-(SUM($H53:$I53))),"") | T53: =IF($B53=712,SUM($G53-(SUM($H53:$I53))),"") | U53: =IF($B53=713,SUM($G53-(SUM($H53:$I53))),"") | V53: =IF($B53=715,SUM($G53-(SUM($H53:$I53))),"") | W53: =IF($B53=724,SUM($G53-(SUM($H53:$I53))),"") | X53: =IF($B53=725,SUM($G53-(SUM($H53:$I53))),"") | Y53: =IF($B53=726,SUM($G53-(SUM($H53:$I53))),"") | Z53: =IF($B53=727,SUM($G53-(SUM($H53:$I53))),"") | AA53: =IF($B53=728,SUM($G53-(SUM($H53:$I53))),"") | AB53: =IF($B53=729,SUM($G53-(SUM($H53:$I53))),"") | AC53: =IF($B53=730,SUM($G53-(SUM($H53:$I53))),"") | AD53: =IF($B53=732,SUM($G53-(SUM($H53:$I53))),"") | AE53: =IF($B53=733,SUM($G53-(SUM($H53:$I53))),"") | AF53: =IF($B53=734,SUM($G53-(SUM($H53:$I53))),"") | AG53: =IF($B53=705,SUM($G53-(SUM($H53:$I53))),"") | AH53: =IF($B53=735,SUM($G53-(SUM($H53:$I53))),"") | AI53: =IF($B53=736,SUM($G53-(SUM($H53:$I53))),"") | AJ53: =IF($B53=737,SUM($G53-(SUM($H53:$I53))),"") | AK53: =IF($B53=725,SUM($G53-(SUM($H53:$I53))),"") | AL53: =IF($B53=735,SUM($G53-(SUM($H53:$I53))),"") | AM53: =IF($B53=727,SUM($G53-(SUM($H53:$I53))),"") | AN53: =IF($B53=718,SUM($G53-(SUM($H53:$I53))),"") | AO53: =IF($B53=719,SUM($G53-(SUM($H53:$I53))),"") | AP53: =IF($B53=717,SUM($G53-(SUM($H53:$I53))),"") | AQ53: =IF($B53=722,SUM($G53-(SUM($H53:$I53))),"") | AR53: =IF($B53=708,SUM($G53-(SUM($H53:$I53))),"") | AS53: =IF($B53=701,SUM($G53-(SUM($H53:$I53))),"") | AT53: =IF($B53=702,SUM($G53-(SUM($H53:$I53))),"") | AU53: =IF($B53=731,SUM($G53-(SUM($H53:$I53))),"") | AV53: =IF($B53=730,SUM($G53-(SUM($H53:$I53))),"")
B54: 711 | C54: Accountant Fee (Accountancy) | D54: =D53+G54 -> 0 | F54: =SUM(H54:AV54)-G54 -> 0 | G54: 0 | H54: =IF(G54/23*3>0,SUM(G54/23*3),"") | I54: =IF(G54/23*3<0,SUM(G54/23*3),"") | J54: =IF($B54=707,SUM($G54-(SUM($H54:$I54))),"") | K54: =IF($B54=706,SUM($G54-(SUM($H54:$I54))),"") | L54: =IF($B54=703,SUM($G54-(SUM($H54:$I54))),"") | M54: =IF($B54=704,SUM($G54-(SUM($H54:$I54))),"") | N54: =IF($B54=709,SUM($G54-(SUM($H54:$I54))),"") | O54: =IF($B54=738,SUM($G54-(SUM($H54:$I54))),"") | P54: =IF($B54=739,SUM($G54-(SUM($H54:$I54))),"") | Q54: =IF($B54=714,SUM($G54-(SUM($H54:$I54))),"") | R54: =IF($B54=710,SUM($G54-(SUM($H54:$I54))),"") | S54: =IF($B54=711,SUM($G54-(SUM($H54:$I54))),"") -> 0 | T54: =IF($B54=712,SUM($G54-(SUM($H54:$I54))),"") | U54: =IF($B54=713,SUM($G54-(SUM($H54:$I54))),"") | V54: =IF($B54=715,SUM($G54-(SUM($H54:$I54))),"") | W54: =IF($B54=724,SUM($G54-(SUM($H54:$I54))),"") | X54: =IF($B54=725,SUM($G54-(SUM($H54:$I54))),"") | Y54: =IF($B54=726,SUM($G54-(SUM($H54:$I54))),"") | Z54: =IF($B54=727,SUM($G54-(SUM($H54:$I54))),"") | AA54: =IF($B54=728,SUM($G54-(SUM($H54:$I54))),"") | AB54: =IF($B54=729,SUM($G54-(SUM($H54:$I54))),"") | AC54: =IF($B54=730,SUM($G54-(SUM($H54:$I54))),"") | AD54: =IF($B54=732,SUM($G54-(SUM($H54:$I54))),"") | AE54: =IF($B54=733,SUM($G54-(SUM($H54:$I54))),"") | AF54: =IF($B54=734,SUM($G54-(SUM($H54:$I54))),"") | AG54: =IF($B54=705,SUM($G54-(SUM($H54:$I54))),"") | AH54: =IF($B54=735,SUM($G54-(SUM($H54:$I54))),"") | AI54: =IF($B54=736,SUM($G54-(SUM($H54:$I54))),"") | AJ54: =IF($B54=737,SUM($G54-(SUM($H54:$I54))),"") | AK54: =IF($B54=725,SUM($G54-(SUM($H54:$I54))),"") | AL54: =IF($B54=735,SUM($G54-(SUM($H54:$I54))),"") | AM54: =IF($B54=727,SUM($G54-(SUM($H54:$I54))),"") | AN54: =IF($B54=718,SUM($G54-(SUM($H54:$I54))),"") | AO54: =IF($B54=719,SUM($G54-(SUM($H54:$I54))),"") | AP54: =IF($B54=717,SUM($G54-(SUM($H54:$I54))),"") | AQ54: =IF($B54=722,SUM($G54-(SUM($H54:$I54))),"") | AR54: =IF($B54=708,SUM($G54-(SUM($H54:$I54))),"") | AS54: =IF($B54=701,SUM($G54-(SUM($H54:$I54))),"") | AT54: =IF($B54=702,SUM($G54-(SUM($H54:$I54))),"") | AU54: =IF($B54=731,SUM($G54-(SUM($H54:$I54))),"") | AV54: =IF($B54=730,SUM($G54-(SUM($H54:$I54))),"")
D55: =D54+G55 -> 0 | F55: =SUM(H55:AV55)-G55 -> 0 | H55: =IF(G55/23*3>0,SUM(G55/23*3),"") | I55: =IF(G55/23*3<0,SUM(G55/23*3),"") | J55: =IF($B55=707,SUM($G55-(SUM($H55:$I55))),"") | K55: =IF($B55=706,SUM($G55-(SUM($H55:$I55))),"") | L55: =IF($B55=703,SUM($G55-(SUM($H55:$I55))),"") | M55: =IF($B55=704,SUM($G55-(SUM($H55:$I55))),"") | N55: =IF($B55=709,SUM($G55-(SUM($H55:$I55))),"") | O55: =IF($B55=738,SUM($G55-(SUM($H55:$I55))),"") | P55: =IF($B55=739,SUM($G55-(SUM($H55:$I55))),"") | Q55: =IF($B55=714,SUM($G55-(SUM($H55:$I55))),"") | R55: =IF($B55=710,SUM($G55-(SUM($H55:$I55))),"") | S55: =IF($B55=711,SUM($G55-(SUM($H55:$I55))),"") | T55: =IF($B55=712,SUM($G55-(SUM($H55:$I55))),"") | U55: =IF($B55=713,SUM($G55-(SUM($H55:$I55))),"") | V55: =IF($B55=715,SUM($G55-(SUM($H55:$I55))),"") | W55: =IF($B55=724,SUM($G55-(SUM($H55:$I55))),"") | X55: =IF($B55=725,SUM($G55-(SUM($H55:$I55))),"") | Y55: =IF($B55=726,SUM($G55-(SUM($H55:$I55))),"") | Z55: =IF($B55=727,SUM($G55-(SUM($H55:$I55))),"") | AA55: =IF($B55=728,SUM($G55-(SUM($H55:$I55))),"") | AB55: =IF($B55=729,SUM($G55-(SUM($H55:$I55))),"") | AC55: =IF($B55=730,SUM($G55-(SUM($H55:$I55))),"") | AD55: =IF($B55=732,SUM($G55-(SUM($H55:$I55))),"") | AE55: =IF($B55=733,SUM($G55-(SUM($H55:$I55))),"") | AF55: =IF($B55=734,SUM($G55-(SUM($H55:$I55))),"") | AG55: =IF($B55=705,SUM($G55-(SUM($H55:$I55))),"") | AH55: =IF($B55=735,SUM($G55-(SUM($H55:$I55))),"") | AI55: =IF($B55=736,SUM($G55-(SUM($H55:$I55))),"") | AJ55: =IF($B55=737,SUM($G55-(SUM($H55:$I55))),"") | AK55: =IF($B55=725,SUM($G55-(SUM($H55:$I55))),"") | AL55: =IF($B55=735,SUM($G55-(SUM($H55:$I55))),"") | AM55: =IF($B55=727,SUM($G55-(SUM($H55:$I55))),"") | AN55: =IF($B55=718,SUM($G55-(SUM($H55:$I55))),"") | AO55: =IF($B55=719,SUM($G55-(SUM($H55:$I55))),"") | AP55: =IF($B55=717,SUM($G55-(SUM($H55:$I55))),"") | AQ55: =IF($B55=722,SUM($G55-(SUM($H55:$I55))),"") | AR55: =IF($B55=708,SUM($G55-(SUM($H55:$I55))),"") | AS55: =IF($B55=701,SUM($G55-(SUM($H55:$I55))),"") | AT55: =IF($B55=702,SUM($G55-(SUM($H55:$I55))),"") | AU55: =IF($B55=731,SUM($G55-(SUM($H55:$I55))),"") | AV55: =IF($B55=730,SUM($G55-(SUM($H55:$I55))),"")
B56: 707 | C56: Income - January - Client (50% progress payment received) | D56: =D55+G56 -> 0 | F56: =SUM(H56:AV56)-G56 -> 0 | G56: 0 | H56: =IF(G56/23*3>0,SUM(G56/23*3),"") | I56: =IF(G56/23*3<0,SUM(G56/23*3),"") | J56: =IF($B56=707,SUM($G56-(SUM($H56:$I56))),"") -> 0 | K56: =IF($B56=706,SUM($G56-(SUM($H56:$I56))),"") | L56: =IF($B56=703,SUM($G56-(SUM($H56:$I56))),"") | M56: =IF($B56=704,SUM($G56-(SUM($H56:$I56))),"") | N56: =IF($B56=709,SUM($G56-(SUM($H56:$I56))),"") | O56: =IF($B56=738,SUM($G56-(SUM($H56:$I56))),"") | P56: =IF($B56=739,SUM($G56-(SUM($H56:$I56))),"") | Q56: =IF($B56=714,SUM($G56-(SUM($H56:$I56))),"") | R56: =IF($B56=710,SUM($G56-(SUM($H56:$I56))),"") | S56: =IF($B56=711,SUM($G56-(SUM($H56:$I56))),"") | T56: =IF($B56=712,SUM($G56-(SUM($H56:$I56))),"") | U56: =IF($B56=713,SUM($G56-(SUM($H56:$I56))),"") | V56: =IF($B56=715,SUM($G56-(SUM($H56:$I56))),"") | W56: =IF($B56=724,SUM($G56-(SUM($H56:$I56))),"") | X56: =IF($B56=725,SUM($G56-(SUM($H56:$I56))),"") | Y56: =IF($B56=726,SUM($G56-(SUM($H56:$I56))),"") | Z56: =IF($B56=727,SUM($G56-(SUM($H56:$I56))),"") | AA56: =IF($B56=728,SUM($G56-(SUM($H56:$I56))),"") | AB56: =IF($B56=729,SUM($G56-(SUM($H56:$I56))),"") | AC56: =IF($B56=730,SUM($G56-(SUM($H56:$I56))),"") | AD56: =IF($B56=732,SUM($G56-(SUM($H56:$I56))),"") | AE56: =IF($B56=733,SUM($G56-(SUM($H56:$I56))),"") | AF56: =IF($B56=734,SUM($G56-(SUM($H56:$I56))),"") | AG56: =IF($B56=705,SUM($G56-(SUM($H56:$I56))),"") | AH56: =IF($B56=735,SUM($G56-(SUM($H56:$I56))),"") | AI56: =IF($B56=736,SUM($G56-(SUM($H56:$I56))),"") | AJ56: =IF($B56=737,SUM($G56-(SUM($H56:$I56))),"") | AK56: =IF($B56=725,SUM($G56-(SUM($H56:$I56))),"") | AL56: =IF($B56=735,SUM($G56-(SUM($H56:$I56))),"") | AM56: =IF($B56=727,SUM($G56-(SUM($H56:$I56))),"") | AN56: =IF($B56=718,SUM($G56-(SUM($H56:$I56))),"") | AO56: =IF($B56=719,SUM($G56-(SUM($H56:$I56))),"") | AP56: =IF($B56=717,SUM($G56-(SUM($H56:$I56))),"") | AQ56: =IF($B56=722,SUM($G56-(SUM($H56:$I56))),"") | AR56: =IF($B56=708,SUM($G56-(SUM($H56:$I56))),"") | AS56: =IF($B56=701,SUM($G56-(SUM($H56:$I56))),"") | AT56: =IF($B56=702,SUM($G56-(SUM($H56:$I56))),"") | AU56: =IF($B56=731,SUM($G56-(SUM($H56:$I56))),"") | AV56: =IF($B56=730,SUM($G56-(SUM($H56:$I56))),"")
B57: 707 | C57: Income - January - Client (50% progress payment received) | D57: =D56+G57 -> 0 | F57: =SUM(H57:AV57)-G57 -> 0 | G57: 0 | H57: =IF(G57/23*3>0,SUM(G57/23*3),"") | I57: =IF(G57/23*3<0,SUM(G57/23*3),"") | J57: =IF($B57=707,SUM($G57-(SUM($H57:$I57))),"") -> 0 | K57: =IF($B57=706,SUM($G57-(SUM($H57:$I57))),"") | L57: =IF($B57=703,SUM($G57-(SUM($H57:$I57))),"") | M57: =IF($B57=704,SUM($G57-(SUM($H57:$I57))),"") | N57: =IF($B57=709,SUM($G57-(SUM($H57:$I57))),"") | O57: =IF($B57=738,SUM($G57-(SUM($H57:$I57))),"") | P57: =IF($B57=739,SUM($G57-(SUM($H57:$I57))),"") | Q57: =IF($B57=714,SUM($G57-(SUM($H57:$I57))),"") | R57: =IF($B57=710,SUM($G57-(SUM($H57:$I57))),"") | S57: =IF($B57=711,SUM($G57-(SUM($H57:$I57))),"") | T57: =IF($B57=712,SUM($G57-(SUM($H57:$I57))),"") | U57: =IF($B57=713,SUM($G57-(SUM($H57:$I57))),"") | V57: =IF($B57=715,SUM($G57-(SUM($H57:$I57))),"") | W57: =IF($B57=724,SUM($G57-(SUM($H57:$I57))),"") | X57: =IF($B57=725,SUM($G57-(SUM($H57:$I57))),"") | Y57: =IF($B57=726,SUM($G57-(SUM($H57:$I57))),"") | Z57: =IF($B57=727,SUM($G57-(SUM($H57:$I57))),"") | AA57: =IF($B57=728,SUM($G57-(SUM($H57:$I57))),"") | AB57: =IF($B57=729,SUM($G57-(SUM($H57:$I57))),"") | AC57: =IF($B57=730,SUM($G57-(SUM($H57:$I57))),"") | AD57: =IF($B57=732,SUM($G57-(SUM($H57:$I57))),"") | AE57: =IF($B57=733,SUM($G57-(SUM($H57:$I57))),"") | AF57: =IF($B57=734,SUM($G57-(SUM($H57:$I57))),"") | AG57: =IF($B57=705,SUM($G57-(SUM($H57:$I57))),"") | AH57: =IF($B57=735,SUM($G57-(SUM($H57:$I57))),"") | AI57: =IF($B57=736,SUM($G57-(SUM($H57:$I57))),"") | AJ57: =IF($B57=737,SUM($G57-(SUM($H57:$I57))),"") | AK57: =IF($B57=725,SUM($G57-(SUM($H57:$I57))),"") | AL57: =IF($B57=735,SUM($G57-(SUM($H57:$I57))),"") | AM57: =IF($B57=727,SUM($G57-(SUM($H57:$I57))),"") | AN57: =IF($B57=718,SUM($G57-(SUM($H57:$I57))),"") | AO57: =IF($B57=719,SUM($G57-(SUM($H57:$I57))),"") | AP57: =IF($B57=717,SUM($G57-(SUM($H57:$I57))),"") | AQ57: =IF($B57=722,SUM($G57-(SUM($H57:$I57))),"") | AR57: =IF($B57=708,SUM($G57-(SUM($H57:$I57))),"") | AS57: =IF($B57=701,SUM($G57-(SUM($H57:$I57))),"") | AT57: =IF($B57=702,SUM($G57-(SUM($H57:$I57))),"") | AU57: =IF($B57=731,SUM($G57-(SUM($H57:$I57))),"") | AV57: =IF($B57=730,SUM($G57-(SUM($H57:$I57))),"")
B58: 725 | C58: Power - Fibrewave | D58: =D57+G58 -> 0 | F58: =SUM(H58:AV58)-G58 -> 0 | G58: 0 | H58: =IF(G58/23*3>0,SUM(G58/23*3),"") | I58: =IF(G58/23*3<0,SUM(G58/23*3),"") | J58: =IF($B58=707,SUM($G58-(SUM($H58:$I58))),"") | K58: =IF($B58=706,SUM($G58-(SUM($H58:$I58))),"") | L58: =IF($B58=703,SUM($G58-(SUM($H58:$I58))),"") | M58: =IF($B58=704,SUM($G58-(SUM($H58:$I58))),"") | N58: =IF($B58=709,SUM($G58-(SUM($H58:$I58))),"") | O58: =IF($B58=738,SUM($G58-(SUM($H58:$I58))),"") | P58: =IF($B58=739,SUM($G58-(SUM($H58:$I58))),"") | Q58: =IF($B58=714,SUM($G58-(SUM($H58:$I58))),"") | R58: =IF($B58=710,SUM($G58-(SUM($H58:$I58))),"") | S58: =IF($B58=711,SUM($G58-(SUM($H58:$I58))),"") | T58: =IF($B58=712,SUM($G58-(SUM($H58:$I58))),"") | U58: =IF($B58=713,SUM($G58-(SUM($H58:$I58))),"") | V58: =IF($B58=715,SUM($G58-(SUM($H58:$I58))),"") | W58: =IF($B58=724,SUM($G58-(SUM($H58:$I58))),"") | X58: =IF($B58=725,SUM($G58-(SUM($H58:$I58))),"") -> 0 | Y58: =IF($B58=726,SUM($G58-(SUM($H58:$I58))),"") | Z58: =IF($B58=727,SUM($G58-(SUM($H58:$I58))),"") | AA58: =IF($B58=728,SUM($G58-(SUM($H58:$I58))),"") | AB58: =IF($B58=729,SUM($G58-(SUM($H58:$I58))),"") | AC58: =IF($B58=730,SUM($G58-(SUM($H58:$I58))),"") | AD58: =IF($B58=732,SUM($G58-(SUM($H58:$I58))),"") | AE58: =IF($B58=733,SUM($G58-(SUM($H58:$I58))),"") | AF58: =IF($B58=734,SUM($G58-(SUM($H58:$I58))),"") | AG58: =IF($B58=705,SUM($G58-(SUM($H58:$I58))),"") | AH58: =IF($B58=735,SUM($G58-(SUM($H58:$I58))),"") | AI58: =IF($B58=736,SUM($G58-(SUM($H58:$I58))),"") | AJ58: =IF($B58=737,SUM($G58-(SUM($H58:$I58))),"") | AK58: =IF($B58=725,SUM($G58-(SUM($H58:$I58))),"") -> 0 | AL58: =IF($B58=735,SUM($G58-(SUM($H58:$I58))),"") | AM58: =IF($B58=727,SUM($G58-(SUM($H58:$I58))),"") | AN58: =IF($B58=718,SUM($G58-(SUM($H58:$I58))),"") | AO58: =IF($B58=719,SUM($G58-(SUM($H58:$I58))),"") | AP58: =IF($B58=717,SUM($G58-(SUM($H58:$I58))),"") | AQ58: =IF($B58=722,SUM($G58-(SUM($H58:$I58))),"") | AR58: =IF($B58=708,SUM($G58-(SUM($H58:$I58))),"") | AS58: =IF($B58=701,SUM($G58-(SUM($H58:$I58))),"") | AT58: =IF($B58=702,SUM($G58-(SUM($H58:$I58))),"") | AU58: =IF($B58=731,SUM($G58-(SUM($H58:$I58))),"") | AV58: =IF($B58=730,SUM($G58-(SUM($H58:$I58))),"")
B59: 726 | C59: Entertainment (Business Lunch/Coffee/Meals/Drinks) | D59: =D58+G59 -> 0 | F59: =SUM(H59:AV59)-G59 -> 0 | G59: =-(OtherCalculation!C8) -> 0 | H59: =IF(G59/23*3>0,SUM(G59/23*3),"") | I59: =IF(G59/23*3<0,SUM(G59/23*3),"") | J59: =IF($B59=707,SUM($G59-(SUM($H59:$I59))),"") | K59: =IF($B59=706,SUM($G59-(SUM($H59:$I59))),"") | L59: =IF($B59=703,SUM($G59-(SUM($H59:$I59))),"") | M59: =IF($B59=704,SUM($G59-(SUM($H59:$I59))),"") | N59: =IF($B59=709,SUM($G59-(SUM($H59:$I59))),"") | O59: =IF($B59=738,SUM($G59-(SUM($H59:$I59))),"") | P59: =IF($B59=739,SUM($G59-(SUM($H59:$I59))),"") | Q59: =IF($B59=714,SUM($G59-(SUM($H59:$I59))),"") | R59: =IF($B59=710,SUM($G59-(SUM($H59:$I59))),"") | S59: =IF($B59=711,SUM($G59-(SUM($H59:$I59))),"") | T59: =IF($B59=712,SUM($G59-(SUM($H59:$I59))),"") | U59: =IF($B59=713,SUM($G59-(SUM($H59:$I59))),"") | V59: =IF($B59=715,SUM($G59-(SUM($H59:$I59))),"") | W59: =IF($B59=724,SUM($G59-(SUM($H59:$I59))),"") | X59: =IF($B59=725,SUM($G59-(SUM($H59:$I59))),"") | Y59: =IF($B59=726,SUM($G59-(SUM($H59:$I59))),"") -> 0 | Z59: =IF($B59=727,SUM($G59-(SUM($H59:$I59))),"") | AA59: =IF($B59=728,SUM($G59-(SUM($H59:$I59))),"") | AB59: =IF($B59=729,SUM($G59-(SUM($H59:$I59))),"") | AC59: =IF($B59=730,SUM($G59-(SUM($H59:$I59))),"") | AD59: =IF($B59=732,SUM($G59-(SUM($H59:$I59))),"") | AE59: =IF($B59=733,SUM($G59-(SUM($H59:$I59))),"") | AF59: =IF($B59=734,SUM($G59-(SUM($H59:$I59))),"") | AG59: =IF($B59=705,SUM($G59-(SUM($H59:$I59))),"") | AH59: =IF($B59=735,SUM($G59-(SUM($H59:$I59))),"") | AI59: =IF($B59=736,SUM($G59-(SUM($H59:$I59))),"") | AJ59: =IF($B59=737,SUM($G59-(SUM($H59:$I59))),"") | AK59: =IF($B59=725,SUM($G59-(SUM($H59:$I59))),"") | AL59: =IF($B59=735,SUM($G59-(SUM($H59:$I59))),"") | AM59: =IF($B59=727,SUM($G59-(SUM($H59:$I59))),"") | AN59: =IF($B59=718,SUM($G59-(SUM($H59:$I59))),"") | AO59: =IF($B59=719,SUM($G59-(SUM($H59:$I59))),"") | AP59: =IF($B59=717,SUM($G59-(SUM($H59:$I59))),"") | AQ59: =IF($B59=722,SUM($G59-(SUM($H59:$I59))),"") | AR59: =IF($B59=708,SUM($G59-(SUM($H59:$I59))),"") | AS59: =IF($B59=701,SUM($G59-(SUM($H59:$I59))),"") | AT59: =IF($B59=702,SUM($G59-(SUM($H59:$I59))),"") | AU59: =IF($B59=731,SUM($G59-(SUM($H59:$I59))),"") | AV59: =IF($B59=730,SUM($G59-(SUM($H59:$I59))),"")
B60: 727 | C60: Internet - Fibrewave | D60: =D59+G60 -> 0 | F60: =SUM(H60:AV60)-G60 -> 0 | G60: 0 | H60: =IF(G60/23*3>0,SUM(G60/23*3),"") | I60: =IF(G60/23*3<0,SUM(G60/23*3),"") | J60: =IF($B60=707,SUM($G60-(SUM($H60:$I60))),"") | K60: =IF($B60=706,SUM($G60-(SUM($H60:$I60))),"") | L60: =IF($B60=703,SUM($G60-(SUM($H60:$I60))),"") | M60: =IF($B60=704,SUM($G60-(SUM($H60:$I60))),"") | N60: =IF($B60=709,SUM($G60-(SUM($H60:$I60))),"") | O60: =IF($B60=738,SUM($G60-(SUM($H60:$I60))),"") | P60: =IF($B60=739,SUM($G60-(SUM($H60:$I60))),"") | Q60: =IF($B60=714,SUM($G60-(SUM($H60:$I60))),"") | R60: =IF($B60=710,SUM($G60-(SUM($H60:$I60))),"") | S60: =IF($B60=711,SUM($G60-(SUM($H60:$I60))),"") | T60: =IF($B60=712,SUM($G60-(SUM($H60:$I60))),"") | U60: =IF($B60=713,SUM($G60-(SUM($H60:$I60))),"") | V60: =IF($B60=715,SUM($G60-(SUM($H60:$I60))),"") | W60: =IF($B60=724,SUM($G60-(SUM($H60:$I60))),"") | X60: =IF($B60=725,SUM($G60-(SUM($H60:$I60))),"") | Y60: =IF($B60=726,SUM($G60-(SUM($H60:$I60))),"") | Z60: =IF($B60=727,SUM($G60-(SUM($H60:$I60))),"") -> 0 | AA60: =IF($B60=728,SUM($G60-(SUM($H60:$I60))),"") | AB60: =IF($B60=729,SUM($G60-(SUM($H60:$I60))),"") | AC60: =IF($B60=730,SUM($G60-(SUM($H60:$I60))),"") | AD60: =IF($B60=732,SUM($G60-(SUM($H60:$I60))),"") | AE60: =IF($B60=733,SUM($G60-(SUM($H60:$I60))),"") | AF60: =IF($B60=734,SUM($G60-(SUM($H60:$I60))),"") | AG60: =IF($B60=705,SUM($G60-(SUM($H60:$I60))),"") | AH60: =IF($B60=735,SUM($G60-(SUM($H60:$I60))),"") | AI60: =IF($B60=736,SUM($G60-(SUM($H60:$I60))),"") | AJ60: =IF($B60=737,SUM($G60-(SUM($H60:$I60))),"") | AK60: =IF($B60=725,SUM($G60-(SUM($H60:$I60))),"") | AL60: =IF($B60=735,SUM($G60-(SUM($H60:$I60))),"") | AM60: =IF($B60=727,SUM($G60-(SUM($H60:$I60))),"") -> 0 | AN60: =IF($B60=718,SUM($G60-(SUM($H60:$I60))),"") | AO60: =IF($B60=719,SUM($G60-(SUM($H60:$I60))),"") | AP60: =IF($B60=717,SUM($G60-(SUM($H60:$I60))),"") | AQ60: =IF($B60=722,SUM($G60-(SUM($H60:$I60))),"") | AR60: =IF($B60=708,SUM($G60-(SUM($H60:$I60))),"") | AS60: =IF($B60=701,SUM($G60-(SUM($H60:$I60))),"") | AT60: =IF($B60=702,SUM($G60-(SUM($H60:$I60))),"") | AU60: =IF($B60=731,SUM($G60-(SUM($H60:$I60))),"") | AV60: =IF($B60=730,SUM($G60-(SUM($H60:$I60))),"")
B61: 728 | C61: Mobile Plan - Tui Mobile NZ | D61: =D60+G61 -> 0 | F61: =SUM(H61:AV61)-G61 -> 0 | G61: 0 | H61: =IF(G61/23*3>0,SUM(G61/23*3),"") | I61: =IF(G61/23*3<0,SUM(G61/23*3),"") | J61: =IF($B61=707,SUM($G61-(SUM($H61:$I61))),"") | K61: =IF($B61=706,SUM($G61-(SUM($H61:$I61))),"") | L61: =IF($B61=703,SUM($G61-(SUM($H61:$I61))),"") | M61: =IF($B61=704,SUM($G61-(SUM($H61:$I61))),"") | N61: =IF($B61=709,SUM($G61-(SUM($H61:$I61))),"") | O61: =IF($B61=738,SUM($G61-(SUM($H61:$I61))),"") | P61: =IF($B61=739,SUM($G61-(SUM($H61:$I61))),"") | Q61: =IF($B61=714,SUM($G61-(SUM($H61:$I61))),"") | R61: =IF($B61=710,SUM($G61-(SUM($H61:$I61))),"") | S61: =IF($B61=711,SUM($G61-(SUM($H61:$I61))),"") | T61: =IF($B61=712,SUM($G61-(SUM($H61:$I61))),"") | U61: =IF($B61=713,SUM($G61-(SUM($H61:$I61))),"") | V61: =IF($B61=715,SUM($G61-(SUM($H61:$I61))),"") | W61: =IF($B61=724,SUM($G61-(SUM($H61:$I61))),"") | X61: =IF($B61=725,SUM($G61-(SUM($H61:$I61))),"") | Y61: =IF($B61=726,SUM($G61-(SUM($H61:$I61))),"") | Z61: =IF($B61=727,SUM($G61-(SUM($H61:$I61))),"") | AA61: =IF($B61=728,SUM($G61-(SUM($H61:$I61))),"") -> 0 | AB61: =IF($B61=729,SUM($G61-(SUM($H61:$I61))),"") | AC61: =IF($B61=730,SUM($G61-(SUM($H61:$I61))),"") | AD61: =IF($B61=732,SUM($G61-(SUM($H61:$I61))),"") | AE61: =IF($B61=733,SUM($G61-(SUM($H61:$I61))),"") | AF61: =IF($B61=734,SUM($G61-(SUM($H61:$I61))),"") | AG61: =IF($B61=705,SUM($G61-(SUM($H61:$I61))),"") | AH61: =IF($B61=735,SUM($G61-(SUM($H61:$I61))),"") | AI61: =IF($B61=736,SUM($G61-(SUM($H61:$I61))),"") | AJ61: =IF($B61=737,SUM($G61-(SUM($H61:$I61))),"") | AK61: =IF($B61=725,SUM($G61-(SUM($H61:$I61))),"") | AL61: =IF($B61=735,SUM($G61-(SUM($H61:$I61))),"") | AM61: =IF($B61=727,SUM($G61-(SUM($H61:$I61))),"") | AN61: =IF($B61=718,SUM($G61-(SUM($H61:$I61))),"") | AO61: =IF($B61=719,SUM($G61-(SUM($H61:$I61))),"") | AP61: =IF($B61=717,SUM($G61-(SUM($H61:$I61))),"") | AQ61: =IF($B61=722,SUM($G61-(SUM($H61:$I61))),"") | AR61: =IF($B61=708,SUM($G61-(SUM($H61:$I61))),"") | AS61: =IF($B61=701,SUM($G61-(SUM($H61:$I61))),"") | AT61: =IF($B61=702,SUM($G61-(SUM($H61:$I61))),"") | AU61: =IF($B61=731,SUM($G61-(SUM($H61:$I61))),"") | AV61: =IF($B61=730,SUM($G61-(SUM($H61:$I61))),"")
B62: 729 | C62: Car Park Fees | D62: =D61+G62 -> 0 | F62: =SUM(H62:AV62)-G62 -> 0 | G62: 0 | H62: =IF(G62/23*3>0,SUM(G62/23*3),"") | I62: =IF(G62/23*3<0,SUM(G62/23*3),"") | J62: =IF($B62=707,SUM($G62-(SUM($H62:$I62))),"") | K62: =IF($B62=706,SUM($G62-(SUM($H62:$I62))),"") | L62: =IF($B62=703,SUM($G62-(SUM($H62:$I62))),"") | M62: =IF($B62=704,SUM($G62-(SUM($H62:$I62))),"") | N62: =IF($B62=709,SUM($G62-(SUM($H62:$I62))),"") | O62: =IF($B62=738,SUM($G62-(SUM($H62:$I62))),"") | P62: =IF($B62=739,SUM($G62-(SUM($H62:$I62))),"") | Q62: =IF($B62=714,SUM($G62-(SUM($H62:$I62))),"") | R62: =IF($B62=710,SUM($G62-(SUM($H62:$I62))),"") | S62: =IF($B62=711,SUM($G62-(SUM($H62:$I62))),"") | T62: =IF($B62=712,SUM($G62-(SUM($H62:$I62))),"") | U62: =IF($B62=713,SUM($G62-(SUM($H62:$I62))),"") | V62: =IF($B62=715,SUM($G62-(SUM($H62:$I62))),"") | W62: =IF($B62=724,SUM($G62-(SUM($H62:$I62))),"") | X62: =IF($B62=725,SUM($G62-(SUM($H62:$I62))),"") | Y62: =IF($B62=726,SUM($G62-(SUM($H62:$I62))),"") | Z62: =IF($B62=727,SUM($G62-(SUM($H62:$I62))),"") | AA62: =IF($B62=728,SUM($G62-(SUM($H62:$I62))),"") | AB62: =IF($B62=729,SUM($G62-(SUM($H62:$I62))),"") -> 0 | AC62: =IF($B62=730,SUM($G62-(SUM($H62:$I62))),"") | AD62: =IF($B62=732,SUM($G62-(SUM($H62:$I62))),"") | AE62: =IF($B62=733,SUM($G62-(SUM($H62:$I62))),"") | AF62: =IF($B62=734,SUM($G62-(SUM($H62:$I62))),"") | AG62: =IF($B62=705,SUM($G62-(SUM($H62:$I62))),"") | AH62: =IF($B62=735,SUM($G62-(SUM($H62:$I62))),"") | AI62: =IF($B62=736,SUM($G62-(SUM($H62:$I62))),"") | AJ62: =IF($B62=737,SUM($G62-(SUM($H62:$I62))),"") | AK62: =IF($B62=725,SUM($G62-(SUM($H62:$I62))),"") | AL62: =IF($B62=735,SUM($G62-(SUM($H62:$I62))),"") | AM62: =IF($B62=727,SUM($G62-(SUM($H62:$I62))),"") | AN62: =IF($B62=718,SUM($G62-(SUM($H62:$I62))),"") | AO62: =IF($B62=719,SUM($G62-(SUM($H62:$I62))),"") | AP62: =IF($B62=717,SUM($G62-(SUM($H62:$I62))),"") | AQ62: =IF($B62=722,SUM($G62-(SUM($H62:$I62))),"") | AR62: =IF($B62=708,SUM($G62-(SUM($H62:$I62))),"") | AS62: =IF($B62=701,SUM($G62-(SUM($H62:$I62))),"") | AT62: =IF($B62=702,SUM($G62-(SUM($H62:$I62))),"") | AU62: =IF($B62=731,SUM($G62-(SUM($H62:$I62))),"") | AV62: =IF($B62=730,SUM($G62-(SUM($H62:$I62))),"")
B63: 734 | C63: Home Office Expenses | D63: =D62+G63 -> 0 | F63: =SUM(H63:AV63)-G63 -> 0 | G63: 0 | H63: =IF(G63/23*3>0,SUM(G63/23*3),"") | I63: =IF(G63/23*3<0,SUM(G63/23*3),"") | J63: =IF($B63=707,SUM($G63-(SUM($H63:$I63))),"") | K63: =IF($B63=706,SUM($G63-(SUM($H63:$I63))),"") | L63: =IF($B63=703,SUM($G63-(SUM($H63:$I63))),"") | M63: =IF($B63=704,SUM($G63-(SUM($H63:$I63))),"") | N63: =IF($B63=709,SUM($G63-(SUM($H63:$I63))),"") | O63: =IF($B63=738,SUM($G63-(SUM($H63:$I63))),"") | P63: =IF($B63=739,SUM($G63-(SUM($H63:$I63))),"") | Q63: =IF($B63=714,SUM($G63-(SUM($H63:$I63))),"") | R63: =IF($B63=710,SUM($G63-(SUM($H63:$I63))),"") | S63: =IF($B63=711,SUM($G63-(SUM($H63:$I63))),"") | T63: =IF($B63=712,SUM($G63-(SUM($H63:$I63))),"") | U63: =IF($B63=713,SUM($G63-(SUM($H63:$I63))),"") | V63: =IF($B63=715,SUM($G63-(SUM($H63:$I63))),"") | W63: =IF($B63=724,SUM($G63-(SUM($H63:$I63))),"") | X63: =IF($B63=725,SUM($G63-(SUM($H63:$I63))),"") | Y63: =IF($B63=726,SUM($G63-(SUM($H63:$I63))),"") | Z63: =IF($B63=727,SUM($G63-(SUM($H63:$I63))),"") | AA63: =IF($B63=728,SUM($G63-(SUM($H63:$I63))),"") | AB63: =IF($B63=729,SUM($G63-(SUM($H63:$I63))),"") | AC63: =IF($B63=730,SUM($G63-(SUM($H63:$I63))),"") | AD63: =IF($B63=732,SUM($G63-(SUM($H63:$I63))),"") | AE63: =IF($B63=733,SUM($G63-(SUM($H63:$I63))),"") | AF63: =IF($B63=734,SUM($G63-(SUM($H63:$I63))),"") -> 0 | AG63: =IF($B63=705,SUM($G63-(SUM($H63:$I63))),"") | AH63: =IF($B63=735,SUM($G63-(SUM($H63:$I63))),"") | AI63: =IF($B63=736,SUM($G63-(SUM($H63:$I63))),"") | AJ63: =IF($B63=737,SUM($G63-(SUM($H63:$I63))),"") | AK63: =IF($B63=725,SUM($G63-(SUM($H63:$I63))),"") | AL63: =IF($B63=735,SUM($G63-(SUM($H63:$I63))),"") | AM63: =IF($B63=727,SUM($G63-(SUM($H63:$I63))),"") | AN63: =IF($B63=718,SUM($G63-(SUM($H63:$I63))),"") | AO63: =IF($B63=719,SUM($G63-(SUM($H63:$I63))),"") | AP63: =IF($B63=717,SUM($G63-(SUM($H63:$I63))),"") | AQ63: =IF($B63=722,SUM($G63-(SUM($H63:$I63))),"") | AR63: =IF($B63=708,SUM($G63-(SUM($H63:$I63))),"") | AS63: =IF($B63=701,SUM($G63-(SUM($H63:$I63))),"") | AT63: =IF($B63=702,SUM($G63-(SUM($H63:$I63))),"") | AU63: =IF($B63=731,SUM($G63-(SUM($H63:$I63))),"") | AV63: =IF($B63=730,SUM($G63-(SUM($H63:$I63))),"")
B64: 734 | C64: Home Office Expenses | D64: =D63+G64 -> 0 | F64: =SUM(H64:AV64)-G64 -> 0 | G64: 0 | H64: =IF(G64/23*3>0,SUM(G64/23*3),"") | I64: =IF(G64/23*3<0,SUM(G64/23*3),"") | J64: =IF($B64=707,SUM($G64-(SUM($H64:$I64))),"") | K64: =IF($B64=706,SUM($G64-(SUM($H64:$I64))),"") | L64: =IF($B64=703,SUM($G64-(SUM($H64:$I64))),"") | M64: =IF($B64=704,SUM($G64-(SUM($H64:$I64))),"") | N64: =IF($B64=709,SUM($G64-(SUM($H64:$I64))),"") | O64: =IF($B64=738,SUM($G64-(SUM($H64:$I64))),"") | P64: =IF($B64=739,SUM($G64-(SUM($H64:$I64))),"") | Q64: =IF($B64=714,SUM($G64-(SUM($H64:$I64))),"") | R64: =IF($B64=710,SUM($G64-(SUM($H64:$I64))),"") | S64: =IF($B64=711,SUM($G64-(SUM($H64:$I64))),"") | T64: =IF($B64=712,SUM($G64-(SUM($H64:$I64))),"") | U64: =IF($B64=713,SUM($G64-(SUM($H64:$I64))),"") | V64: =IF($B64=715,SUM($G64-(SUM($H64:$I64))),"") | W64: =IF($B64=724,SUM($G64-(SUM($H64:$I64))),"") | X64: =IF($B64=725,SUM($G64-(SUM($H64:$I64))),"") | Y64: =IF($B64=726,SUM($G64-(SUM($H64:$I64))),"") | Z64: =IF($B64=727,SUM($G64-(SUM($H64:$I64))),"") | AA64: =IF($B64=728,SUM($G64-(SUM($H64:$I64))),"") | AB64: =IF($B64=729,SUM($G64-(SUM($H64:$I64))),"") | AC64: =IF($B64=730,SUM($G64-(SUM($H64:$I64))),"") | AD64: =IF($B64=732,SUM($G64-(SUM($H64:$I64))),"") | AE64: =IF($B64=733,SUM($G64-(SUM($H64:$I64))),"") | AF64: =IF($B64=734,SUM($G64-(SUM($H64:$I64))),"") -> 0 | AG64: =IF($B64=705,SUM($G64-(SUM($H64:$I64))),"") | AH64: =IF($B64=735,SUM($G64-(SUM($H64:$I64))),"") | AI64: =IF($B64=736,SUM($G64-(SUM($H64:$I64))),"") | AJ64: =IF($B64=737,SUM($G64-(SUM($H64:$I64))),"") | AK64: =IF($B64=725,SUM($G64-(SUM($H64:$I64))),"") | AL64: =IF($B64=735,SUM($G64-(SUM($H64:$I64))),"") | AM64: =IF($B64=727,SUM($G64-(SUM($H64:$I64))),"") | AN64: =IF($B64=718,SUM($G64-(SUM($H64:$I64))),"") | AO64: =IF($B64=719,SUM($G64-(SUM($H64:$I64))),"") | AP64: =IF($B64=717,SUM($G64-(SUM($H64:$I64))),"") | AQ64: =IF($B64=722,SUM($G64-(SUM($H64:$I64))),"") | AR64: =IF($B64=708,SUM($G64-(SUM($H64:$I64))),"") | AS64: =IF($B64=701,SUM($G64-(SUM($H64:$I64))),"") | AT64: =IF($B64=702,SUM($G64-(SUM($H64:$I64))),"") | AU64: =IF($B64=731,SUM($G64-(SUM($H64:$I64))),"") | AV64: =IF($B64=730,SUM($G64-(SUM($H64:$I64))),"")
B65: 734 | C65: Home Office Expenses | D65: =D64+G65 -> 0 | F65: =SUM(H65:AV65)-G65 -> 0 | G65: 0 | H65: =IF(G65/23*3>0,SUM(G65/23*3),"") | I65: =IF(G65/23*3<0,SUM(G65/23*3),"") | J65: =IF($B65=707,SUM($G65-(SUM($H65:$I65))),"") | K65: =IF($B65=706,SUM($G65-(SUM($H65:$I65))),"") | L65: =IF($B65=703,SUM($G65-(SUM($H65:$I65))),"") | M65: =IF($B65=704,SUM($G65-(SUM($H65:$I65))),"") | N65: =IF($B65=709,SUM($G65-(SUM($H65:$I65))),"") | O65: =IF($B65=738,SUM($G65-(SUM($H65:$I65))),"") | P65: =IF($B65=739,SUM($G65-(SUM($H65:$I65))),"") | Q65: =IF($B65=714,SUM($G65-(SUM($H65:$I65))),"") | R65: =IF($B65=710,SUM($G65-(SUM($H65:$I65))),"") | S65: =IF($B65=711,SUM($G65-(SUM($H65:$I65))),"") | T65: =IF($B65=712,SUM($G65-(SUM($H65:$I65))),"") | U65: =IF($B65=713,SUM($G65-(SUM($H65:$I65))),"") | V65: =IF($B65=715,SUM($G65-(SUM($H65:$I65))),"") | W65: =IF($B65=724,SUM($G65-(SUM($H65:$I65))),"") | X65: =IF($B65=725,SUM($G65-(SUM($H65:$I65))),"") | Y65: =IF($B65=726,SUM($G65-(SUM($H65:$I65))),"") | Z65: =IF($B65=727,SUM($G65-(SUM($H65:$I65))),"") | AA65: =IF($B65=728,SUM($G65-(SUM($H65:$I65))),"") | AB65: =IF($B65=729,SUM($G65-(SUM($H65:$I65))),"") | AC65: =IF($B65=730,SUM($G65-(SUM($H65:$I65))),"") | AD65: =IF($B65=732,SUM($G65-(SUM($H65:$I65))),"") | AE65: =IF($B65=733,SUM($G65-(SUM($H65:$I65))),"") | AF65: =IF($B65=734,SUM($G65-(SUM($H65:$I65))),"") -> 0 | AG65: =IF($B65=705,SUM($G65-(SUM($H65:$I65))),"") | AH65: =IF($B65=735,SUM($G65-(SUM($H65:$I65))),"") | AI65: =IF($B65=736,SUM($G65-(SUM($H65:$I65))),"") | AJ65: =IF($B65=737,SUM($G65-(SUM($H65:$I65))),"") | AK65: =IF($B65=725,SUM($G65-(SUM($H65:$I65))),"") | AL65: =IF($B65=735,SUM($G65-(SUM($H65:$I65))),"") | AM65: =IF($B65=727,SUM($G65-(SUM($H65:$I65))),"") | AN65: =IF($B65=718,SUM($G65-(SUM($H65:$I65))),"") | AO65: =IF($B65=719,SUM($G65-(SUM($H65:$I65))),"") | AP65: =IF($B65=717,SUM($G65-(SUM($H65:$I65))),"") | AQ65: =IF($B65=722,SUM($G65-(SUM($H65:$I65))),"") | AR65: =IF($B65=708,SUM($G65-(SUM($H65:$I65))),"") | AS65: =IF($B65=701,SUM($G65-(SUM($H65:$I65))),"") | AT65: =IF($B65=702,SUM($G65-(SUM($H65:$I65))),"") | AU65: =IF($B65=731,SUM($G65-(SUM($H65:$I65))),"") | AV65: =IF($B65=730,SUM($G65-(SUM($H65:$I65))),"")
B66: 734 | C66: Home Office Expenses | D66: =D65+G66 -> 0 | F66: =SUM(H66:AV66)-G66 -> 0 | G66: 0 | H66: =IF(G66/23*3>0,SUM(G66/23*3),"") | I66: =IF(G66/23*3<0,SUM(G66/23*3),"") | J66: =IF($B66=707,SUM($G66-(SUM($H66:$I66))),"") | K66: =IF($B66=706,SUM($G66-(SUM($H66:$I66))),"") | L66: =IF($B66=703,SUM($G66-(SUM($H66:$I66))),"") | M66: =IF($B66=704,SUM($G66-(SUM($H66:$I66))),"") | N66: =IF($B66=709,SUM($G66-(SUM($H66:$I66))),"") | O66: =IF($B66=738,SUM($G66-(SUM($H66:$I66))),"") | P66: =IF($B66=739,SUM($G66-(SUM($H66:$I66))),"") | Q66: =IF($B66=714,SUM($G66-(SUM($H66:$I66))),"") | R66: =IF($B66=710,SUM($G66-(SUM($H66:$I66))),"") | S66: =IF($B66=711,SUM($G66-(SUM($H66:$I66))),"") | T66: =IF($B66=712,SUM($G66-(SUM($H66:$I66))),"") | U66: =IF($B66=713,SUM($G66-(SUM($H66:$I66))),"") | V66: =IF($B66=715,SUM($G66-(SUM($H66:$I66))),"") | W66: =IF($B66=724,SUM($G66-(SUM($H66:$I66))),"") | X66: =IF($B66=725,SUM($G66-(SUM($H66:$I66))),"") | Y66: =IF($B66=726,SUM($G66-(SUM($H66:$I66))),"") | Z66: =IF($B66=727,SUM($G66-(SUM($H66:$I66))),"") | AA66: =IF($B66=728,SUM($G66-(SUM($H66:$I66))),"") | AB66: =IF($B66=729,SUM($G66-(SUM($H66:$I66))),"") | AC66: =IF($B66=730,SUM($G66-(SUM($H66:$I66))),"") | AD66: =IF($B66=732,SUM($G66-(SUM($H66:$I66))),"") | AE66: =IF($B66=733,SUM($G66-(SUM($H66:$I66))),"") | AF66: =IF($B66=734,SUM($G66-(SUM($H66:$I66))),"") -> 0 | AG66: =IF($B66=705,SUM($G66-(SUM($H66:$I66))),"") | AH66: =IF($B66=735,SUM($G66-(SUM($H66:$I66))),"") | AI66: =IF($B66=736,SUM($G66-(SUM($H66:$I66))),"") | AJ66: =IF($B66=737,SUM($G66-(SUM($H66:$I66))),"") | AK66: =IF($B66=725,SUM($G66-(SUM($H66:$I66))),"") | AL66: =IF($B66=735,SUM($G66-(SUM($H66:$I66))),"") | AM66: =IF($B66=727,SUM($G66-(SUM($H66:$I66))),"") | AN66: =IF($B66=718,SUM($G66-(SUM($H66:$I66))),"") | AO66: =IF($B66=719,SUM($G66-(SUM($H66:$I66))),"") | AP66: =IF($B66=717,SUM($G66-(SUM($H66:$I66))),"") | AQ66: =IF($B66=722,SUM($G66-(SUM($H66:$I66))),"") | AR66: =IF($B66=708,SUM($G66-(SUM($H66:$I66))),"") | AS66: =IF($B66=701,SUM($G66-(SUM($H66:$I66))),"") | AT66: =IF($B66=702,SUM($G66-(SUM($H66:$I66))),"") | AU66: =IF($B66=731,SUM($G66-(SUM($H66:$I66))),"") | AV66: =IF($B66=730,SUM($G66-(SUM($H66:$I66))),"")
B67: 710 | C67: Bank Fees | D67: =D66+G67 -> 0 | F67: =SUM(H67:AV67)-G67 -> 0 | G67: 0 | H67: =IF(G67/23*3>0,SUM(G67/23*3),"") | J67: =IF($B67=707,SUM($G67-(SUM($H67:$I67))),"") | K67: =IF($B67=706,SUM($G67-(SUM($H67:$I67))),"") | L67: =IF($B67=703,SUM($G67-(SUM($H67:$I67))),"") | M67: =IF($B67=704,SUM($G67-(SUM($H67:$I67))),"") | N67: =IF($B67=709,SUM($G67-(SUM($H67:$I67))),"") | O67: =IF($B67=738,SUM($G67-(SUM($H67:$I67))),"") | P67: =IF($B67=739,SUM($G67-(SUM($H67:$I67))),"") | Q67: =IF($B67=714,SUM($G67-(SUM($H67:$I67))),"") | R67: =IF($B67=710,SUM($G67-(SUM($H67:$I67))),"") -> 0 | S67: =IF($B67=711,SUM($G67-(SUM($H67:$I67))),"") | T67: =IF($B67=712,SUM($G67-(SUM($H67:$I67))),"") | U67: =IF($B67=713,SUM($G67-(SUM($H67:$I67))),"") | V67: =IF($B67=715,SUM($G67-(SUM($H67:$I67))),"") | W67: =IF($B67=724,SUM($G67-(SUM($H67:$I67))),"") | X67: =IF($B67=725,SUM($G67-(SUM($H67:$I67))),"") | Y67: =IF($B67=726,SUM($G67-(SUM($H67:$I67))),"") | Z67: =IF($B67=727,SUM($G67-(SUM($H67:$I67))),"") | AA67: =IF($B67=728,SUM($G67-(SUM($H67:$I67))),"") | AB67: =IF($B67=729,SUM($G67-(SUM($H67:$I67))),"") | AC67: =IF($B67=730,SUM($G67-(SUM($H67:$I67))),"") | AD67: =IF($B67=732,SUM($G67-(SUM($H67:$I67))),"") | AE67: =IF($B67=733,SUM($G67-(SUM($H67:$I67))),"") | AF67: =IF($B67=734,SUM($G67-(SUM($H67:$I67))),"") | AG67: =IF($B67=705,SUM($G67-(SUM($H67:$I67))),"") | AH67: =IF($B67=735,SUM($G67-(SUM($H67:$I67))),"") | AI67: =IF($B67=736,SUM($G67-(SUM($H67:$I67))),"") | AJ67: =IF($B67=737,SUM($G67-(SUM($H67:$I67))),"") | AK67: =IF($B67=725,SUM($G67-(SUM($H67:$I67))),"") | AL67: =IF($B67=735,SUM($G67-(SUM($H67:$I67))),"") | AM67: =IF($B67=727,SUM($G67-(SUM($H67:$I67))),"") | AN67: =IF($B67=718,SUM($G67-(SUM($H67:$I67))),"") | AO67: =IF($B67=719,SUM($G67-(SUM($H67:$I67))),"") | AP67: =IF($B67=717,SUM($G67-(SUM($H67:$I67))),"") | AQ67: =IF($B67=722,SUM($G67-(SUM($H67:$I67))),"") | AR67: =IF($B67=708,SUM($G67-(SUM($H67:$I67))),"") | AS67: =IF($B67=701,SUM($G67-(SUM($H67:$I67))),"") | AT67: =IF($B67=702,SUM($G67-(SUM($H67:$I67))),"") | AU67: =IF($B67=731,SUM($G67-(SUM($H67:$I67))),"") | AV67: =IF($B67=730,SUM($G67-(SUM($H67:$I67))),"")
B68: 739 | C68: Online Tech Subscriptions (NO GST) | D68: =D67+G68 -> 0 | F68: =SUM(H68:AV68)-G68 -> 0 | G68: 0 | H68: =IF(G68/23*3>0,SUM(G68/23*3),"") | I68: 0 | J68: =IF($B68=707,SUM($G68-(SUM($H68:$I68))),"") | K68: =IF($B68=706,SUM($G68-(SUM($H68:$I68))),"") | L68: =IF($B68=703,SUM($G68-(SUM($H68:$I68))),"") | M68: =IF($B68=704,SUM($G68-(SUM($H68:$I68))),"") | N68: =IF($B68=709,SUM($G68-(SUM($H68:$I68))),"") | O68: =IF($B68=738,SUM($G68-(SUM($H68:$I68))),"") | P68: =IF($B68=739,SUM($G68-(SUM($H68:$I68))),"") -> 0 | Q68: =IF($B68=714,SUM($G68-(SUM($H68:$I68))),"") | R68: =IF($B68=710,SUM($G68-(SUM($H68:$I68))),"") | S68: =IF($B68=711,SUM($G68-(SUM($H68:$I68))),"") | T68: =IF($B68=712,SUM($G68-(SUM($H68:$I68))),"") | U68: =IF($B68=713,SUM($G68-(SUM($H68:$I68))),"") | V68: =IF($B68=715,SUM($G68-(SUM($H68:$I68))),"") | W68: =IF($B68=724,SUM($G68-(SUM($H68:$I68))),"") | X68: =IF($B68=725,SUM($G68-(SUM($H68:$I68))),"") | Y68: =IF($B68=726,SUM($G68-(SUM($H68:$I68))),"") | Z68: =IF($B68=727,SUM($G68-(SUM($H68:$I68))),"") | AA68: =IF($B68=728,SUM($G68-(SUM($H68:$I68))),"") | AB68: =IF($B68=729,SUM($G68-(SUM($H68:$I68))),"") | AC68: =IF($B68=730,SUM($G68-(SUM($H68:$I68))),"") | AD68: =IF($B68=732,SUM($G68-(SUM($H68:$I68))),"") | AE68: =IF($B68=733,SUM($G68-(SUM($H68:$I68))),"") | AF68: =IF($B68=734,SUM($G68-(SUM($H68:$I68))),"") | AG68: =IF($B68=705,SUM($G68-(SUM($H68:$I68))),"") | AH68: =IF($B68=735,SUM($G68-(SUM($H68:$I68))),"") | AI68: =IF($B68=736,SUM($G68-(SUM($H68:$I68))),"") | AJ68: =IF($B68=737,SUM($G68-(SUM($H68:$I68))),"") | AK68: =IF($B68=725,SUM($G68-(SUM($H68:$I68))),"") | AL68: =IF($B68=735,SUM($G68-(SUM($H68:$I68))),"") | AM68: =IF($B68=727,SUM($G68-(SUM($H68:$I68))),"") | AN68: =IF($B68=718,SUM($G68-(SUM($H68:$I68))),"") | AO68: =IF($B68=719,SUM($G68-(SUM($H68:$I68))),"") | AP68: =IF($B68=717,SUM($G68-(SUM($H68:$I68))),"") | AQ68: =IF($B68=722,SUM($G68-(SUM($H68:$I68))),"") | AR68: =IF($B68=708,SUM($G68-(SUM($H68:$I68))),"") | AS68: =IF($B68=701,SUM($G68-(SUM($H68:$I68))),"") | AT68: =IF($B68=702,SUM($G68-(SUM($H68:$I68))),"") | AU68: =IF($B68=731,SUM($G68-(SUM($H68:$I68))),"") | AV68: =IF($B68=730,SUM($G68-(SUM($H68:$I68))),"")
B69: 739 | C69: Online Tech Subscriptions (NO GST) | D69: =D68+G69 -> 0 | F69: =SUM(H69:AV69)-G69 -> 0 | G69: 0 | H69: =IF(G69/23*3>0,SUM(G69/23*3),"") | I69: 0 | J69: =IF($B69=707,SUM($G69-(SUM($H69:$I69))),"") | K69: =IF($B69=706,SUM($G69-(SUM($H69:$I69))),"") | L69: =IF($B69=703,SUM($G69-(SUM($H69:$I69))),"") | M69: =IF($B69=704,SUM($G69-(SUM($H69:$I69))),"") | N69: =IF($B69=709,SUM($G69-(SUM($H69:$I69))),"") | O69: =IF($B69=738,SUM($G69-(SUM($H69:$I69))),"") | P69: =IF($B69=739,SUM($G69-(SUM($H69:$I69))),"") -> 0 | Q69: =IF($B69=714,SUM($G69-(SUM($H69:$I69))),"") | R69: =IF($B69=710,SUM($G69-(SUM($H69:$I69))),"") | S69: =IF($B69=711,SUM($G69-(SUM($H69:$I69))),"") | T69: =IF($B69=712,SUM($G69-(SUM($H69:$I69))),"") | U69: =IF($B69=713,SUM($G69-(SUM($H69:$I69))),"") | V69: =IF($B69=715,SUM($G69-(SUM($H69:$I69))),"") | W69: =IF($B69=724,SUM($G69-(SUM($H69:$I69))),"") | X69: =IF($B69=725,SUM($G69-(SUM($H69:$I69))),"") | Y69: =IF($B69=726,SUM($G69-(SUM($H69:$I69))),"") | Z69: =IF($B69=727,SUM($G69-(SUM($H69:$I69))),"") | AA69: =IF($B69=728,SUM($G69-(SUM($H69:$I69))),"") | AB69: =IF($B69=729,SUM($G69-(SUM($H69:$I69))),"") | AC69: =IF($B69=730,SUM($G69-(SUM($H69:$I69))),"") | AD69: =IF($B69=732,SUM($G69-(SUM($H69:$I69))),"") | AE69: =IF($B69=733,SUM($G69-(SUM($H69:$I69))),"") | AF69: =IF($B69=734,SUM($G69-(SUM($H69:$I69))),"") | AG69: =IF($B69=705,SUM($G69-(SUM($H69:$I69))),"") | AH69: =IF($B69=735,SUM($G69-(SUM($H69:$I69))),"") | AI69: =IF($B69=736,SUM($G69-(SUM($H69:$I69))),"") | AJ69: =IF($B69=737,SUM($G69-(SUM($H69:$I69))),"") | AK69: =IF($B69=725,SUM($G69-(SUM($H69:$I69))),"") | AL69: =IF($B69=735,SUM($G69-(SUM($H69:$I69))),"") | AM69: =IF($B69=727,SUM($G69-(SUM($H69:$I69))),"") | AN69: =IF($B69=718,SUM($G69-(SUM($H69:$I69))),"") | AO69: =IF($B69=719,SUM($G69-(SUM($H69:$I69))),"") | AP69: =IF($B69=717,SUM($G69-(SUM($H69:$I69))),"") | AQ69: =IF($B69=722,SUM($G69-(SUM($H69:$I69))),"") | AR69: =IF($B69=708,SUM($G69-(SUM($H69:$I69))),"") | AS69: =IF($B69=701,SUM($G69-(SUM($H69:$I69))),"") | AT69: =IF($B69=702,SUM($G69-(SUM($H69:$I69))),"") | AU69: =IF($B69=731,SUM($G69-(SUM($H69:$I69))),"") | AV69: =IF($B69=730,SUM($G69-(SUM($H69:$I69))),"")
B70: 733 | C70: Body Corp Fees / Council Rates | D70: =D69+G70 -> 0 | F70: =SUM(H70:AV70)-G70 -> 0 | G70: 0 | H70: =IF(G70/23*3>0,SUM(G70/23*3),"") | I70: =IF(G70/23*3<0,SUM(G70/23*3),"") | J70: =IF($B70=707,SUM($G70-(SUM($H70:$I70))),"") | K70: =IF($B70=706,SUM($G70-(SUM($H70:$I70))),"") | L70: =IF($B70=703,SUM($G70-(SUM($H70:$I70))),"") | M70: =IF($B70=704,SUM($G70-(SUM($H70:$I70))),"") | N70: =IF($B70=709,SUM($G70-(SUM($H70:$I70))),"") | O70: =IF($B70=738,SUM($G70-(SUM($H70:$I70))),"") | P70: =IF($B70=739,SUM($G70-(SUM($H70:$I70))),"") | Q70: =IF($B70=714,SUM($G70-(SUM($H70:$I70))),"") | R70: =IF($B70=710,SUM($G70-(SUM($H70:$I70))),"") | S70: =IF($B70=711,SUM($G70-(SUM($H70:$I70))),"") | T70: =IF($B70=712,SUM($G70-(SUM($H70:$I70))),"") | U70: =IF($B70=713,SUM($G70-(SUM($H70:$I70))),"") | V70: =IF($B70=715,SUM($G70-(SUM($H70:$I70))),"") | W70: =IF($B70=724,SUM($G70-(SUM($H70:$I70))),"") | X70: =IF($B70=725,SUM($G70-(SUM($H70:$I70))),"") | Y70: =IF($B70=726,SUM($G70-(SUM($H70:$I70))),"") | Z70: =IF($B70=727,SUM($G70-(SUM($H70:$I70))),"") | AA70: =IF($B70=728,SUM($G70-(SUM($H70:$I70))),"") | AB70: =IF($B70=729,SUM($G70-(SUM($H70:$I70))),"") | AC70: =IF($B70=730,SUM($G70-(SUM($H70:$I70))),"") | AD70: =IF($B70=732,SUM($G70-(SUM($H70:$I70))),"") | AE70: =IF($B70=733,SUM($G70-(SUM($H70:$I70))),"") -> 0 | AF70: =IF($B70=734,SUM($G70-(SUM($H70:$I70))),"") | AG70: =IF($B70=705,SUM($G70-(SUM($H70:$I70))),"") | AH70: =IF($B70=735,SUM($G70-(SUM($H70:$I70))),"") | AI70: =IF($B70=736,SUM($G70-(SUM($H70:$I70))),"") | AJ70: =IF($B70=737,SUM($G70-(SUM($H70:$I70))),"") | AK70: =IF($B70=725,SUM($G70-(SUM($H70:$I70))),"") | AL70: =IF($B70=735,SUM($G70-(SUM($H70:$I70))),"") | AM70: =IF($B70=727,SUM($G70-(SUM($H70:$I70))),"") | AN70: =IF($B70=718,SUM($G70-(SUM($H70:$I70))),"") | AO70: =IF($B70=719,SUM($G70-(SUM($H70:$I70))),"") | AP70: =IF($B70=717,SUM($G70-(SUM($H70:$I70))),"") | AQ70: =IF($B70=722,SUM($G70-(SUM($H70:$I70))),"") | AR70: =IF($B70=708,SUM($G70-(SUM($H70:$I70))),"") | AS70: =IF($B70=701,SUM($G70-(SUM($H70:$I70))),"") | AT70: =IF($B70=702,SUM($G70-(SUM($H70:$I70))),"") | AU70: =IF($B70=731,SUM($G70-(SUM($H70:$I70))),"") | AV70: =IF($B70=730,SUM($G70-(SUM($H70:$I70))),"")
D71: =D70+G71 -> 0 | F71: =SUM(H71:AV71)-G71 -> 0 | H71: =IF(G71/23*3>0,SUM(G71/23*3),"") | I71: =IF(G71/23*3<0,SUM(G71/23*3),"") | J71: =IF($B71=707,SUM($G71-(SUM($H71:$I71))),"") | K71: =IF($B71=706,SUM($G71-(SUM($H71:$I71))),"") | L71: =IF($B71=703,SUM($G71-(SUM($H71:$I71))),"") | M71: =IF($B71=704,SUM($G71-(SUM($H71:$I71))),"") | N71: =IF($B71=709,SUM($G71-(SUM($H71:$I71))),"") | O71: =IF($B71=738,SUM($G71-(SUM($H71:$I71))),"") | P71: =IF($B71=739,SUM($G71-(SUM($H71:$I71))),"") | Q71: =IF($B71=714,SUM($G71-(SUM($H71:$I71))),"") | R71: =IF($B71=710,SUM($G71-(SUM($H71:$I71))),"") | S71: =IF($B71=711,SUM($G71-(SUM($H71:$I71))),"") | T71: =IF($B71=712,SUM($G71-(SUM($H71:$I71))),"") | U71: =IF($B71=713,SUM($G71-(SUM($H71:$I71))),"") | V71: =IF($B71=715,SUM($G71-(SUM($H71:$I71))),"") | W71: =IF($B71=724,SUM($G71-(SUM($H71:$I71))),"") | X71: =IF($B71=725,SUM($G71-(SUM($H71:$I71))),"") | Y71: =IF($B71=726,SUM($G71-(SUM($H71:$I71))),"") | Z71: =IF($B71=727,SUM($G71-(SUM($H71:$I71))),"") | AA71: =IF($B71=728,SUM($G71-(SUM($H71:$I71))),"") | AB71: =IF($B71=729,SUM($G71-(SUM($H71:$I71))),"") | AC71: =IF($B71=730,SUM($G71-(SUM($H71:$I71))),"") | AD71: =IF($B71=732,SUM($G71-(SUM($H71:$I71))),"") | AE71: =IF($B71=733,SUM($G71-(SUM($H71:$I71))),"") | AF71: =IF($B71=734,SUM($G71-(SUM($H71:$I71))),"") | AG71: =IF($B71=705,SUM($G71-(SUM($H71:$I71))),"") | AH71: =IF($B71=735,SUM($G71-(SUM($H71:$I71))),"") | AI71: =IF($B71=736,SUM($G71-(SUM($H71:$I71))),"") | AJ71: =IF($B71=737,SUM($G71-(SUM($H71:$I71))),"") | AK71: =IF($B71=725,SUM($G71-(SUM($H71:$I71))),"") | AL71: =IF($B71=735,SUM($G71-(SUM($H71:$I71))),"") | AM71: =IF($B71=727,SUM($G71-(SUM($H71:$I71))),"") | AN71: =IF($B71=718,SUM($G71-(SUM($H71:$I71))),"") | AO71: =IF($B71=719,SUM($G71-(SUM($H71:$I71))),"") | AP71: =IF($B71=717,SUM($G71-(SUM($H71:$I71))),"") | AQ71: =IF($B71=722,SUM($G71-(SUM($H71:$I71))),"") | AR71: =IF($B71=708,SUM($G71-(SUM($H71:$I71))),"") | AS71: =IF($B71=701,SUM($G71-(SUM($H71:$I71))),"") | AT71: =IF($B71=702,SUM($G71-(SUM($H71:$I71))),"") | AU71: =IF($B71=731,SUM($G71-(SUM($H71:$I71))),"") | AV71: =IF($B71=730,SUM($G71-(SUM($H71:$I71))),"")
B72: 707 | C72: Income - February - Client (50% progress payment received) | D72: =D71+G72 -> 0 | F72: =SUM(H72:AV72)-G72 -> 0 | G72: 0 | H72: =IF(G72/23*3>0,SUM(G72/23*3),"") | I72: =IF(G72/23*3<0,SUM(G72/23*3),"") | J72: =IF($B72=707,SUM($G72-(SUM($H72:$I72))),"") -> 0 | K72: =IF($B72=706,SUM($G72-(SUM($H72:$I72))),"") | L72: =IF($B72=703,SUM($G72-(SUM($H72:$I72))),"") | M72: =IF($B72=704,SUM($G72-(SUM($H72:$I72))),"") | N72: =IF($B72=709,SUM($G72-(SUM($H72:$I72))),"") | O72: =IF($B72=738,SUM($G72-(SUM($H72:$I72))),"") | P72: =IF($B72=739,SUM($G72-(SUM($H72:$I72))),"") | Q72: =IF($B72=714,SUM($G72-(SUM($H72:$I72))),"") | R72: =IF($B72=710,SUM($G72-(SUM($H72:$I72))),"") | S72: =IF($B72=711,SUM($G72-(SUM($H72:$I72))),"") | T72: =IF($B72=712,SUM($G72-(SUM($H72:$I72))),"") | U72: =IF($B72=713,SUM($G72-(SUM($H72:$I72))),"") | V72: =IF($B72=715,SUM($G72-(SUM($H72:$I72))),"") | W72: =IF($B72=724,SUM($G72-(SUM($H72:$I72))),"") | X72: =IF($B72=725,SUM($G72-(SUM($H72:$I72))),"") | Y72: =IF($B72=726,SUM($G72-(SUM($H72:$I72))),"") | Z72: =IF($B72=727,SUM($G72-(SUM($H72:$I72))),"") | AA72: =IF($B72=728,SUM($G72-(SUM($H72:$I72))),"") | AB72: =IF($B72=729,SUM($G72-(SUM($H72:$I72))),"") | AC72: =IF($B72=730,SUM($G72-(SUM($H72:$I72))),"") | AD72: =IF($B72=732,SUM($G72-(SUM($H72:$I72))),"") | AE72: =IF($B72=733,SUM($G72-(SUM($H72:$I72))),"") | AF72: =IF($B72=734,SUM($G72-(SUM($H72:$I72))),"") | AG72: =IF($B72=705,SUM($G72-(SUM($H72:$I72))),"") | AH72: =IF($B72=735,SUM($G72-(SUM($H72:$I72))),"") | AI72: =IF($B72=736,SUM($G72-(SUM($H72:$I72))),"") | AJ72: =IF($B72=737,SUM($G72-(SUM($H72:$I72))),"") | AK72: =IF($B72=725,SUM($G72-(SUM($H72:$I72))),"") | AL72: =IF($B72=735,SUM($G72-(SUM($H72:$I72))),"") | AM72: =IF($B72=727,SUM($G72-(SUM($H72:$I72))),"") | AN72: =IF($B72=718,SUM($G72-(SUM($H72:$I72))),"") | AO72: =IF($B72=719,SUM($G72-(SUM($H72:$I72))),"") | AP72: =IF($B72=717,SUM($G72-(SUM($H72:$I72))),"") | AQ72: =IF($B72=722,SUM($G72-(SUM($H72:$I72))),"") | AR72: =IF($B72=708,SUM($G72-(SUM($H72:$I72))),"") | AS72: =IF($B72=701,SUM($G72-(SUM($H72:$I72))),"") | AT72: =IF($B72=702,SUM($G72-(SUM($H72:$I72))),"") | AU72: =IF($B72=731,SUM($G72-(SUM($H72:$I72))),"") | AV72: =IF($B72=730,SUM($G72-(SUM($H72:$I72))),"")
B73: 725 | C73: Power - Fibrewave | D73: =D72+G73 -> 0 | F73: =SUM(H73:AV73)-G73 -> 0 | G73: 0 | H73: =IF(G73/23*3>0,SUM(G73/23*3),"") | I73: =IF(G73/23*3<0,SUM(G73/23*3),"") | J73: =IF($B73=707,SUM($G73-(SUM($H73:$I73))),"") | K73: =IF($B73=706,SUM($G73-(SUM($H73:$I73))),"") | L73: =IF($B73=703,SUM($G73-(SUM($H73:$I73))),"") | M73: =IF($B73=704,SUM($G73-(SUM($H73:$I73))),"") | N73: =IF($B73=709,SUM($G73-(SUM($H73:$I73))),"") | O73: =IF($B73=738,SUM($G73-(SUM($H73:$I73))),"") | P73: =IF($B73=739,SUM($G73-(SUM($H73:$I73))),"") | Q73: =IF($B73=714,SUM($G73-(SUM($H73:$I73))),"") | R73: =IF($B73=710,SUM($G73-(SUM($H73:$I73))),"") | S73: =IF($B73=711,SUM($G73-(SUM($H73:$I73))),"") | T73: =IF($B73=712,SUM($G73-(SUM($H73:$I73))),"") | U73: =IF($B73=713,SUM($G73-(SUM($H73:$I73))),"") | V73: =IF($B73=715,SUM($G73-(SUM($H73:$I73))),"") | W73: =IF($B73=724,SUM($G73-(SUM($H73:$I73))),"") | X73: =IF($B73=725,SUM($G73-(SUM($H73:$I73))),"") -> 0 | Y73: =IF($B73=726,SUM($G73-(SUM($H73:$I73))),"") | Z73: =IF($B73=727,SUM($G73-(SUM($H73:$I73))),"") | AA73: =IF($B73=728,SUM($G73-(SUM($H73:$I73))),"") | AB73: =IF($B73=729,SUM($G73-(SUM($H73:$I73))),"") | AC73: =IF($B73=730,SUM($G73-(SUM($H73:$I73))),"") | AD73: =IF($B73=732,SUM($G73-(SUM($H73:$I73))),"") | AE73: =IF($B73=733,SUM($G73-(SUM($H73:$I73))),"") | AF73: =IF($B73=734,SUM($G73-(SUM($H73:$I73))),"") | AG73: =IF($B73=705,SUM($G73-(SUM($H73:$I73))),"") | AH73: =IF($B73=735,SUM($G73-(SUM($H73:$I73))),"") | AI73: =IF($B73=736,SUM($G73-(SUM($H73:$I73))),"") | AJ73: =IF($B73=737,SUM($G73-(SUM($H73:$I73))),"") | AK73: =IF($B73=725,SUM($G73-(SUM($H73:$I73))),"") -> 0 | AL73: =IF($B73=735,SUM($G73-(SUM($H73:$I73))),"") | AM73: =IF($B73=727,SUM($G73-(SUM($H73:$I73))),"") | AN73: =IF($B73=718,SUM($G73-(SUM($H73:$I73))),"") | AO73: =IF($B73=719,SUM($G73-(SUM($H73:$I73))),"") | AP73: =IF($B73=717,SUM($G73-(SUM($H73:$I73))),"") | AQ73: =IF($B73=722,SUM($G73-(SUM($H73:$I73))),"") | AR73: =IF($B73=708,SUM($G73-(SUM($H73:$I73))),"") | AS73: =IF($B73=701,SUM($G73-(SUM($H73:$I73))),"") | AT73: =IF($B73=702,SUM($G73-(SUM($H73:$I73))),"") | AU73: =IF($B73=731,SUM($G73-(SUM($H73:$I73))),"") | AV73: =IF($B73=730,SUM($G73-(SUM($H73:$I73))),"")
B74: 726 | C74: Entertainment (Business Lunch/Coffee/Meals/Drinks) | D74: =D73+G74 -> 0 | F74: =SUM(H74:AV74)-G74 -> 0 | G74: =-(OtherCalculation!C9) -> 0 | H74: =IF(G74/23*3>0,SUM(G74/23*3),"") | I74: =IF(G74/23*3<0,SUM(G74/23*3),"") | J74: =IF($B74=707,SUM($G74-(SUM($H74:$I74))),"") | K74: =IF($B74=706,SUM($G74-(SUM($H74:$I74))),"") | L74: =IF($B74=703,SUM($G74-(SUM($H74:$I74))),"") | M74: =IF($B74=704,SUM($G74-(SUM($H74:$I74))),"") | N74: =IF($B74=709,SUM($G74-(SUM($H74:$I74))),"") | O74: =IF($B74=738,SUM($G74-(SUM($H74:$I74))),"") | P74: =IF($B74=739,SUM($G74-(SUM($H74:$I74))),"") | Q74: =IF($B74=714,SUM($G74-(SUM($H74:$I74))),"") | R74: =IF($B74=710,SUM($G74-(SUM($H74:$I74))),"") | S74: =IF($B74=711,SUM($G74-(SUM($H74:$I74))),"") | T74: =IF($B74=712,SUM($G74-(SUM($H74:$I74))),"") | U74: =IF($B74=713,SUM($G74-(SUM($H74:$I74))),"") | V74: =IF($B74=715,SUM($G74-(SUM($H74:$I74))),"") | W74: =IF($B74=724,SUM($G74-(SUM($H74:$I74))),"") | X74: =IF($B74=725,SUM($G74-(SUM($H74:$I74))),"") | Y74: =IF($B74=726,SUM($G74-(SUM($H74:$I74))),"") -> 0 | Z74: =IF($B74=727,SUM($G74-(SUM($H74:$I74))),"") | AA74: =IF($B74=728,SUM($G74-(SUM($H74:$I74))),"") | AB74: =IF($B74=729,SUM($G74-(SUM($H74:$I74))),"") | AC74: =IF($B74=730,SUM($G74-(SUM($H74:$I74))),"") | AD74: =IF($B74=732,SUM($G74-(SUM($H74:$I74))),"") | AE74: =IF($B74=733,SUM($G74-(SUM($H74:$I74))),"") | AF74: =IF($B74=734,SUM($G74-(SUM($H74:$I74))),"") | AG74: =IF($B74=705,SUM($G74-(SUM($H74:$I74))),"") | AH74: =IF($B74=735,SUM($G74-(SUM($H74:$I74))),"") | AI74: =IF($B74=736,SUM($G74-(SUM($H74:$I74))),"") | AJ74: =IF($B74=737,SUM($G74-(SUM($H74:$I74))),"") | AK74: =IF($B74=725,SUM($G74-(SUM($H74:$I74))),"") | AL74: =IF($B74=735,SUM($G74-(SUM($H74:$I74))),"") | AM74: =IF($B74=727,SUM($G74-(SUM($H74:$I74))),"") | AN74: =IF($B74=718,SUM($G74-(SUM($H74:$I74))),"") | AO74: =IF($B74=719,SUM($G74-(SUM($H74:$I74))),"") | AP74: =IF($B74=717,SUM($G74-(SUM($H74:$I74))),"") | AQ74: =IF($B74=722,SUM($G74-(SUM($H74:$I74))),"") | AR74: =IF($B74=708,SUM($G74-(SUM($H74:$I74))),"") | AS74: =IF($B74=701,SUM($G74-(SUM($H74:$I74))),"") | AT74: =IF($B74=702,SUM($G74-(SUM($H74:$I74))),"") | AU74: =IF($B74=731,SUM($G74-(SUM($H74:$I74))),"") | AV74: =IF($B74=730,SUM($G74-(SUM($H74:$I74))),"")
B75: 730 | C75: Home Contents Insurance | D75: =D74+G75 -> 0 | F75: =SUM(H75:AV75)-G75 -> 0 | G75: 0 | H75: =IF(G75/23*3>0,SUM(G75/23*3),"") | I75: =IF(G75/23*3<0,SUM(G75/23*3),"") | J75: =IF($B75=707,SUM($G75-(SUM($H75:$I75))),"") | K75: =IF($B75=706,SUM($G75-(SUM($H75:$I75))),"") | L75: =IF($B75=703,SUM($G75-(SUM($H75:$I75))),"") | M75: =IF($B75=704,SUM($G75-(SUM($H75:$I75))),"") | N75: =IF($B75=709,SUM($G75-(SUM($H75:$I75))),"") | O75: =IF($B75=738,SUM($G75-(SUM($H75:$I75))),"") | P75: =IF($B75=739,SUM($G75-(SUM($H75:$I75))),"") | Q75: =IF($B75=714,SUM($G75-(SUM($H75:$I75))),"") | R75: =IF($B75=710,SUM($G75-(SUM($H75:$I75))),"") | S75: =IF($B75=711,SUM($G75-(SUM($H75:$I75))),"") | T75: =IF($B75=712,SUM($G75-(SUM($H75:$I75))),"") | U75: =IF($B75=713,SUM($G75-(SUM($H75:$I75))),"") | V75: =IF($B75=715,SUM($G75-(SUM($H75:$I75))),"") | W75: =IF($B75=724,SUM($G75-(SUM($H75:$I75))),"") | X75: =IF($B75=725,SUM($G75-(SUM($H75:$I75))),"") | Y75: =IF($B75=726,SUM($G75-(SUM($H75:$I75))),"") | Z75: =IF($B75=727,SUM($G75-(SUM($H75:$I75))),"") | AA75: =IF($B75=728,SUM($G75-(SUM($H75:$I75))),"") | AB75: =IF($B75=729,SUM($G75-(SUM($H75:$I75))),"") | AC75: =IF($B75=730,SUM($G75-(SUM($H75:$I75))),"") -> 0 | AD75: =IF($B75=732,SUM($G75-(SUM($H75:$I75))),"") | AE75: =IF($B75=733,SUM($G75-(SUM($H75:$I75))),"") | AF75: =IF($B75=734,SUM($G75-(SUM($H75:$I75))),"") | AG75: =IF($B75=705,SUM($G75-(SUM($H75:$I75))),"") | AH75: =IF($B75=735,SUM($G75-(SUM($H75:$I75))),"") | AI75: =IF($B75=736,SUM($G75-(SUM($H75:$I75))),"") | AJ75: =IF($B75=737,SUM($G75-(SUM($H75:$I75))),"") | AK75: =IF($B75=725,SUM($G75-(SUM($H75:$I75))),"") | AL75: =IF($B75=735,SUM($G75-(SUM($H75:$I75))),"") | AM75: =IF($B75=727,SUM($G75-(SUM($H75:$I75))),"") | AN75: =IF($B75=718,SUM($G75-(SUM($H75:$I75))),"") | AO75: =IF($B75=719,SUM($G75-(SUM($H75:$I75))),"") | AP75: =IF($B75=717,SUM($G75-(SUM($H75:$I75))),"") | AQ75: =IF($B75=722,SUM($G75-(SUM($H75:$I75))),"") | AR75: =IF($B75=708,SUM($G75-(SUM($H75:$I75))),"") | AS75: =IF($B75=701,SUM($G75-(SUM($H75:$I75))),"") | AT75: =IF($B75=702,SUM($G75-(SUM($H75:$I75))),"") | AU75: =IF($B75=731,SUM($G75-(SUM($H75:$I75))),"") | AV75: =IF($B75=730,SUM($G75-(SUM($H75:$I75))),"") -> 0
B76: 727 | C76: Internet - Fibrewave | D76: =D75+G76 -> 0 | F76: =SUM(H76:AV76)-G76 -> 0 | G76: 0 | H76: =IF(G76/23*3>0,SUM(G76/23*3),"") | I76: =IF(G76/23*3<0,SUM(G76/23*3),"") | J76: =IF($B76=707,SUM($G76-(SUM($H76:$I76))),"") | K76: =IF($B76=706,SUM($G76-(SUM($H76:$I76))),"") | L76: =IF($B76=703,SUM($G76-(SUM($H76:$I76))),"") | M76: =IF($B76=704,SUM($G76-(SUM($H76:$I76))),"") | N76: =IF($B76=709,SUM($G76-(SUM($H76:$I76))),"") | O76: =IF($B76=738,SUM($G76-(SUM($H76:$I76))),"") | P76: =IF($B76=739,SUM($G76-(SUM($H76:$I76))),"") | Q76: =IF($B76=714,SUM($G76-(SUM($H76:$I76))),"") | R76: =IF($B76=710,SUM($G76-(SUM($H76:$I76))),"") | S76: =IF($B76=711,SUM($G76-(SUM($H76:$I76))),"") | T76: =IF($B76=712,SUM($G76-(SUM($H76:$I76))),"") | U76: =IF($B76=713,SUM($G76-(SUM($H76:$I76))),"") | V76: =IF($B76=715,SUM($G76-(SUM($H76:$I76))),"") | W76: =IF($B76=724,SUM($G76-(SUM($H76:$I76))),"") | X76: =IF($B76=725,SUM($G76-(SUM($H76:$I76))),"") | Y76: =IF($B76=726,SUM($G76-(SUM($H76:$I76))),"") | Z76: =IF($B76=727,SUM($G76-(SUM($H76:$I76))),"") -> 0 | AA76: =IF($B76=728,SUM($G76-(SUM($H76:$I76))),"") | AB76: =IF($B76=729,SUM($G76-(SUM($H76:$I76))),"") | AC76: =IF($B76=730,SUM($G76-(SUM($H76:$I76))),"") | AD76: =IF($B76=732,SUM($G76-(SUM($H76:$I76))),"") | AE76: =IF($B76=733,SUM($G76-(SUM($H76:$I76))),"") | AF76: =IF($B76=734,SUM($G76-(SUM($H76:$I76))),"") | AG76: =IF($B76=705,SUM($G76-(SUM($H76:$I76))),"") | AH76: =IF($B76=735,SUM($G76-(SUM($H76:$I76))),"") | AI76: =IF($B76=736,SUM($G76-(SUM($H76:$I76))),"") | AJ76: =IF($B76=737,SUM($G76-(SUM($H76:$I76))),"") | AK76: =IF($B76=725,SUM($G76-(SUM($H76:$I76))),"") | AL76: =IF($B76=735,SUM($G76-(SUM($H76:$I76))),"") | AM76: =IF($B76=727,SUM($G76-(SUM($H76:$I76))),"") -> 0 | AN76: =IF($B76=718,SUM($G76-(SUM($H76:$I76))),"") | AO76: =IF($B76=719,SUM($G76-(SUM($H76:$I76))),"") | AP76: =IF($B76=717,SUM($G76-(SUM($H76:$I76))),"") | AQ76: =IF($B76=722,SUM($G76-(SUM($H76:$I76))),"") | AR76: =IF($B76=708,SUM($G76-(SUM($H76:$I76))),"") | AS76: =IF($B76=701,SUM($G76-(SUM($H76:$I76))),"") | AT76: =IF($B76=702,SUM($G76-(SUM($H76:$I76))),"") | AU76: =IF($B76=731,SUM($G76-(SUM($H76:$I76))),"") | AV76: =IF($B76=730,SUM($G76-(SUM($H76:$I76))),"")
B77: 728 | C77: Mobile Plan - Tui Mobile NZ | D77: =D76+G77 -> 0 | F77: =SUM(H77:AV77)-G77 -> 0 | G77: 0 | H77: =IF(G77/23*3>0,SUM(G77/23*3),"") | I77: =IF(G77/23*3<0,SUM(G77/23*3),"") | J77: =IF($B77=707,SUM($G77-(SUM($H77:$I77))),"") | K77: =IF($B77=706,SUM($G77-(SUM($H77:$I77))),"") | L77: =IF($B77=703,SUM($G77-(SUM($H77:$I77))),"") | M77: =IF($B77=704,SUM($G77-(SUM($H77:$I77))),"") | N77: =IF($B77=709,SUM($G77-(SUM($H77:$I77))),"") | O77: =IF($B77=738,SUM($G77-(SUM($H77:$I77))),"") | P77: =IF($B77=739,SUM($G77-(SUM($H77:$I77))),"") | Q77: =IF($B77=714,SUM($G77-(SUM($H77:$I77))),"") | R77: =IF($B77=710,SUM($G77-(SUM($H77:$I77))),"") | S77: =IF($B77=711,SUM($G77-(SUM($H77:$I77))),"") | T77: =IF($B77=712,SUM($G77-(SUM($H77:$I77))),"") | U77: =IF($B77=713,SUM($G77-(SUM($H77:$I77))),"") | V77: =IF($B77=715,SUM($G77-(SUM($H77:$I77))),"") | W77: =IF($B77=724,SUM($G77-(SUM($H77:$I77))),"") | X77: =IF($B77=725,SUM($G77-(SUM($H77:$I77))),"") | Y77: =IF($B77=726,SUM($G77-(SUM($H77:$I77))),"") | Z77: =IF($B77=727,SUM($G77-(SUM($H77:$I77))),"") | AA77: =IF($B77=728,SUM($G77-(SUM($H77:$I77))),"") -> 0 | AB77: =IF($B77=729,SUM($G77-(SUM($H77:$I77))),"") | AC77: =IF($B77=730,SUM($G77-(SUM($H77:$I77))),"") | AD77: =IF($B77=732,SUM($G77-(SUM($H77:$I77))),"") | AE77: =IF($B77=733,SUM($G77-(SUM($H77:$I77))),"") | AF77: =IF($B77=734,SUM($G77-(SUM($H77:$I77))),"") | AG77: =IF($B77=705,SUM($G77-(SUM($H77:$I77))),"") | AH77: =IF($B77=735,SUM($G77-(SUM($H77:$I77))),"") | AI77: =IF($B77=736,SUM($G77-(SUM($H77:$I77))),"") | AJ77: =IF($B77=737,SUM($G77-(SUM($H77:$I77))),"") | AK77: =IF($B77=725,SUM($G77-(SUM($H77:$I77))),"") | AL77: =IF($B77=735,SUM($G77-(SUM($H77:$I77))),"") | AM77: =IF($B77=727,SUM($G77-(SUM($H77:$I77))),"") | AN77: =IF($B77=718,SUM($G77-(SUM($H77:$I77))),"") | AO77: =IF($B77=719,SUM($G77-(SUM($H77:$I77))),"") | AP77: =IF($B77=717,SUM($G77-(SUM($H77:$I77))),"") | AQ77: =IF($B77=722,SUM($G77-(SUM($H77:$I77))),"") | AR77: =IF($B77=708,SUM($G77-(SUM($H77:$I77))),"") | AS77: =IF($B77=701,SUM($G77-(SUM($H77:$I77))),"") | AT77: =IF($B77=702,SUM($G77-(SUM($H77:$I77))),"") | AU77: =IF($B77=731,SUM($G77-(SUM($H77:$I77))),"") | AV77: =IF($B77=730,SUM($G77-(SUM($H77:$I77))),"")
B78: 729 | C78: Car Park Fees | D78: =D77+G78 -> 0 | F78: =SUM(H78:AV78)-G78 -> 0 | G78: 0 | H78: =IF(G78/23*3>0,SUM(G78/23*3),"") | I78: =IF(G78/23*3<0,SUM(G78/23*3),"") | J78: =IF($B78=707,SUM($G78-(SUM($H78:$I78))),"") | K78: =IF($B78=706,SUM($G78-(SUM($H78:$I78))),"") | L78: =IF($B78=703,SUM($G78-(SUM($H78:$I78))),"") | M78: =IF($B78=704,SUM($G78-(SUM($H78:$I78))),"") | N78: =IF($B78=709,SUM($G78-(SUM($H78:$I78))),"") | O78: =IF($B78=738,SUM($G78-(SUM($H78:$I78))),"") | P78: =IF($B78=739,SUM($G78-(SUM($H78:$I78))),"") | Q78: =IF($B78=714,SUM($G78-(SUM($H78:$I78))),"") | R78: =IF($B78=710,SUM($G78-(SUM($H78:$I78))),"") | S78: =IF($B78=711,SUM($G78-(SUM($H78:$I78))),"") | T78: =IF($B78=712,SUM($G78-(SUM($H78:$I78))),"") | U78: =IF($B78=713,SUM($G78-(SUM($H78:$I78))),"") | V78: =IF($B78=715,SUM($G78-(SUM($H78:$I78))),"") | W78: =IF($B78=724,SUM($G78-(SUM($H78:$I78))),"") | X78: =IF($B78=725,SUM($G78-(SUM($H78:$I78))),"") | Y78: =IF($B78=726,SUM($G78-(SUM($H78:$I78))),"") | Z78: =IF($B78=727,SUM($G78-(SUM($H78:$I78))),"") | AA78: =IF($B78=728,SUM($G78-(SUM($H78:$I78))),"") | AB78: =IF($B78=729,SUM($G78-(SUM($H78:$I78))),"") -> 0 | AC78: =IF($B78=730,SUM($G78-(SUM($H78:$I78))),"") | AD78: =IF($B78=732,SUM($G78-(SUM($H78:$I78))),"") | AE78: =IF($B78=733,SUM($G78-(SUM($H78:$I78))),"") | AF78: =IF($B78=734,SUM($G78-(SUM($H78:$I78))),"") | AG78: =IF($B78=705,SUM($G78-(SUM($H78:$I78))),"") | AH78: =IF($B78=735,SUM($G78-(SUM($H78:$I78))),"") | AI78: =IF($B78=736,SUM($G78-(SUM($H78:$I78))),"") | AJ78: =IF($B78=737,SUM($G78-(SUM($H78:$I78))),"") | AK78: =IF($B78=725,SUM($G78-(SUM($H78:$I78))),"") | AL78: =IF($B78=735,SUM($G78-(SUM($H78:$I78))),"") | AM78: =IF($B78=727,SUM($G78-(SUM($H78:$I78))),"") | AN78: =IF($B78=718,SUM($G78-(SUM($H78:$I78))),"") | AO78: =IF($B78=719,SUM($G78-(SUM($H78:$I78))),"") | AP78: =IF($B78=717,SUM($G78-(SUM($H78:$I78))),"") | AQ78: =IF($B78=722,SUM($G78-(SUM($H78:$I78))),"") | AR78: =IF($B78=708,SUM($G78-(SUM($H78:$I78))),"") | AS78: =IF($B78=701,SUM($G78-(SUM($H78:$I78))),"") | AT78: =IF($B78=702,SUM($G78-(SUM($H78:$I78))),"") | AU78: =IF($B78=731,SUM($G78-(SUM($H78:$I78))),"") | AV78: =IF($B78=730,SUM($G78-(SUM($H78:$I78))),"")
B79: 733 | C79: Body Corp Fees / Council Rates | D79: =D78+G79 -> 0 | F79: =SUM(H79:AV79)-G79 -> 0 | G79: 0 | H79: =IF(G79/23*3>0,SUM(G79/23*3),"") | I79: =IF(G79/23*3<0,SUM(G79/23*3),"") | J79: =IF($B79=707,SUM($G79-(SUM($H79:$I79))),"") | K79: =IF($B79=706,SUM($G79-(SUM($H79:$I79))),"") | L79: =IF($B79=703,SUM($G79-(SUM($H79:$I79))),"") | M79: =IF($B79=704,SUM($G79-(SUM($H79:$I79))),"") | N79: =IF($B79=709,SUM($G79-(SUM($H79:$I79))),"") | O79: =IF($B79=738,SUM($G79-(SUM($H79:$I79))),"") | P79: =IF($B79=739,SUM($G79-(SUM($H79:$I79))),"") | Q79: =IF($B79=714,SUM($G79-(SUM($H79:$I79))),"") | R79: =IF($B79=710,SUM($G79-(SUM($H79:$I79))),"") | S79: =IF($B79=711,SUM($G79-(SUM($H79:$I79))),"") | T79: =IF($B79=712,SUM($G79-(SUM($H79:$I79))),"") | U79: =IF($B79=713,SUM($G79-(SUM($H79:$I79))),"") | V79: =IF($B79=715,SUM($G79-(SUM($H79:$I79))),"") | W79: =IF($B79=724,SUM($G79-(SUM($H79:$I79))),"") | X79: =IF($B79=725,SUM($G79-(SUM($H79:$I79))),"") | Y79: =IF($B79=726,SUM($G79-(SUM($H79:$I79))),"") | Z79: =IF($B79=727,SUM($G79-(SUM($H79:$I79))),"") | AA79: =IF($B79=728,SUM($G79-(SUM($H79:$I79))),"") | AB79: =IF($B79=729,SUM($G79-(SUM($H79:$I79))),"") | AC79: =IF($B79=730,SUM($G79-(SUM($H79:$I79))),"") | AD79: =IF($B79=732,SUM($G79-(SUM($H79:$I79))),"") | AE79: =IF($B79=733,SUM($G79-(SUM($H79:$I79))),"") -> 0 | AF79: =IF($B79=734,SUM($G79-(SUM($H79:$I79))),"") | AG79: =IF($B79=705,SUM($G79-(SUM($H79:$I79))),"") | AH79: =IF($B79=735,SUM($G79-(SUM($H79:$I79))),"") | AI79: =IF($B79=736,SUM($G79-(SUM($H79:$I79))),"") | AJ79: =IF($B79=737,SUM($G79-(SUM($H79:$I79))),"") | AK79: =IF($B79=725,SUM($G79-(SUM($H79:$I79))),"") | AL79: =IF($B79=735,SUM($G79-(SUM($H79:$I79))),"") | AM79: =IF($B79=727,SUM($G79-(SUM($H79:$I79))),"") | AN79: =IF($B79=718,SUM($G79-(SUM($H79:$I79))),"") | AO79: =IF($B79=719,SUM($G79-(SUM($H79:$I79))),"") | AP79: =IF($B79=717,SUM($G79-(SUM($H79:$I79))),"") | AQ79: =IF($B79=722,SUM($G79-(SUM($H79:$I79))),"") | AR79: =IF($B79=708,SUM($G79-(SUM($H79:$I79))),"") | AS79: =IF($B79=701,SUM($G79-(SUM($H79:$I79))),"") | AT79: =IF($B79=702,SUM($G79-(SUM($H79:$I79))),"") | AU79: =IF($B79=731,SUM($G79-(SUM($H79:$I79))),"") | AV79: =IF($B79=730,SUM($G79-(SUM($H79:$I79))),"")
B80: 734 | C80: Home Office Expenses | D80: =D79+G80 -> 0 | F80: =SUM(H80:AV80)-G80 -> 0 | G80: 0 | H80: =IF(G80/23*3>0,SUM(G80/23*3),"") | I80: =IF(G80/23*3<0,SUM(G80/23*3),"") | J80: =IF($B80=707,SUM($G80-(SUM($H80:$I80))),"") | K80: =IF($B80=706,SUM($G80-(SUM($H80:$I80))),"") | L80: =IF($B80=703,SUM($G80-(SUM($H80:$I80))),"") | M80: =IF($B80=704,SUM($G80-(SUM($H80:$I80))),"") | N80: =IF($B80=709,SUM($G80-(SUM($H80:$I80))),"") | O80: =IF($B80=738,SUM($G80-(SUM($H80:$I80))),"") | P80: =IF($B80=739,SUM($G80-(SUM($H80:$I80))),"") | Q80: =IF($B80=714,SUM($G80-(SUM($H80:$I80))),"") | R80: =IF($B80=710,SUM($G80-(SUM($H80:$I80))),"") | S80: =IF($B80=711,SUM($G80-(SUM($H80:$I80))),"") | T80: =IF($B80=712,SUM($G80-(SUM($H80:$I80))),"") | U80: =IF($B80=713,SUM($G80-(SUM($H80:$I80))),"") | V80: =IF($B80=715,SUM($G80-(SUM($H80:$I80))),"") | W80: =IF($B80=724,SUM($G80-(SUM($H80:$I80))),"") | X80: =IF($B80=725,SUM($G80-(SUM($H80:$I80))),"") | Y80: =IF($B80=726,SUM($G80-(SUM($H80:$I80))),"") | Z80: =IF($B80=727,SUM($G80-(SUM($H80:$I80))),"") | AA80: =IF($B80=728,SUM($G80-(SUM($H80:$I80))),"") | AB80: =IF($B80=729,SUM($G80-(SUM($H80:$I80))),"") | AC80: =IF($B80=730,SUM($G80-(SUM($H80:$I80))),"") | AD80: =IF($B80=732,SUM($G80-(SUM($H80:$I80))),"") | AE80: =IF($B80=733,SUM($G80-(SUM($H80:$I80))),"") | AF80: =IF($B80=734,SUM($G80-(SUM($H80:$I80))),"") -> 0 | AG80: =IF($B80=705,SUM($G80-(SUM($H80:$I80))),"") | AH80: =IF($B80=735,SUM($G80-(SUM($H80:$I80))),"") | AI80: =IF($B80=736,SUM($G80-(SUM($H80:$I80))),"") | AJ80: =IF($B80=737,SUM($G80-(SUM($H80:$I80))),"") | AK80: =IF($B80=725,SUM($G80-(SUM($H80:$I80))),"") | AL80: =IF($B80=735,SUM($G80-(SUM($H80:$I80))),"") | AM80: =IF($B80=727,SUM($G80-(SUM($H80:$I80))),"") | AN80: =IF($B80=718,SUM($G80-(SUM($H80:$I80))),"") | AO80: =IF($B80=719,SUM($G80-(SUM($H80:$I80))),"") | AP80: =IF($B80=717,SUM($G80-(SUM($H80:$I80))),"") | AQ80: =IF($B80=722,SUM($G80-(SUM($H80:$I80))),"") | AR80: =IF($B80=708,SUM($G80-(SUM($H80:$I80))),"") | AS80: =IF($B80=701,SUM($G80-(SUM($H80:$I80))),"") | AT80: =IF($B80=702,SUM($G80-(SUM($H80:$I80))),"") | AU80: =IF($B80=731,SUM($G80-(SUM($H80:$I80))),"") | AV80: =IF($B80=730,SUM($G80-(SUM($H80:$I80))),"")
B81: 734 | C81: Home Office Expenses | D81: =D80+G81 -> 0 | F81: =SUM(H81:AV81)-G81 -> 0 | G81: 0 | H81: =IF(G81/23*3>0,SUM(G81/23*3),"") | I81: =IF(G81/23*3<0,SUM(G81/23*3),"") | J81: =IF($B81=707,SUM($G81-(SUM($H81:$I81))),"") | K81: =IF($B81=706,SUM($G81-(SUM($H81:$I81))),"") | L81: =IF($B81=703,SUM($G81-(SUM($H81:$I81))),"") | M81: =IF($B81=704,SUM($G81-(SUM($H81:$I81))),"") | N81: =IF($B81=709,SUM($G81-(SUM($H81:$I81))),"") | O81: =IF($B81=738,SUM($G81-(SUM($H81:$I81))),"") | P81: =IF($B81=739,SUM($G81-(SUM($H81:$I81))),"") | Q81: =IF($B81=714,SUM($G81-(SUM($H81:$I81))),"") | R81: =IF($B81=710,SUM($G81-(SUM($H81:$I81))),"") | S81: =IF($B81=711,SUM($G81-(SUM($H81:$I81))),"") | T81: =IF($B81=712,SUM($G81-(SUM($H81:$I81))),"") | U81: =IF($B81=713,SUM($G81-(SUM($H81:$I81))),"") | V81: =IF($B81=715,SUM($G81-(SUM($H81:$I81))),"") | W81: =IF($B81=724,SUM($G81-(SUM($H81:$I81))),"") | X81: =IF($B81=725,SUM($G81-(SUM($H81:$I81))),"") | Y81: =IF($B81=726,SUM($G81-(SUM($H81:$I81))),"") | Z81: =IF($B81=727,SUM($G81-(SUM($H81:$I81))),"") | AA81: =IF($B81=728,SUM($G81-(SUM($H81:$I81))),"") | AB81: =IF($B81=729,SUM($G81-(SUM($H81:$I81))),"") | AC81: =IF($B81=730,SUM($G81-(SUM($H81:$I81))),"") | AD81: =IF($B81=732,SUM($G81-(SUM($H81:$I81))),"") | AE81: =IF($B81=733,SUM($G81-(SUM($H81:$I81))),"") | AF81: =IF($B81=734,SUM($G81-(SUM($H81:$I81))),"") -> 0 | AG81: =IF($B81=705,SUM($G81-(SUM($H81:$I81))),"") | AH81: =IF($B81=735,SUM($G81-(SUM($H81:$I81))),"") | AI81: =IF($B81=736,SUM($G81-(SUM($H81:$I81))),"") | AJ81: =IF($B81=737,SUM($G81-(SUM($H81:$I81))),"") | AK81: =IF($B81=725,SUM($G81-(SUM($H81:$I81))),"") | AL81: =IF($B81=735,SUM($G81-(SUM($H81:$I81))),"") | AM81: =IF($B81=727,SUM($G81-(SUM($H81:$I81))),"") | AN81: =IF($B81=718,SUM($G81-(SUM($H81:$I81))),"") | AO81: =IF($B81=719,SUM($G81-(SUM($H81:$I81))),"") | AP81: =IF($B81=717,SUM($G81-(SUM($H81:$I81))),"") | AQ81: =IF($B81=722,SUM($G81-(SUM($H81:$I81))),"") | AR81: =IF($B81=708,SUM($G81-(SUM($H81:$I81))),"") | AS81: =IF($B81=701,SUM($G81-(SUM($H81:$I81))),"") | AT81: =IF($B81=702,SUM($G81-(SUM($H81:$I81))),"") | AU81: =IF($B81=731,SUM($G81-(SUM($H81:$I81))),"") | AV81: =IF($B81=730,SUM($G81-(SUM($H81:$I81))),"")
B82: 734 | C82: Home Office Expenses | D82: =D81+G82 -> 0 | F82: =SUM(H82:AV82)-G82 -> 0 | G82: 0 | H82: =IF(G82/23*3>0,SUM(G82/23*3),"") | I82: =IF(G82/23*3<0,SUM(G82/23*3),"") | J82: =IF($B82=707,SUM($G82-(SUM($H82:$I82))),"") | K82: =IF($B82=706,SUM($G82-(SUM($H82:$I82))),"") | L82: =IF($B82=703,SUM($G82-(SUM($H82:$I82))),"") | M82: =IF($B82=704,SUM($G82-(SUM($H82:$I82))),"") | N82: =IF($B82=709,SUM($G82-(SUM($H82:$I82))),"") | O82: =IF($B82=738,SUM($G82-(SUM($H82:$I82))),"") | P82: =IF($B82=739,SUM($G82-(SUM($H82:$I82))),"") | Q82: =IF($B82=714,SUM($G82-(SUM($H82:$I82))),"") | R82: =IF($B82=710,SUM($G82-(SUM($H82:$I82))),"") | S82: =IF($B82=711,SUM($G82-(SUM($H82:$I82))),"") | T82: =IF($B82=712,SUM($G82-(SUM($H82:$I82))),"") | U82: =IF($B82=713,SUM($G82-(SUM($H82:$I82))),"") | V82: =IF($B82=715,SUM($G82-(SUM($H82:$I82))),"") | W82: =IF($B82=724,SUM($G82-(SUM($H82:$I82))),"") | X82: =IF($B82=725,SUM($G82-(SUM($H82:$I82))),"") | Y82: =IF($B82=726,SUM($G82-(SUM($H82:$I82))),"") | Z82: =IF($B82=727,SUM($G82-(SUM($H82:$I82))),"") | AA82: =IF($B82=728,SUM($G82-(SUM($H82:$I82))),"") | AB82: =IF($B82=729,SUM($G82-(SUM($H82:$I82))),"") | AC82: =IF($B82=730,SUM($G82-(SUM($H82:$I82))),"") | AD82: =IF($B82=732,SUM($G82-(SUM($H82:$I82))),"") | AE82: =IF($B82=733,SUM($G82-(SUM($H82:$I82))),"") | AF82: =IF($B82=734,SUM($G82-(SUM($H82:$I82))),"") -> 0 | AG82: =IF($B82=705,SUM($G82-(SUM($H82:$I82))),"") | AH82: =IF($B82=735,SUM($G82-(SUM($H82:$I82))),"") | AI82: =IF($B82=736,SUM($G82-(SUM($H82:$I82))),"") | AJ82: =IF($B82=737,SUM($G82-(SUM($H82:$I82))),"") | AK82: =IF($B82=725,SUM($G82-(SUM($H82:$I82))),"") | AL82: =IF($B82=735,SUM($G82-(SUM($H82:$I82))),"") | AM82: =IF($B82=727,SUM($G82-(SUM($H82:$I82))),"") | AN82: =IF($B82=718,SUM($G82-(SUM($H82:$I82))),"") | AO82: =IF($B82=719,SUM($G82-(SUM($H82:$I82))),"") | AP82: =IF($B82=717,SUM($G82-(SUM($H82:$I82))),"") | AQ82: =IF($B82=722,SUM($G82-(SUM($H82:$I82))),"") | AR82: =IF($B82=708,SUM($G82-(SUM($H82:$I82))),"") | AS82: =IF($B82=701,SUM($G82-(SUM($H82:$I82))),"") | AT82: =IF($B82=702,SUM($G82-(SUM($H82:$I82))),"") | AU82: =IF($B82=731,SUM($G82-(SUM($H82:$I82))),"") | AV82: =IF($B82=730,SUM($G82-(SUM($H82:$I82))),"")
B83: 724 | C83: Apartment Rent | D83: =D82+G83 -> 0 | F83: =SUM(H83:AV83)-G83 -> 0 | G83: 0 | H83: =IF(G83/23*3>0,SUM(G83/23*3),"") | J83: =IF($B83=707,SUM($G83-(SUM($H83:$I83))),"") | K83: =IF($B83=706,SUM($G83-(SUM($H83:$I83))),"") | L83: =IF($B83=703,SUM($G83-(SUM($H83:$I83))),"") | M83: =IF($B83=704,SUM($G83-(SUM($H83:$I83))),"") | N83: =IF($B83=709,SUM($G83-(SUM($H83:$I83))),"") | O83: =IF($B83=738,SUM($G83-(SUM($H83:$I83))),"") | P83: =IF($B83=739,SUM($G83-(SUM($H83:$I83))),"") | Q83: =IF($B83=714,SUM($G83-(SUM($H83:$I83))),"") | R83: =IF($B83=710,SUM($G83-(SUM($H83:$I83))),"") | S83: =IF($B83=711,SUM($G83-(SUM($H83:$I83))),"") | T83: =IF($B83=712,SUM($G83-(SUM($H83:$I83))),"") | U83: =IF($B83=713,SUM($G83-(SUM($H83:$I83))),"") | V83: =IF($B83=715,SUM($G83-(SUM($H83:$I83))),"") | W83: =IF($B83=724,SUM($G83-(SUM($H83:$I83))),"") -> 0 | X83: =IF($B83=725,SUM($G83-(SUM($H83:$I83))),"") | Y83: =IF($B83=726,SUM($G83-(SUM($H83:$I83))),"") | Z83: =IF($B83=727,SUM($G83-(SUM($H83:$I83))),"") | AA83: =IF($B83=728,SUM($G83-(SUM($H83:$I83))),"") | AB83: =IF($B83=729,SUM($G83-(SUM($H83:$I83))),"") | AC83: =IF($B83=730,SUM($G83-(SUM($H83:$I83))),"") | AD83: =IF($B83=732,SUM($G83-(SUM($H83:$I83))),"") | AE83: =IF($B83=733,SUM($G83-(SUM($H83:$I83))),"") | AF83: =IF($B83=734,SUM($G83-(SUM($H83:$I83))),"") | AG83: =IF($B83=705,SUM($G83-(SUM($H83:$I83))),"") | AH83: =IF($B83=735,SUM($G83-(SUM($H83:$I83))),"") | AI83: =IF($B83=736,SUM($G83-(SUM($H83:$I83))),"") | AJ83: =IF($B83=737,SUM($G83-(SUM($H83:$I83))),"") | AK83: =IF($B83=725,SUM($G83-(SUM($H83:$I83))),"") | AL83: =IF($B83=735,SUM($G83-(SUM($H83:$I83))),"") | AM83: =IF($B83=727,SUM($G83-(SUM($H83:$I83))),"") | AN83: =IF($B83=718,SUM($G83-(SUM($H83:$I83))),"") | AO83: =IF($B83=719,SUM($G83-(SUM($H83:$I83))),"") | AP83: =IF($B83=717,SUM($G83-(SUM($H83:$I83))),"") | AQ83: =IF($B83=722,SUM($G83-(SUM($H83:$I83))),"") | AR83: =IF($B83=708,SUM($G83-(SUM($H83:$I83))),"") | AS83: =IF($B83=701,SUM($G83-(SUM($H83:$I83))),"") | AT83: =IF($B83=702,SUM($G83-(SUM($H83:$I83))),"") | AU83: =IF($B83=731,SUM($G83-(SUM($H83:$I83))),"") | AV83: =IF($B83=730,SUM($G83-(SUM($H83:$I83))),"")
B84: 710 | C84: Bank Fees | D84: =D83+G84 -> 0 | F84: =SUM(H84:AV84)-G84 -> 0 | G84: 0 | H84: =IF(G84/23*3>0,SUM(G84/23*3),"") | J84: =IF($B84=707,SUM($G84-(SUM($H84:$I84))),"") | K84: =IF($B84=706,SUM($G84-(SUM($H84:$I84))),"") | L84: =IF($B84=703,SUM($G84-(SUM($H84:$I84))),"") | M84: =IF($B84=704,SUM($G84-(SUM($H84:$I84))),"") | N84: =IF($B84=709,SUM($G84-(SUM($H84:$I84))),"") | O84: =IF($B84=738,SUM($G84-(SUM($H84:$I84))),"") | P84: =IF($B84=739,SUM($G84-(SUM($H84:$I84))),"") | Q84: =IF($B84=714,SUM($G84-(SUM($H84:$I84))),"") | R84: =IF($B84=710,SUM($G84-(SUM($H84:$I84))),"") -> 0 | S84: =IF($B84=711,SUM($G84-(SUM($H84:$I84))),"") | T84: =IF($B84=712,SUM($G84-(SUM($H84:$I84))),"") | U84: =IF($B84=713,SUM($G84-(SUM($H84:$I84))),"") | V84: =IF($B84=715,SUM($G84-(SUM($H84:$I84))),"") | W84: =IF($B84=724,SUM($G84-(SUM($H84:$I84))),"") | X84: =IF($B84=725,SUM($G84-(SUM($H84:$I84))),"") | Y84: =IF($B84=726,SUM($G84-(SUM($H84:$I84))),"") | Z84: =IF($B84=727,SUM($G84-(SUM($H84:$I84))),"") | AA84: =IF($B84=728,SUM($G84-(SUM($H84:$I84))),"") | AB84: =IF($B84=729,SUM($G84-(SUM($H84:$I84))),"") | AC84: =IF($B84=730,SUM($G84-(SUM($H84:$I84))),"") | AD84: =IF($B84=732,SUM($G84-(SUM($H84:$I84))),"") | AE84: =IF($B84=733,SUM($G84-(SUM($H84:$I84))),"") | AF84: =IF($B84=734,SUM($G84-(SUM($H84:$I84))),"") | AG84: =IF($B84=705,SUM($G84-(SUM($H84:$I84))),"") | AH84: =IF($B84=735,SUM($G84-(SUM($H84:$I84))),"") | AI84: =IF($B84=736,SUM($G84-(SUM($H84:$I84))),"") | AJ84: =IF($B84=737,SUM($G84-(SUM($H84:$I84))),"") | AK84: =IF($B84=725,SUM($G84-(SUM($H84:$I84))),"") | AL84: =IF($B84=735,SUM($G84-(SUM($H84:$I84))),"") | AM84: =IF($B84=727,SUM($G84-(SUM($H84:$I84))),"") | AN84: =IF($B84=718,SUM($G84-(SUM($H84:$I84))),"") | AO84: =IF($B84=719,SUM($G84-(SUM($H84:$I84))),"") | AP84: =IF($B84=717,SUM($G84-(SUM($H84:$I84))),"") | AQ84: =IF($B84=722,SUM($G84-(SUM($H84:$I84))),"") | AR84: =IF($B84=708,SUM($G84-(SUM($H84:$I84))),"") | AS84: =IF($B84=701,SUM($G84-(SUM($H84:$I84))),"") | AT84: =IF($B84=702,SUM($G84-(SUM($H84:$I84))),"") | AU84: =IF($B84=731,SUM($G84-(SUM($H84:$I84))),"") | AV84: =IF($B84=730,SUM($G84-(SUM($H84:$I84))),"")
B85: 711 | C85: Accountant Fee (Accountancy) | D85: =D84+G85 -> 0 | F85: =SUM(H85:AV85)-G85 -> 0 | G85: 0 | H85: =IF(G85/23*3>0,SUM(G85/23*3),"") | I85: =IF(G85/23*3<0,SUM(G85/23*3),"") | J85: =IF($B85=707,SUM($G85-(SUM($H85:$I85))),"") | K85: =IF($B85=706,SUM($G85-(SUM($H85:$I85))),"") | L85: =IF($B85=703,SUM($G85-(SUM($H85:$I85))),"") | M85: =IF($B85=704,SUM($G85-(SUM($H85:$I85))),"") | N85: =IF($B85=709,SUM($G85-(SUM($H85:$I85))),"") | O85: =IF($B85=738,SUM($G85-(SUM($H85:$I85))),"") | P85: =IF($B85=739,SUM($G85-(SUM($H85:$I85))),"") | Q85: =IF($B85=714,SUM($G85-(SUM($H85:$I85))),"") | R85: =IF($B85=710,SUM($G85-(SUM($H85:$I85))),"") | S85: =IF($B85=711,SUM($G85-(SUM($H85:$I85))),"") -> 0 | T85: =IF($B85=712,SUM($G85-(SUM($H85:$I85))),"") | U85: =IF($B85=713,SUM($G85-(SUM($H85:$I85))),"") | V85: =IF($B85=715,SUM($G85-(SUM($H85:$I85))),"") | W85: =IF($B85=724,SUM($G85-(SUM($H85:$I85))),"") | X85: =IF($B85=725,SUM($G85-(SUM($H85:$I85))),"") | Y85: =IF($B85=726,SUM($G85-(SUM($H85:$I85))),"") | Z85: =IF($B85=727,SUM($G85-(SUM($H85:$I85))),"") | AA85: =IF($B85=728,SUM($G85-(SUM($H85:$I85))),"") | AB85: =IF($B85=729,SUM($G85-(SUM($H85:$I85))),"") | AC85: =IF($B85=730,SUM($G85-(SUM($H85:$I85))),"") | AD85: =IF($B85=732,SUM($G85-(SUM($H85:$I85))),"") | AE85: =IF($B85=733,SUM($G85-(SUM($H85:$I85))),"") | AF85: =IF($B85=734,SUM($G85-(SUM($H85:$I85))),"") | AG85: =IF($B85=705,SUM($G85-(SUM($H85:$I85))),"") | AH85: =IF($B85=735,SUM($G85-(SUM($H85:$I85))),"") | AI85: =IF($B85=736,SUM($G85-(SUM($H85:$I85))),"") | AJ85: =IF($B85=737,SUM($G85-(SUM($H85:$I85))),"") | AK85: =IF($B85=725,SUM($G85-(SUM($H85:$I85))),"") | AL85: =IF($B85=735,SUM($G85-(SUM($H85:$I85))),"") | AM85: =IF($B85=727,SUM($G85-(SUM($H85:$I85))),"") | AN85: =IF($B85=718,SUM($G85-(SUM($H85:$I85))),"") | AO85: =IF($B85=719,SUM($G85-(SUM($H85:$I85))),"") | AP85: =IF($B85=717,SUM($G85-(SUM($H85:$I85))),"") | AQ85: =IF($B85=722,SUM($G85-(SUM($H85:$I85))),"") | AR85: =IF($B85=708,SUM($G85-(SUM($H85:$I85))),"") | AS85: =IF($B85=701,SUM($G85-(SUM($H85:$I85))),"") | AT85: =IF($B85=702,SUM($G85-(SUM($H85:$I85))),"") | AU85: =IF($B85=731,SUM($G85-(SUM($H85:$I85))),"") | AV85: =IF($B85=730,SUM($G85-(SUM($H85:$I85))),"")
B86: 739 | C86: Online Tech Subscriptions (NO GST) | D86: =D85+G86 -> 0 | F86: =SUM(H86:AV86)-G86 -> 0 | G86: 0 | H86: =IF(G86/23*3>0,SUM(G86/23*3),"") | I86: 0 | J86: =IF($B86=707,SUM($G86-(SUM($H86:$I86))),"") | K86: =IF($B86=706,SUM($G86-(SUM($H86:$I86))),"") | L86: =IF($B86=703,SUM($G86-(SUM($H86:$I86))),"") | M86: =IF($B86=704,SUM($G86-(SUM($H86:$I86))),"") | N86: =IF($B86=709,SUM($G86-(SUM($H86:$I86))),"") | O86: =IF($B86=738,SUM($G86-(SUM($H86:$I86))),"") | P86: =IF($B86=739,SUM($G86-(SUM($H86:$I86))),"") -> 0 | Q86: =IF($B86=714,SUM($G86-(SUM($H86:$I86))),"") | R86: =IF($B86=710,SUM($G86-(SUM($H86:$I86))),"") | S86: =IF($B86=711,SUM($G86-(SUM($H86:$I86))),"") | T86: =IF($B86=712,SUM($G86-(SUM($H86:$I86))),"") | U86: =IF($B86=713,SUM($G86-(SUM($H86:$I86))),"") | V86: =IF($B86=715,SUM($G86-(SUM($H86:$I86))),"") | W86: =IF($B86=724,SUM($G86-(SUM($H86:$I86))),"") | X86: =IF($B86=725,SUM($G86-(SUM($H86:$I86))),"") | Y86: =IF($B86=726,SUM($G86-(SUM($H86:$I86))),"") | Z86: =IF($B86=727,SUM($G86-(SUM($H86:$I86))),"") | AA86: =IF($B86=728,SUM($G86-(SUM($H86:$I86))),"") | AB86: =IF($B86=729,SUM($G86-(SUM($H86:$I86))),"") | AC86: =IF($B86=730,SUM($G86-(SUM($H86:$I86))),"") | AD86: =IF($B86=732,SUM($G86-(SUM($H86:$I86))),"") | AE86: =IF($B86=733,SUM($G86-(SUM($H86:$I86))),"") | AF86: =IF($B86=734,SUM($G86-(SUM($H86:$I86))),"") | AG86: =IF($B86=705,SUM($G86-(SUM($H86:$I86))),"") | AH86: =IF($B86=735,SUM($G86-(SUM($H86:$I86))),"") | AI86: =IF($B86=736,SUM($G86-(SUM($H86:$I86))),"") | AJ86: =IF($B86=737,SUM($G86-(SUM($H86:$I86))),"") | AK86: =IF($B86=725,SUM($G86-(SUM($H86:$I86))),"") | AL86: =IF($B86=735,SUM($G86-(SUM($H86:$I86))),"") | AM86: =IF($B86=727,SUM($G86-(SUM($H86:$I86))),"") | AN86: =IF($B86=718,SUM($G86-(SUM($H86:$I86))),"") | AO86: =IF($B86=719,SUM($G86-(SUM($H86:$I86))),"") | AP86: =IF($B86=717,SUM($G86-(SUM($H86:$I86))),"") | AQ86: =IF($B86=722,SUM($G86-(SUM($H86:$I86))),"") | AR86: =IF($B86=708,SUM($G86-(SUM($H86:$I86))),"") | AS86: =IF($B86=701,SUM($G86-(SUM($H86:$I86))),"") | AT86: =IF($B86=702,SUM($G86-(SUM($H86:$I86))),"") | AU86: =IF($B86=731,SUM($G86-(SUM($H86:$I86))),"") | AV86: =IF($B86=730,SUM($G86-(SUM($H86:$I86))),"")
D87: =D86+G87 -> 0 | F87: =SUM(H87:AV87)-G87 -> 0 | H87: =IF(G87/23*3>0,SUM(G87/23*3),"") | I87: =IF(G87/23*3<0,SUM(G87/23*3),"") | J87: =IF($B87=707,SUM($G87-(SUM($H87:$I87))),"") | K87: =IF($B87=706,SUM($G87-(SUM($H87:$I87))),"") | L87: =IF($B87=703,SUM($G87-(SUM($H87:$I87))),"") | M87: =IF($B87=704,SUM($G87-(SUM($H87:$I87))),"") | N87: =IF($B87=709,SUM($G87-(SUM($H87:$I87))),"") | O87: =IF($B87=738,SUM($G87-(SUM($H87:$I87))),"") | P87: =IF($B87=739,SUM($G87-(SUM($H87:$I87))),"") | Q87: =IF($B87=714,SUM($G87-(SUM($H87:$I87))),"") | R87: =IF($B87=710,SUM($G87-(SUM($H87:$I87))),"") | S87: =IF($B87=711,SUM($G87-(SUM($H87:$I87))),"") | T87: =IF($B87=712,SUM($G87-(SUM($H87:$I87))),"") | U87: =IF($B87=713,SUM($G87-(SUM($H87:$I87))),"") | V87: =IF($B87=715,SUM($G87-(SUM($H87:$I87))),"") | W87: =IF($B87=724,SUM($G87-(SUM($H87:$I87))),"") | X87: =IF($B87=725,SUM($G87-(SUM($H87:$I87))),"") | Y87: =IF($B87=726,SUM($G87-(SUM($H87:$I87))),"") | Z87: =IF($B87=727,SUM($G87-(SUM($H87:$I87))),"") | AA87: =IF($B87=728,SUM($G87-(SUM($H87:$I87))),"") | AB87: =IF($B87=729,SUM($G87-(SUM($H87:$I87))),"") | AC87: =IF($B87=730,SUM($G87-(SUM($H87:$I87))),"") | AD87: =IF($B87=732,SUM($G87-(SUM($H87:$I87))),"") | AE87: =IF($B87=733,SUM($G87-(SUM($H87:$I87))),"") | AF87: =IF($B87=734,SUM($G87-(SUM($H87:$I87))),"") | AG87: =IF($B87=705,SUM($G87-(SUM($H87:$I87))),"") | AH87: =IF($B87=735,SUM($G87-(SUM($H87:$I87))),"") | AI87: =IF($B87=736,SUM($G87-(SUM($H87:$I87))),"") | AJ87: =IF($B87=737,SUM($G87-(SUM($H87:$I87))),"") | AK87: =IF($B87=725,SUM($G87-(SUM($H87:$I87))),"") | AL87: =IF($B87=735,SUM($G87-(SUM($H87:$I87))),"") | AM87: =IF($B87=727,SUM($G87-(SUM($H87:$I87))),"") | AN87: =IF($B87=718,SUM($G87-(SUM($H87:$I87))),"") | AO87: =IF($B87=719,SUM($G87-(SUM($H87:$I87))),"") | AP87: =IF($B87=717,SUM($G87-(SUM($H87:$I87))),"") | AQ87: =IF($B87=722,SUM($G87-(SUM($H87:$I87))),"") | AR87: =IF($B87=708,SUM($G87-(SUM($H87:$I87))),"") | AS87: =IF($B87=701,SUM($G87-(SUM($H87:$I87))),"") | AT87: =IF($B87=702,SUM($G87-(SUM($H87:$I87))),"") | AU87: =IF($B87=731,SUM($G87-(SUM($H87:$I87))),"") | AV87: =IF($B87=730,SUM($G87-(SUM($H87:$I87))),"")
B88: 707 | C88: Income - March - Client (50% progress payment received) | D88: =D87+G88 -> 0 | F88: =SUM(H88:AV88)-G88 -> 0 | G88: 0 | H88: =IF(G88/23*3>0,SUM(G88/23*3),"") | I88: =IF(G88/23*3<0,SUM(G88/23*3),"") | J88: =IF($B88=707,SUM($G88-(SUM($H88:$I88))),"") -> 0 | K88: =IF($B88=706,SUM($G88-(SUM($H88:$I88))),"") | L88: =IF($B88=703,SUM($G88-(SUM($H88:$I88))),"") | M88: =IF($B88=704,SUM($G88-(SUM($H88:$I88))),"") | N88: =IF($B88=709,SUM($G88-(SUM($H88:$I88))),"") | O88: =IF($B88=738,SUM($G88-(SUM($H88:$I88))),"") | P88: =IF($B88=739,SUM($G88-(SUM($H88:$I88))),"") | Q88: =IF($B88=714,SUM($G88-(SUM($H88:$I88))),"") | R88: =IF($B88=710,SUM($G88-(SUM($H88:$I88))),"") | S88: =IF($B88=711,SUM($G88-(SUM($H88:$I88))),"") | T88: =IF($B88=712,SUM($G88-(SUM($H88:$I88))),"") | U88: =IF($B88=713,SUM($G88-(SUM($H88:$I88))),"") | V88: =IF($B88=715,SUM($G88-(SUM($H88:$I88))),"") | W88: =IF($B88=724,SUM($G88-(SUM($H88:$I88))),"") | X88: =IF($B88=725,SUM($G88-(SUM($H88:$I88))),"") | Y88: =IF($B88=726,SUM($G88-(SUM($H88:$I88))),"") | Z88: =IF($B88=727,SUM($G88-(SUM($H88:$I88))),"") | AA88: =IF($B88=728,SUM($G88-(SUM($H88:$I88))),"") | AB88: =IF($B88=729,SUM($G88-(SUM($H88:$I88))),"") | AC88: =IF($B88=730,SUM($G88-(SUM($H88:$I88))),"") | AD88: =IF($B88=732,SUM($G88-(SUM($H88:$I88))),"") | AE88: =IF($B88=733,SUM($G88-(SUM($H88:$I88))),"") | AF88: =IF($B88=734,SUM($G88-(SUM($H88:$I88))),"") | AG88: =IF($B88=705,SUM($G88-(SUM($H88:$I88))),"") | AH88: =IF($B88=735,SUM($G88-(SUM($H88:$I88))),"") | AI88: =IF($B88=736,SUM($G88-(SUM($H88:$I88))),"") | AJ88: =IF($B88=737,SUM($G88-(SUM($H88:$I88))),"") | AK88: =IF($B88=725,SUM($G88-(SUM($H88:$I88))),"") | AL88: =IF($B88=735,SUM($G88-(SUM($H88:$I88))),"") | AM88: =IF($B88=727,SUM($G88-(SUM($H88:$I88))),"") | AN88: =IF($B88=718,SUM($G88-(SUM($H88:$I88))),"") | AO88: =IF($B88=719,SUM($G88-(SUM($H88:$I88))),"") | AP88: =IF($B88=717,SUM($G88-(SUM($H88:$I88))),"") | AQ88: =IF($B88=722,SUM($G88-(SUM($H88:$I88))),"") | AR88: =IF($B88=708,SUM($G88-(SUM($H88:$I88))),"") | AS88: =IF($B88=701,SUM($G88-(SUM($H88:$I88))),"") | AT88: =IF($B88=702,SUM($G88-(SUM($H88:$I88))),"") | AU88: =IF($B88=731,SUM($G88-(SUM($H88:$I88))),"") | AV88: =IF($B88=730,SUM($G88-(SUM($H88:$I88))),"")
B89: 725 | C89: Power - Fibrewave | D89: =D88+G89 -> 0 | F89: =SUM(H89:AV89)-G89 -> 0 | G89: 0 | H89: =IF(G89/23*3>0,SUM(G89/23*3),"") | I89: =IF(G89/23*3<0,SUM(G89/23*3),"") | J89: =IF($B89=707,SUM($G89-(SUM($H89:$I89))),"") | K89: =IF($B89=706,SUM($G89-(SUM($H89:$I89))),"") | L89: =IF($B89=703,SUM($G89-(SUM($H89:$I89))),"") | M89: =IF($B89=704,SUM($G89-(SUM($H89:$I89))),"") | N89: =IF($B89=709,SUM($G89-(SUM($H89:$I89))),"") | O89: =IF($B89=738,SUM($G89-(SUM($H89:$I89))),"") | P89: =IF($B89=739,SUM($G89-(SUM($H89:$I89))),"") | Q89: =IF($B89=714,SUM($G89-(SUM($H89:$I89))),"") | R89: =IF($B89=710,SUM($G89-(SUM($H89:$I89))),"") | S89: =IF($B89=711,SUM($G89-(SUM($H89:$I89))),"") | T89: =IF($B89=712,SUM($G89-(SUM($H89:$I89))),"") | U89: =IF($B89=713,SUM($G89-(SUM($H89:$I89))),"") | V89: =IF($B89=715,SUM($G89-(SUM($H89:$I89))),"") | W89: =IF($B89=724,SUM($G89-(SUM($H89:$I89))),"") | X89: =IF($B89=725,SUM($G89-(SUM($H89:$I89))),"") -> 0 | Y89: =IF($B89=726,SUM($G89-(SUM($H89:$I89))),"") | Z89: =IF($B89=727,SUM($G89-(SUM($H89:$I89))),"") | AA89: =IF($B89=728,SUM($G89-(SUM($H89:$I89))),"") | AB89: =IF($B89=729,SUM($G89-(SUM($H89:$I89))),"") | AC89: =IF($B89=730,SUM($G89-(SUM($H89:$I89))),"") | AD89: =IF($B89=732,SUM($G89-(SUM($H89:$I89))),"") | AE89: =IF($B89=733,SUM($G89-(SUM($H89:$I89))),"") | AF89: =IF($B89=734,SUM($G89-(SUM($H89:$I89))),"") | AG89: =IF($B89=705,SUM($G89-(SUM($H89:$I89))),"") | AH89: =IF($B89=735,SUM($G89-(SUM($H89:$I89))),"") | AI89: =IF($B89=736,SUM($G89-(SUM($H89:$I89))),"") | AJ89: =IF($B89=737,SUM($G89-(SUM($H89:$I89))),"") | AK89: =IF($B89=725,SUM($G89-(SUM($H89:$I89))),"") -> 0 | AL89: =IF($B89=735,SUM($G89-(SUM($H89:$I89))),"") | AM89: =IF($B89=727,SUM($G89-(SUM($H89:$I89))),"") | AN89: =IF($B89=718,SUM($G89-(SUM($H89:$I89))),"") | AO89: =IF($B89=719,SUM($G89-(SUM($H89:$I89))),"") | AP89: =IF($B89=717,SUM($G89-(SUM($H89:$I89))),"") | AQ89: =IF($B89=722,SUM($G89-(SUM($H89:$I89))),"") | AR89: =IF($B89=708,SUM($G89-(SUM($H89:$I89))),"") | AS89: =IF($B89=701,SUM($G89-(SUM($H89:$I89))),"") | AT89: =IF($B89=702,SUM($G89-(SUM($H89:$I89))),"") | AU89: =IF($B89=731,SUM($G89-(SUM($H89:$I89))),"") | AV89: =IF($B89=730,SUM($G89-(SUM($H89:$I89))),"")
B90: 726 | C90: Entertainment (Business Lunch/Coffee/Meals/Drinks) | D90: =D89+G90 -> 0 | F90: =SUM(H90:AV90)-G90 -> 0 | G90: =-(OtherCalculation!C10) -> 0 | H90: =IF(G90/23*3>0,SUM(G90/23*3),"") | I90: =IF(G90/23*3<0,SUM(G90/23*3),"") | J90: =IF($B90=707,SUM($G90-(SUM($H90:$I90))),"") | K90: =IF($B90=706,SUM($G90-(SUM($H90:$I90))),"") | L90: =IF($B90=703,SUM($G90-(SUM($H90:$I90))),"") | M90: =IF($B90=704,SUM($G90-(SUM($H90:$I90))),"") | N90: =IF($B90=709,SUM($G90-(SUM($H90:$I90))),"") | O90: =IF($B90=738,SUM($G90-(SUM($H90:$I90))),"") | P90: =IF($B90=739,SUM($G90-(SUM($H90:$I90))),"") | Q90: =IF($B90=714,SUM($G90-(SUM($H90:$I90))),"") | R90: =IF($B90=710,SUM($G90-(SUM($H90:$I90))),"") | S90: =IF($B90=711,SUM($G90-(SUM($H90:$I90))),"") | T90: =IF($B90=712,SUM($G90-(SUM($H90:$I90))),"") | U90: =IF($B90=713,SUM($G90-(SUM($H90:$I90))),"") | V90: =IF($B90=715,SUM($G90-(SUM($H90:$I90))),"") | W90: =IF($B90=724,SUM($G90-(SUM($H90:$I90))),"") | X90: =IF($B90=725,SUM($G90-(SUM($H90:$I90))),"") | Y90: =IF($B90=726,SUM($G90-(SUM($H90:$I90))),"") -> 0 | Z90: =IF($B90=727,SUM($G90-(SUM($H90:$I90))),"") | AA90: =IF($B90=728,SUM($G90-(SUM($H90:$I90))),"") | AB90: =IF($B90=729,SUM($G90-(SUM($H90:$I90))),"") | AC90: =IF($B90=730,SUM($G90-(SUM($H90:$I90))),"") | AD90: =IF($B90=732,SUM($G90-(SUM($H90:$I90))),"") | AE90: =IF($B90=733,SUM($G90-(SUM($H90:$I90))),"") | AF90: =IF($B90=734,SUM($G90-(SUM($H90:$I90))),"") | AG90: =IF($B90=705,SUM($G90-(SUM($H90:$I90))),"") | AH90: =IF($B90=735,SUM($G90-(SUM($H90:$I90))),"") | AI90: =IF($B90=736,SUM($G90-(SUM($H90:$I90))),"") | AJ90: =IF($B90=737,SUM($G90-(SUM($H90:$I90))),"") | AK90: =IF($B90=725,SUM($G90-(SUM($H90:$I90))),"") | AL90: =IF($B90=735,SUM($G90-(SUM($H90:$I90))),"") | AM90: =IF($B90=727,SUM($G90-(SUM($H90:$I90))),"") | AN90: =IF($B90=718,SUM($G90-(SUM($H90:$I90))),"") | AO90: =IF($B90=719,SUM($G90-(SUM($H90:$I90))),"") | AP90: =IF($B90=717,SUM($G90-(SUM($H90:$I90))),"") | AQ90: =IF($B90=722,SUM($G90-(SUM($H90:$I90))),"") | AR90: =IF($B90=708,SUM($G90-(SUM($H90:$I90))),"") | AS90: =IF($B90=701,SUM($G90-(SUM($H90:$I90))),"") | AT90: =IF($B90=702,SUM($G90-(SUM($H90:$I90))),"") | AU90: =IF($B90=731,SUM($G90-(SUM($H90:$I90))),"") | AV90: =IF($B90=730,SUM($G90-(SUM($H90:$I90))),"")
B91: 727 | C91: Internet - Fibrewave | D91: =D90+G91 -> 0 | F91: =SUM(H91:AV91)-G91 -> 0 | G91: 0 | H91: =IF(G91/23*3>0,SUM(G91/23*3),"") | I91: =IF(G91/23*3<0,SUM(G91/23*3),"") | J91: =IF($B91=707,SUM($G91-(SUM($H91:$I91))),"") | K91: =IF($B91=706,SUM($G91-(SUM($H91:$I91))),"") | L91: =IF($B91=703,SUM($G91-(SUM($H91:$I91))),"") | M91: =IF($B91=704,SUM($G91-(SUM($H91:$I91))),"") | N91: =IF($B91=709,SUM($G91-(SUM($H91:$I91))),"") | O91: =IF($B91=738,SUM($G91-(SUM($H91:$I91))),"") | P91: =IF($B91=739,SUM($G91-(SUM($H91:$I91))),"") | Q91: =IF($B91=714,SUM($G91-(SUM($H91:$I91))),"") | R91: =IF($B91=710,SUM($G91-(SUM($H91:$I91))),"") | S91: =IF($B91=711,SUM($G91-(SUM($H91:$I91))),"") | T91: =IF($B91=712,SUM($G91-(SUM($H91:$I91))),"") | U91: =IF($B91=713,SUM($G91-(SUM($H91:$I91))),"") | V91: =IF($B91=715,SUM($G91-(SUM($H91:$I91))),"") | W91: =IF($B91=724,SUM($G91-(SUM($H91:$I91))),"") | X91: =IF($B91=725,SUM($G91-(SUM($H91:$I91))),"") | Y91: =IF($B91=726,SUM($G91-(SUM($H91:$I91))),"") | Z91: =IF($B91=727,SUM($G91-(SUM($H91:$I91))),"") -> 0 | AA91: =IF($B91=728,SUM($G91-(SUM($H91:$I91))),"") | AB91: =IF($B91=729,SUM($G91-(SUM($H91:$I91))),"") | AC91: =IF($B91=730,SUM($G91-(SUM($H91:$I91))),"") | AD91: =IF($B91=732,SUM($G91-(SUM($H91:$I91))),"") | AE91: =IF($B91=733,SUM($G91-(SUM($H91:$I91))),"") | AF91: =IF($B91=734,SUM($G91-(SUM($H91:$I91))),"") | AG91: =IF($B91=705,SUM($G91-(SUM($H91:$I91))),"") | AH91: =IF($B91=735,SUM($G91-(SUM($H91:$I91))),"") | AI91: =IF($B91=736,SUM($G91-(SUM($H91:$I91))),"") | AJ91: =IF($B91=737,SUM($G91-(SUM($H91:$I91))),"") | AK91: =IF($B91=725,SUM($G91-(SUM($H91:$I91))),"") | AL91: =IF($B91=735,SUM($G91-(SUM($H91:$I91))),"") | AM91: =IF($B91=727,SUM($G91-(SUM($H91:$I91))),"") -> 0 | AN91: =IF($B91=718,SUM($G91-(SUM($H91:$I91))),"") | AO91: =IF($B91=719,SUM($G91-(SUM($H91:$I91))),"") | AP91: =IF($B91=717,SUM($G91-(SUM($H91:$I91))),"") | AQ91: =IF($B91=722,SUM($G91-(SUM($H91:$I91))),"") | AR91: =IF($B91=708,SUM($G91-(SUM($H91:$I91))),"") | AS91: =IF($B91=701,SUM($G91-(SUM($H91:$I91))),"") | AT91: =IF($B91=702,SUM($G91-(SUM($H91:$I91))),"") | AU91: =IF($B91=731,SUM($G91-(SUM($H91:$I91))),"") | AV91: =IF($B91=730,SUM($G91-(SUM($H91:$I91))),"")
B92: 728 | C92: Mobile Plan - Tui Mobile NZ | D92: =D91+G92 -> 0 | F92: =SUM(H92:AV92)-G92 -> 0 | G92: 0 | H92: =IF(G92/23*3>0,SUM(G92/23*3),"") | I92: =IF(G92/23*3<0,SUM(G92/23*3),"") | J92: =IF($B92=707,SUM($G92-(SUM($H92:$I92))),"") | K92: =IF($B92=706,SUM($G92-(SUM($H92:$I92))),"") | L92: =IF($B92=703,SUM($G92-(SUM($H92:$I92))),"") | M92: =IF($B92=704,SUM($G92-(SUM($H92:$I92))),"") | N92: =IF($B92=709,SUM($G92-(SUM($H92:$I92))),"") | O92: =IF($B92=738,SUM($G92-(SUM($H92:$I92))),"") | P92: =IF($B92=739,SUM($G92-(SUM($H92:$I92))),"") | Q92: =IF($B92=714,SUM($G92-(SUM($H92:$I92))),"") | R92: =IF($B92=710,SUM($G92-(SUM($H92:$I92))),"") | S92: =IF($B92=711,SUM($G92-(SUM($H92:$I92))),"") | T92: =IF($B92=712,SUM($G92-(SUM($H92:$I92))),"") | U92: =IF($B92=713,SUM($G92-(SUM($H92:$I92))),"") | V92: =IF($B92=715,SUM($G92-(SUM($H92:$I92))),"") | W92: =IF($B92=724,SUM($G92-(SUM($H92:$I92))),"") | X92: =IF($B92=725,SUM($G92-(SUM($H92:$I92))),"") | Y92: =IF($B92=726,SUM($G92-(SUM($H92:$I92))),"") | Z92: =IF($B92=727,SUM($G92-(SUM($H92:$I92))),"") | AA92: =IF($B92=728,SUM($G92-(SUM($H92:$I92))),"") -> 0 | AB92: =IF($B92=729,SUM($G92-(SUM($H92:$I92))),"") | AC92: =IF($B92=730,SUM($G92-(SUM($H92:$I92))),"") | AD92: =IF($B92=732,SUM($G92-(SUM($H92:$I92))),"") | AE92: =IF($B92=733,SUM($G92-(SUM($H92:$I92))),"") | AF92: =IF($B92=734,SUM($G92-(SUM($H92:$I92))),"") | AG92: =IF($B92=705,SUM($G92-(SUM($H92:$I92))),"") | AH92: =IF($B92=735,SUM($G92-(SUM($H92:$I92))),"") | AI92: =IF($B92=736,SUM($G92-(SUM($H92:$I92))),"") | AJ92: =IF($B92=737,SUM($G92-(SUM($H92:$I92))),"") | AK92: =IF($B92=725,SUM($G92-(SUM($H92:$I92))),"") | AL92: =IF($B92=735,SUM($G92-(SUM($H92:$I92))),"") | AM92: =IF($B92=727,SUM($G92-(SUM($H92:$I92))),"") | AN92: =IF($B92=718,SUM($G92-(SUM($H92:$I92))),"") | AO92: =IF($B92=719,SUM($G92-(SUM($H92:$I92))),"") | AP92: =IF($B92=717,SUM($G92-(SUM($H92:$I92))),"") | AQ92: =IF($B92=722,SUM($G92-(SUM($H92:$I92))),"") | AR92: =IF($B92=708,SUM($G92-(SUM($H92:$I92))),"") | AS92: =IF($B92=701,SUM($G92-(SUM($H92:$I92))),"") | AT92: =IF($B92=702,SUM($G92-(SUM($H92:$I92))),"") | AU92: =IF($B92=731,SUM($G92-(SUM($H92:$I92))),"") | AV92: =IF($B92=730,SUM($G92-(SUM($H92:$I92))),"")
B93: 729 | C93: Car Park Fees | D93: =D92+G93 -> 0 | F93: =SUM(H93:AV93)-G93 -> 0 | G93: 0 | H93: =IF(G93/23*3>0,SUM(G93/23*3),"") | I93: =IF(G93/23*3<0,SUM(G93/23*3),"") | J93: =IF($B93=707,SUM($G93-(SUM($H93:$I93))),"") | K93: =IF($B93=706,SUM($G93-(SUM($H93:$I93))),"") | L93: =IF($B93=703,SUM($G93-(SUM($H93:$I93))),"") | M93: =IF($B93=704,SUM($G93-(SUM($H93:$I93))),"") | N93: =IF($B93=709,SUM($G93-(SUM($H93:$I93))),"") | O93: =IF($B93=738,SUM($G93-(SUM($H93:$I93))),"") | P93: =IF($B93=739,SUM($G93-(SUM($H93:$I93))),"") | Q93: =IF($B93=714,SUM($G93-(SUM($H93:$I93))),"") | R93: =IF($B93=710,SUM($G93-(SUM($H93:$I93))),"") | S93: =IF($B93=711,SUM($G93-(SUM($H93:$I93))),"") | T93: =IF($B93=712,SUM($G93-(SUM($H93:$I93))),"") | U93: =IF($B93=713,SUM($G93-(SUM($H93:$I93))),"") | V93: =IF($B93=715,SUM($G93-(SUM($H93:$I93))),"") | W93: =IF($B93=724,SUM($G93-(SUM($H93:$I93))),"") | X93: =IF($B93=725,SUM($G93-(SUM($H93:$I93))),"") | Y93: =IF($B93=726,SUM($G93-(SUM($H93:$I93))),"") | Z93: =IF($B93=727,SUM($G93-(SUM($H93:$I93))),"") | AA93: =IF($B93=728,SUM($G93-(SUM($H93:$I93))),"") | AB93: =IF($B93=729,SUM($G93-(SUM($H93:$I93))),"") -> 0 | AC93: =IF($B93=730,SUM($G93-(SUM($H93:$I93))),"") | AD93: =IF($B93=732,SUM($G93-(SUM($H93:$I93))),"") | AE93: =IF($B93=733,SUM($G93-(SUM($H93:$I93))),"") | AF93: =IF($B93=734,SUM($G93-(SUM($H93:$I93))),"") | AG93: =IF($B93=705,SUM($G93-(SUM($H93:$I93))),"") | AH93: =IF($B93=735,SUM($G93-(SUM($H93:$I93))),"") | AI93: =IF($B93=736,SUM($G93-(SUM($H93:$I93))),"") | AJ93: =IF($B93=737,SUM($G93-(SUM($H93:$I93))),"") | AK93: =IF($B93=725,SUM($G93-(SUM($H93:$I93))),"") | AL93: =IF($B93=735,SUM($G93-(SUM($H93:$I93))),"") | AM93: =IF($B93=727,SUM($G93-(SUM($H93:$I93))),"") | AN93: =IF($B93=718,SUM($G93-(SUM($H93:$I93))),"") | AO93: =IF($B93=719,SUM($G93-(SUM($H93:$I93))),"") | AP93: =IF($B93=717,SUM($G93-(SUM($H93:$I93))),"") | AQ93: =IF($B93=722,SUM($G93-(SUM($H93:$I93))),"") | AR93: =IF($B93=708,SUM($G93-(SUM($H93:$I93))),"") | AS93: =IF($B93=701,SUM($G93-(SUM($H93:$I93))),"") | AT93: =IF($B93=702,SUM($G93-(SUM($H93:$I93))),"") | AU93: =IF($B93=731,SUM($G93-(SUM($H93:$I93))),"") | AV93: =IF($B93=730,SUM($G93-(SUM($H93:$I93))),"")
B94: 734 | C94: Home Office Expenses | D94: =D93+G94 -> 0 | F94: =SUM(H94:AV94)-G94 -> 0 | G94: 0 | H94: =IF(G94/23*3>0,SUM(G94/23*3),"") | I94: =IF(G94/23*3<0,SUM(G94/23*3),"") | J94: =IF($B94=707,SUM($G94-(SUM($H94:$I94))),"") | K94: =IF($B94=706,SUM($G94-(SUM($H94:$I94))),"") | L94: =IF($B94=703,SUM($G94-(SUM($H94:$I94))),"") | M94: =IF($B94=704,SUM($G94-(SUM($H94:$I94))),"") | N94: =IF($B94=709,SUM($G94-(SUM($H94:$I94))),"") | O94: =IF($B94=738,SUM($G94-(SUM($H94:$I94))),"") | P94: =IF($B94=739,SUM($G94-(SUM($H94:$I94))),"") | Q94: =IF($B94=714,SUM($G94-(SUM($H94:$I94))),"") | R94: =IF($B94=710,SUM($G94-(SUM($H94:$I94))),"") | S94: =IF($B94=711,SUM($G94-(SUM($H94:$I94))),"") | T94: =IF($B94=712,SUM($G94-(SUM($H94:$I94))),"") | U94: =IF($B94=713,SUM($G94-(SUM($H94:$I94))),"") | V94: =IF($B94=715,SUM($G94-(SUM($H94:$I94))),"") | W94: =IF($B94=724,SUM($G94-(SUM($H94:$I94))),"") | X94: =IF($B94=725,SUM($G94-(SUM($H94:$I94))),"") | Y94: =IF($B94=726,SUM($G94-(SUM($H94:$I94))),"") | Z94: =IF($B94=727,SUM($G94-(SUM($H94:$I94))),"") | AA94: =IF($B94=728,SUM($G94-(SUM($H94:$I94))),"") | AB94: =IF($B94=729,SUM($G94-(SUM($H94:$I94))),"") | AC94: =IF($B94=730,SUM($G94-(SUM($H94:$I94))),"") | AD94: =IF($B94=732,SUM($G94-(SUM($H94:$I94))),"") | AE94: =IF($B94=733,SUM($G94-(SUM($H94:$I94))),"") | AF94: =IF($B94=734,SUM($G94-(SUM($H94:$I94))),"") -> 0 | AG94: =IF($B94=705,SUM($G94-(SUM($H94:$I94))),"") | AH94: =IF($B94=735,SUM($G94-(SUM($H94:$I94))),"") | AI94: =IF($B94=736,SUM($G94-(SUM($H94:$I94))),"") | AJ94: =IF($B94=737,SUM($G94-(SUM($H94:$I94))),"") | AK94: =IF($B94=725,SUM($G94-(SUM($H94:$I94))),"") | AL94: =IF($B94=735,SUM($G94-(SUM($H94:$I94))),"") | AM94: =IF($B94=727,SUM($G94-(SUM($H94:$I94))),"") | AN94: =IF($B94=718,SUM($G94-(SUM($H94:$I94))),"") | AO94: =IF($B94=719,SUM($G94-(SUM($H94:$I94))),"") | AP94: =IF($B94=717,SUM($G94-(SUM($H94:$I94))),"") | AQ94: =IF($B94=722,SUM($G94-(SUM($H94:$I94))),"") | AR94: =IF($B94=708,SUM($G94-(SUM($H94:$I94))),"") | AS94: =IF($B94=701,SUM($G94-(SUM($H94:$I94))),"") | AT94: =IF($B94=702,SUM($G94-(SUM($H94:$I94))),"") | AU94: =IF($B94=731,SUM($G94-(SUM($H94:$I94))),"") | AV94: =IF($B94=730,SUM($G94-(SUM($H94:$I94))),"")
B95: 724 | C95: Apartment Rent | D95: =D94+G95 -> 0 | F95: =SUM(H95:AV95)-G95 -> 0 | G95: =-(OtherCalculation!C15) -> 0 | H95: =IF(G95/23*3>0,SUM(G95/23*3),"") | J95: =IF($B95=707,SUM($G95-(SUM($H95:$I95))),"") | K95: =IF($B95=706,SUM($G95-(SUM($H95:$I95))),"") | L95: =IF($B95=703,SUM($G95-(SUM($H95:$I95))),"") | M95: =IF($B95=704,SUM($G95-(SUM($H95:$I95))),"") | N95: =IF($B95=709,SUM($G95-(SUM($H95:$I95))),"") | O95: =IF($B95=738,SUM($G95-(SUM($H95:$I95))),"") | P95: =IF($B95=739,SUM($G95-(SUM($H95:$I95))),"") | Q95: =IF($B95=714,SUM($G95-(SUM($H95:$I95))),"") | R95: =IF($B95=710,SUM($G95-(SUM($H95:$I95))),"") | S95: =IF($B95=711,SUM($G95-(SUM($H95:$I95))),"") | T95: =IF($B95=712,SUM($G95-(SUM($H95:$I95))),"") | U95: =IF($B95=713,SUM($G95-(SUM($H95:$I95))),"") | V95: =IF($B95=715,SUM($G95-(SUM($H95:$I95))),"") | W95: =IF($B95=724,SUM($G95-(SUM($H95:$I95))),"") -> 0 | X95: =IF($B95=725,SUM($G95-(SUM($H95:$I95))),"") | Y95: =IF($B95=726,SUM($G95-(SUM($H95:$I95))),"") | Z95: =IF($B95=727,SUM($G95-(SUM($H95:$I95))),"") | AA95: =IF($B95=728,SUM($G95-(SUM($H95:$I95))),"") | AB95: =IF($B95=729,SUM($G95-(SUM($H95:$I95))),"") | AC95: =IF($B95=730,SUM($G95-(SUM($H95:$I95))),"") | AD95: =IF($B95=732,SUM($G95-(SUM($H95:$I95))),"") | AE95: =IF($B95=733,SUM($G95-(SUM($H95:$I95))),"") | AF95: =IF($B95=734,SUM($G95-(SUM($H95:$I95))),"") | AG95: =IF($B95=705,SUM($G95-(SUM($H95:$I95))),"") | AH95: =IF($B95=735,SUM($G95-(SUM($H95:$I95))),"") | AI95: =IF($B95=736,SUM($G95-(SUM($H95:$I95))),"") | AJ95: =IF($B95=737,SUM($G95-(SUM($H95:$I95))),"") | AK95: =IF($B95=725,SUM($G95-(SUM($H95:$I95))),"") | AL95: =IF($B95=735,SUM($G95-(SUM($H95:$I95))),"") | AM95: =IF($B95=727,SUM($G95-(SUM($H95:$I95))),"") | AN95: =IF($B95=718,SUM($G95-(SUM($H95:$I95))),"") | AO95: =IF($B95=719,SUM($G95-(SUM($H95:$I95))),"") | AP95: =IF($B95=717,SUM($G95-(SUM($H95:$I95))),"") | AQ95: =IF($B95=722,SUM($G95-(SUM($H95:$I95))),"") | AR95: =IF($B95=708,SUM($G95-(SUM($H95:$I95))),"") | AS95: =IF($B95=701,SUM($G95-(SUM($H95:$I95))),"") | AT95: =IF($B95=702,SUM($G95-(SUM($H95:$I95))),"") | AU95: =IF($B95=731,SUM($G95-(SUM($H95:$I95))),"") | AV95: =IF($B95=730,SUM($G95-(SUM($H95:$I95))),"")
